Workbook

Sheet Inputs
A1: RETIREMENT PLANNING MODEL — INPUTS
A2: Blue = your inputs (change these) | Black = formulas | Orange rows = RMD years
A3: YOUR DETAILS | D3: WIFE DETAILS
A4: Your Current Age | B4: 56 | D4: Wife Current Age | E4: 51
A5: Retirement Age | B5: 65 | D5: Wife Retirement Age | E5: 65
A6: Life Expectancy | B6: 85 | D6: Wife Salary ($) | E6: 0
A7: State of Residence (abbr) | B7: NJ | D7: Wife 401k Balance ($) | E7: 0
A8: Current Salary ($) | B8: 300000 | D8: Wife 401k Contribution ($/yr) | E8: 0
A9: Trad. 401k Balance ($) | B9: 3000000 | D9: Wife Match Rate (%) | E9: 0
A10: Roth 401k Balance ($) | B10: 500000 | D10: Wife Trad IRA ($) | E10: 50000
A11: Your 401k Contribution ($/yr) | B11: 37500 | D11: Wife Roth IRA ($) | E11: 10000
A12: Company Match Rate (%) | B12: 0.05
A13: Roth IRA — Your ($) | B13: 250000
A14: HSA Balance ($) | B14: 100000
A15: HSA 2025 Contribution ($/yr) | B15: 8000
A16: Brokerage Account ($) | B16: 500000
A18: GROWTH & SOCIAL SECURITY
A19: Investment Growth Rate (%) | B19: 0.08
A20: Inflation Rate (%) | B20: 0.03
A21: SS COLA Rate (%) | B21: 0.025
A22: SS Monthly @ Age 65 ($) | B22: 3330
A23: SS Monthly @ Age 67 ($) | B23: 3972
A24: SS Monthly @ Age 70 ($) | B24: 5200
A25: SS Start Age (65/67/70) | B25: 67
A26: Wife SS Start Age | B26: 65
A28: EXPENSES
A29: Monthly Living Expenses ($) | B29: 7000
A30: Mortgage Monthly ($) | B30: 3000
A31: Property Tax Annual ($) | B31: 15000
A32: Home Insurance Annual ($) | B32: 1500
A33: Medicare Part B / mo ($) | B33: 185
A34: Medicare Inflation Rate (%) | B34: 0.05
A35: Wife Private Ins / mo ($) pre-65 | B35: 800
A36: Home Value ($) | B36: 800000
A37: Annual Gift to Children ($) | B37: 0
A38: Gift Start Age | B38: 70
A40: TAX & CONVERSION STRATEGY
A41: Roth Conv. Target ($/yr) | B41: 201050
A42: Federal Std. Deduction ($) | B42: 30000
A43: SS Taxable Portion (%) | B43: 0.85
A44: RMD Start Age | B44: 73
A45: Long-Term Cap Gains Rate (%) | B45: 0.15
A47: MORTGAGE & HOME
A48: Mortgage Years Remaining (today) | B48: 22
A49: Mortgage Interest Rate (decimal, e.g. 0.065) | B49: 0.065
A50: Mortgage Balance at Retirement ($) [auto-calc, override if needed] | B50: =IFERROR(IF(B49>0,ROUND(MAX(0,B30*(1-POWER(1+B49/12,-MAX(0,B48*12-(B5-B4)*12)))/(B49/12)),0),B30*MAX(0,B48*12-(B5-B4)*12)),0) -> 315394
A51: Pay Off Mortgage at Retirement (1 = Yes, 0 = No) | B51: 0
A52: Home Appreciation Rate (%/yr, decimal) — NJ default 0.045 | B52: 0.045
A53: Note: Mortgage balance is auto-calculated from monthly payment, years remaining & rate. Common state rates: NJ 4.5%, WA 6.0%, CA 5.5%, TX 3.5%, FL 4.0%

Sheet Roth Conversion
A1: ROTH CONVERSION PLAN (Ages 65–85)
A2: Age | B2: Trad 401k Start ($) | C2: SS Income ($) | D2: Taxable Pre- Conv ($) | E2: Roth Conv ($) | F2: Total Taxable ($) | G2: Fed Tax ($) | H2: Eff Rate | I2: IRMAA Tier | J2: Trad 401k End ($)
A3: 65 | B3: =Inputs!B9 -> 3000000 | C3: =IF(65>=Inputs!B25,IF(Inputs!B25=65,Inputs!B22*12,IF(Inputs!B25=70,Inputs!B24*12,Inputs!B23*12))*(1+Inputs!B21)^MAX(0,65-Inputs!B25),0) -> 0 | D3: =C3*Inputs!B43 -> 0 | E3: =MAX(0,Inputs!B41-D3-Inputs!B42) -> 171050 | F3: =D3+E3 -> 171050 | G3: =MAX(0,IF(F3<=23200,F3*0.1,IF(F3<=94300,23200*0.1+(F3-23200)*0.12,IF(F3<=201050,23200*0.1+71100*0.12+(F3-94300)*0.22,IF(F3<=383900,23200*0.1+71100*0.12+106750*0.22+(F3-201050)*0.24,23200*0.1+71100*0.12+106750*0.22+182850*0.24+(F3-383900)*0.32))))) -> 27737 | H3: =IFERROR(G3/F3,0) -> 0.16215726 | I3: =IF(F3<=206000,"Tier 0 — $0/yr",IF(F3<=258000,"Tier 1 — $594/yr",IF(F3<=322000,"Tier 2 — $1,494/yr",IF(F3<=386000,"Tier 3 — $2,394/yr",IF(F3<=750000,"Tier 4 — $3,270/yr","Tier 5 — $3,564/yr"))))) -> Tier 0 — $0/yr | J3: =MAX(0,B3-E3) -> 2828950
A4: 66 | B4: =J3 -> 2828950 | C4: =IF(66>=Inputs!B25,IF(Inputs!B25=65,Inputs!B22*12,IF(Inputs!B25=70,Inputs!B24*12,Inputs!B23*12))*(1+Inputs!B21)^MAX(0,66-Inputs!B25),0) -> 0 | D4: =C4*Inputs!B43 -> 0 | E4: =MAX(0,Inputs!B41-D4-Inputs!B42) -> 171050 | F4: =D4+E4 -> 171050 | G4: =MAX(0,IF(F4<=23200,F4*0.1,IF(F4<=94300,23200*0.1+(F4-23200)*0.12,IF(F4<=201050,23200*0.1+71100*0.12+(F4-94300)*0.22,IF(F4<=383900,23200*0.1+71100*0.12+106750*0.22+(F4-201050)*0.24,23200*0.1+71100*0.12+106750*0.22+182850*0.24+(F4-383900)*0.32))))) -> 27737 | H4: =IFERROR(G4/F4,0) -> 0.16215726 | I4: =IF(F4<=206000,"Tier 0 — $0/yr",IF(F4<=258000,"Tier 1 — $594/yr",IF(F4<=322000,"Tier 2 — $1,494/yr",IF(F4<=386000,"Tier 3 — $2,394/yr",IF(F4<=750000,"Tier 4 — $3,270/yr","Tier 5 — $3,564/yr"))))) -> Tier 0 — $0/yr | J4: =MAX(0,B4-E4) -> 2657900
A5: 67 | B5: =J4 -> 2657900 | C5: =IF(67>=Inputs!B25,IF(Inputs!B25=65,Inputs!B22*12,IF(Inputs!B25=70,Inputs!B24*12,Inputs!B23*12))*(1+Inputs!B21)^MAX(0,67-Inputs!B25),0) -> 47664 | D5: =C5*Inputs!B43 -> 40514.4 | E5: =MAX(0,Inputs!B41-D5-Inputs!B42) -> 130535.6 | F5: =D5+E5 -> 171050 | G5: =MAX(0,IF(F5<=23200,F5*0.1,IF(F5<=94300,23200*0.1+(F5-23200)*0.12,IF(F5<=201050,23200*0.1+71100*0.12+(F5-94300)*0.22,IF(F5<=383900,23200*0.1+71100*0.12+106750*0.22+(F5-201050)*0.24,23200*0.1+71100*0.12+106750*0.22+182850*0.24+(F5-383900)*0.32))))) -> 27737 | H5: =IFERROR(G5/F5,0) -> 0.16215726 | I5: =IF(F5<=206000,"Tier 0 — $0/yr",IF(F5<=258000,"Tier 1 — $594/yr",IF(F5<=322000,"Tier 2 — $1,494/yr",IF(F5<=386000,"Tier 3 — $2,394/yr",IF(F5<=750000,"Tier 4 — $3,270/yr","Tier 5 — $3,564/yr"))))) -> Tier 0 — $0/yr | J5: =MAX(0,B5-E5) -> 2527364.4
A6: 68 | B6: =J5 -> 2527364.4 | C6: =IF(68>=Inputs!B25,IF(Inputs!B25=65,Inputs!B22*12,IF(Inputs!B25=70,Inputs!B24*12,Inputs!B23*12))*(1+Inputs!B21)^MAX(0,68-Inputs!B25),0) -> 48855.6 | D6: =C6*Inputs!B43 -> 41527.26 | E6: =MAX(0,Inputs!B41-D6-Inputs!B42) -> 129522.74 | F6: =D6+E6 -> 171050 | G6: =MAX(0,IF(F6<=23200,F6*0.1,IF(F6<=94300,23200*0.1+(F6-23200)*0.12,IF(F6<=201050,23200*0.1+71100*0.12+(F6-94300)*0.22,IF(F6<=383900,23200*0.1+71100*0.12+106750*0.22+(F6-201050)*0.24,23200*0.1+71100*0.12+106750*0.22+182850*0.24+(F6-383900)*0.32))))) -> 27737 | H6: =IFERROR(G6/F6,0) -> 0.16215726 | I6: =IF(F6<=206000,"Tier 0 — $0/yr",IF(F6<=258000,"Tier 1 — $594/yr",IF(F6<=322000,"Tier 2 — $1,494/yr",IF(F6<=386000,"Tier 3 — $2,394/yr",IF(F6<=750000,"Tier 4 — $3,270/yr","Tier 5 — $3,564/yr"))))) -> Tier 0 — $0/yr | J6: =MAX(0,B6-E6) -> 2397841.7
A7: 69 | B7: =J6 -> 2397841.7 | C7: =IF(69>=Inputs!B25,IF(Inputs!B25=65,Inputs!B22*12,IF(Inputs!B25=70,Inputs!B24*12,Inputs!B23*12))*(1+Inputs!B21)^MAX(0,69-Inputs!B25),0) -> 50076.99 | D7: =C7*Inputs!B43 -> 42565.442 | E7: =MAX(0,Inputs!B41-D7-Inputs!B42) -> 128484.56 | F7: =D7+E7 -> 171050 | G7: =MAX(0,IF(F7<=23200,F7*0.1,IF(F7<=94300,23200*0.1+(F7-23200)*0.12,IF(F7<=201050,23200*0.1+71100*0.12+(F7-94300)*0.22,IF(F7<=383900,23200*0.1+71100*0.12+106750*0.22+(F7-201050)*0.24,23200*0.1+71100*0.12+106750*0.22+182850*0.24+(F7-383900)*0.32))))) -> 27737 | H7: =IFERROR(G7/F7,0) -> 0.16215726 | I7: =IF(F7<=206000,"Tier 0 — $0/yr",IF(F7<=258000,"Tier 1 — $594/yr",IF(F7<=322000,"Tier 2 — $1,494/yr",IF(F7<=386000,"Tier 3 — $2,394/yr",IF(F7<=750000,"Tier 4 — $3,270/yr","Tier 5 — $3,564/yr"))))) -> Tier 0 — $0/yr | J7: =MAX(0,B7-E7) -> 2269357.1
A8: 70 | B8: =J7 -> 2269357.1 | C8: =IF(70>=Inputs!B25,IF(Inputs!B25=65,Inputs!B22*12,IF(Inputs!B25=70,Inputs!B24*12,Inputs!B23*12))*(1+Inputs!B21)^MAX(0,70-Inputs!B25),0) -> 51328.915 | D8: =C8*Inputs!B43 -> 43629.578 | E8: =MAX(0,Inputs!B41-D8-Inputs!B42) -> 127420.42 | F8: =D8+E8 -> 171050 | G8: =MAX(0,IF(F8<=23200,F8*0.1,IF(F8<=94300,23200*0.1+(F8-23200)*0.12,IF(F8<=201050,23200*0.1+71100*0.12+(F8-94300)*0.22,IF(F8<=383900,23200*0.1+71100*0.12+106750*0.22+(F8-201050)*0.24,23200*0.1+71100*0.12+106750*0.22+182850*0.24+(F8-383900)*0.32))))) -> 27737 | H8: =IFERROR(G8/F8,0) -> 0.16215726 | I8: =IF(F8<=206000,"Tier 0 — $0/yr",IF(F8<=258000,"Tier 1 — $594/yr",IF(F8<=322000,"Tier 2 — $1,494/yr",IF(F8<=386000,"Tier 3 — $2,394/yr",IF(F8<=750000,"Tier 4 — $3,270/yr","Tier 5 — $3,564/yr"))))) -> Tier 0 — $0/yr | J8: =MAX(0,B8-E8) -> 2141936.7
A9: 71 | B9: =J8 -> 2141936.7 | C9: =IF(71>=Inputs!B25,IF(Inputs!B25=65,Inputs!B22*12,IF(Inputs!B25=70,Inputs!B24*12,Inputs!B23*12))*(1+Inputs!B21)^MAX(0,71-Inputs!B25),0) -> 52612.138 | D9: =C9*Inputs!B43 -> 44720.317 | E9: =MAX(0,Inputs!B41-D9-Inputs!B42) -> 126329.68 | F9: =D9+E9 -> 171050 | G9: =MAX(0,IF(F9<=23200,F9*0.1,IF(F9<=94300,23200*0.1+(F9-23200)*0.12,IF(F9<=201050,23200*0.1+71100*0.12+(F9-94300)*0.22,IF(F9<=383900,23200*0.1+71100*0.12+106750*0.22+(F9-201050)*0.24,23200*0.1+71100*0.12+106750*0.22+182850*0.24+(F9-383900)*0.32))))) -> 27737 | H9: =IFERROR(G9/F9,0) -> 0.16215726 | I9: =IF(F9<=206000,"Tier 0 — $0/yr",IF(F9<=258000,"Tier 1 — $594/yr",IF(F9<=322000,"Tier 2 — $1,494/yr",IF(F9<=386000,"Tier 3 — $2,394/yr",IF(F9<=750000,"Tier 4 — $3,270/yr","Tier 5 — $3,564/yr"))))) -> Tier 0 — $0/yr | J9: =MAX(0,B9-E9) -> 2015607
A10: 72 | B10: =J9 -> 2015607 | C10: =IF(72>=Inputs!B25,IF(Inputs!B25=65,Inputs!B22*12,IF(Inputs!B25=70,Inputs!B24*12,Inputs!B23*12))*(1+Inputs!B21)^MAX(0,72-Inputs!B25),0) -> 53927.441 | D10: =C10*Inputs!B43 -> 45838.325 | E10: =MAX(0,Inputs!B41-D10-Inputs!B42) -> 125211.68 | F10: =D10+E10 -> 171050 | G10: =MAX(0,IF(F10<=23200,F10*0.1,IF(F10<=94300,23200*0.1+(F10-23200)*0.12,IF(F10<=201050,23200*0.1+71100*0.12+(F10-94300)*0.22,IF(F10<=383900,23200*0.1+71100*0.12+106750*0.22+(F10-201050)*0.24,23200*0.1+71100*0.12+106750*0.22+182850*0.24+(F10-383900)*0.32))))) -> 27737 | H10: =IFERROR(G10/F10,0) -> 0.16215726 | I10: =IF(F10<=206000,"Tier 0 — $0/yr",IF(F10<=258000,"Tier 1 — $594/yr",IF(F10<=322000,"Tier 2 — $1,494/yr",IF(F10<=386000,"Tier 3 — $2,394/yr",IF(F10<=750000,"Tier 4 — $3,270/yr","Tier 5 — $3,564/yr"))))) -> Tier 0 — $0/yr | J10: =MAX(0,B10-E10) -> 1890395.3
A11: 73 | B11: =J10 -> 1890395.3 | C11: =IF(73>=Inputs!B25,IF(Inputs!B25=65,Inputs!B22*12,IF(Inputs!B25=70,Inputs!B24*12,Inputs!B23*12))*(1+Inputs!B21)^MAX(0,73-Inputs!B25),0) -> 55275.627 | D11: =C11*Inputs!B43 -> 46984.283 | E11: =MAX(0,Inputs!B41-D11-Inputs!B42) -> 124065.72 | F11: =D11+E11 -> 171050 | G11: =MAX(0,IF(F11<=23200,F11*0.1,IF(F11<=94300,23200*0.1+(F11-23200)*0.12,IF(F11<=201050,23200*0.1+71100*0.12+(F11-94300)*0.22,IF(F11<=383900,23200*0.1+71100*0.12+106750*0.22+(F11-201050)*0.24,23200*0.1+71100*0.12+106750*0.22+182850*0.24+(F11-383900)*0.32))))) -> 27737 | H11: =IFERROR(G11/F11,0) -> 0.16215726 | I11: =IF(F11<=206000,"Tier 0 — $0/yr",IF(F11<=258000,"Tier 1 — $594/yr",IF(F11<=322000,"Tier 2 — $1,494/yr",IF(F11<=386000,"Tier 3 — $2,394/yr",IF(F11<=750000,"Tier 4 — $3,270/yr","Tier 5 — $3,564/yr"))))) -> Tier 0 — $0/yr | J11: =MAX(0,B11-E11) -> 1766329.6
A12: 74 | B12: =J11 -> 1766329.6 | C12: =IF(74>=Inputs!B25,IF(Inputs!B25=65,Inputs!B22*12,IF(Inputs!B25=70,Inputs!B24*12,Inputs!B23*12))*(1+Inputs!B21)^MAX(0,74-Inputs!B25),0) -> 56657.518 | D12: =C12*Inputs!B43 -> 48158.89 | E12: =MAX(0,Inputs!B41-D12-Inputs!B42) -> 122891.11 | F12: =D12+E12 -> 171050 | G12: =MAX(0,IF(F12<=23200,F12*0.1,IF(F12<=94300,23200*0.1+(F12-23200)*0.12,IF(F12<=201050,23200*0.1+71100*0.12+(F12-94300)*0.22,IF(F12<=383900,23200*0.1+71100*0.12+106750*0.22+(F12-201050)*0.24,23200*0.1+71100*0.12+106750*0.22+182850*0.24+(F12-383900)*0.32))))) -> 27737 | H12: =IFERROR(G12/F12,0) -> 0.16215726 | I12: =IF(F12<=206000,"Tier 0 — $0/yr",IF(F12<=258000,"Tier 1 — $594/yr",IF(F12<=322000,"Tier 2 — $1,494/yr",IF(F12<=386000,"Tier 3 — $2,394/yr",IF(F12<=750000,"Tier 4 — $3,270/yr","Tier 5 — $3,564/yr"))))) -> Tier 0 — $0/yr | J12: =MAX(0,B12-E12) -> 1643438.5
A13: 75 | B13: =J12 -> 1643438.5 | C13: =IF(75>=Inputs!B25,IF(Inputs!B25=65,Inputs!B22*12,IF(Inputs!B25=70,Inputs!B24*12,Inputs!B23*12))*(1+Inputs!B21)^MAX(0,75-Inputs!B25),0) -> 58073.956 | D13: =C13*Inputs!B43 -> 49362.862 | E13: =MAX(0,Inputs!B41-D13-Inputs!B42) -> 121687.14 | F13: =D13+E13 -> 171050 | G13: =MAX(0,IF(F13<=23200,F13*0.1,IF(F13<=94300,23200*0.1+(F13-23200)*0.12,IF(F13<=201050,23200*0.1+71100*0.12+(F13-94300)*0.22,IF(F13<=383900,23200*0.1+71100*0.12+106750*0.22+(F13-201050)*0.24,23200*0.1+71100*0.12+106750*0.22+182850*0.24+(F13-383900)*0.32))))) -> 27737 | H13: =IFERROR(G13/F13,0) -> 0.16215726 | I13: =IF(F13<=206000,"Tier 0 — $0/yr",IF(F13<=258000,"Tier 1 — $594/yr",IF(F13<=322000,"Tier 2 — $1,494/yr",IF(F13<=386000,"Tier 3 — $2,394/yr",IF(F13<=750000,"Tier 4 — $3,270/yr","Tier 5 — $3,564/yr"))))) -> Tier 0 — $0/yr | J13: =MAX(0,B13-E13) -> 1521751.4
A14: 76 | B14: =J13 -> 1521751.4 | C14: =IF(76>=Inputs!B25,IF(Inputs!B25=65,Inputs!B22*12,IF(Inputs!B25=70,Inputs!B24*12,Inputs!B23*12))*(1+Inputs!B21)^MAX(0,76-Inputs!B25),0) -> 59525.805 | D14: =C14*Inputs!B43 -> 50596.934 | E14: =MAX(0,Inputs!B41-D14-Inputs!B42) -> 120453.07 | F14: =D14+E14 -> 171050 | G14: =MAX(0,IF(F14<=23200,F14*0.1,IF(F14<=94300,23200*0.1+(F14-23200)*0.12,IF(F14<=201050,23200*0.1+71100*0.12+(F14-94300)*0.22,IF(F14<=383900,23200*0.1+71100*0.12+106750*0.22+(F14-201050)*0.24,23200*0.1+71100*0.12+106750*0.22+182850*0.24+(F14-383900)*0.32))))) -> 27737 | H14: =IFERROR(G14/F14,0) -> 0.16215726 | I14: =IF(F14<=206000,"Tier 0 — $0/yr",IF(F14<=258000,"Tier 1 — $594/yr",IF(F14<=322000,"Tier 2 — $1,494/yr",IF(F14<=386000,"Tier 3 — $2,394/yr",IF(F14<=750000,"Tier 4 — $3,270/yr","Tier 5 — $3,564/yr"))))) -> Tier 0 — $0/yr | J14: =MAX(0,B14-E14) -> 1401298.3
A15: 77 | B15: =J14 -> 1401298.3 | C15: =IF(77>=Inputs!B25,IF(Inputs!B25=65,Inputs!B22*12,IF(Inputs!B25=70,Inputs!B24*12,Inputs!B23*12))*(1+Inputs!B21)^MAX(0,77-Inputs!B25),0) -> 61013.95 | D15: =C15*Inputs!B43 -> 51861.857 | E15: =MAX(0,Inputs!B41-D15-Inputs!B42) -> 119188.14 | F15: =D15+E15 -> 171050 | G15: =MAX(0,IF(F15<=23200,F15*0.1,IF(F15<=94300,23200*0.1+(F15-23200)*0.12,IF(F15<=201050,23200*0.1+71100*0.12+(F15-94300)*0.22,IF(F15<=383900,23200*0.1+71100*0.12+106750*0.22+(F15-201050)*0.24,23200*0.1+71100*0.12+106750*0.22+182850*0.24+(F15-383900)*0.32))))) -> 27737 | H15: =IFERROR(G15/F15,0) -> 0.16215726 | I15: =IF(F15<=206000,"Tier 0 — $0/yr",IF(F15<=258000,"Tier 1 — $594/yr",IF(F15<=322000,"Tier 2 — $1,494/yr",IF(F15<=386000,"Tier 3 — $2,394/yr",IF(F15<=750000,"Tier 4 — $3,270/yr","Tier 5 — $3,564/yr"))))) -> Tier 0 — $0/yr | J15: =MAX(0,B15-E15) -> 1282110.1
A16: 78 | B16: =J15 -> 1282110.1 | C16: =IF(78>=Inputs!B25,IF(Inputs!B25=65,Inputs!B22*12,IF(Inputs!B25=70,Inputs!B24*12,Inputs!B23*12))*(1+Inputs!B21)^MAX(0,78-Inputs!B25),0) -> 62539.298 | D16: =C16*Inputs!B43 -> 53158.404 | E16: =MAX(0,Inputs!B41-D16-Inputs!B42) -> 117891.6 | F16: =D16+E16 -> 171050 | G16: =MAX(0,IF(F16<=23200,F16*0.1,IF(F16<=94300,23200*0.1+(F16-23200)*0.12,IF(F16<=201050,23200*0.1+71100*0.12+(F16-94300)*0.22,IF(F16<=383900,23200*0.1+71100*0.12+106750*0.22+(F16-201050)*0.24,23200*0.1+71100*0.12+106750*0.22+182850*0.24+(F16-383900)*0.32))))) -> 27737 | H16: =IFERROR(G16/F16,0) -> 0.16215726 | I16: =IF(F16<=206000,"Tier 0 — $0/yr",IF(F16<=258000,"Tier 1 — $594/yr",IF(F16<=322000,"Tier 2 — $1,494/yr",IF(F16<=386000,"Tier 3 — $2,394/yr",IF(F16<=750000,"Tier 4 — $3,270/yr","Tier 5 — $3,564/yr"))))) -> Tier 0 — $0/yr | J16: =MAX(0,B16-E16) -> 1164218.6
A17: 79 | B17: =J16 -> 1164218.6 | C17: =IF(79>=Inputs!B25,IF(Inputs!B25=65,Inputs!B22*12,IF(Inputs!B25=70,Inputs!B24*12,Inputs!B23*12))*(1+Inputs!B21)^MAX(0,79-Inputs!B25),0) -> 64102.781 | D17: =C17*Inputs!B43 -> 54487.364 | E17: =MAX(0,Inputs!B41-D17-Inputs!B42) -> 116562.64 | F17: =D17+E17 -> 171050 | G17: =MAX(0,IF(F17<=23200,F17*0.1,IF(F17<=94300,23200*0.1+(F17-23200)*0.12,IF(F17<=201050,23200*0.1+71100*0.12+(F17-94300)*0.22,IF(F17<=383900,23200*0.1+71100*0.12+106750*0.22+(F17-201050)*0.24,23200*0.1+71100*0.12+106750*0.22+182850*0.24+(F17-383900)*0.32))))) -> 27737 | H17: =IFERROR(G17/F17,0) -> 0.16215726 | I17: =IF(F17<=206000,"Tier 0 — $0/yr",IF(F17<=258000,"Tier 1 — $594/yr",IF(F17<=322000,"Tier 2 — $1,494/yr",IF(F17<=386000,"Tier 3 — $2,394/yr",IF(F17<=750000,"Tier 4 — $3,270/yr","Tier 5 — $3,564/yr"))))) -> Tier 0 — $0/yr | J17: =MAX(0,B17-E17) -> 1047655.9
A18: 80 | B18: =J17 -> 1047655.9 | C18: =IF(80>=Inputs!B25,IF(Inputs!B25=65,Inputs!B22*12,IF(Inputs!B25=70,Inputs!B24*12,Inputs!B23*12))*(1+Inputs!B21)^MAX(0,80-Inputs!B25),0) -> 65705.35 | D18: =C18*Inputs!B43 -> 55849.548 | E18: =MAX(0,Inputs!B41-D18-Inputs!B42) -> 115200.45 | F18: =D18+E18 -> 171050 | G18: =MAX(0,IF(F18<=23200,F18*0.1,IF(F18<=94300,23200*0.1+(F18-23200)*0.12,IF(F18<=201050,23200*0.1+71100*0.12+(F18-94300)*0.22,IF(F18<=383900,23200*0.1+71100*0.12+106750*0.22+(F18-201050)*0.24,23200*0.1+71100*0.12+106750*0.22+182850*0.24+(F18-383900)*0.32))))) -> 27737 | H18: =IFERROR(G18/F18,0) -> 0.16215726 | I18: =IF(F18<=206000,"Tier 0 — $0/yr",IF(F18<=258000,"Tier 1 — $594/yr",IF(F18<=322000,"Tier 2 — $1,494/yr",IF(F18<=386000,"Tier 3 — $2,394/yr",IF(F18<=750000,"Tier 4 — $3,270/yr","Tier 5 — $3,564/yr"))))) -> Tier 0 — $0/yr | J18: =MAX(0,B18-E18) -> 932455.46
A19: 81 | B19: =J18 -> 932455.46 | C19: =IF(81>=Inputs!B25,IF(Inputs!B25=65,Inputs!B22*12,IF(Inputs!B25=70,Inputs!B24*12,Inputs!B23*12))*(1+Inputs!B21)^MAX(0,81-Inputs!B25),0) -> 67347.984 | D19: =C19*Inputs!B43 -> 57245.787 | E19: =MAX(0,Inputs!B41-D19-Inputs!B42) -> 113804.21 | F19: =D19+E19 -> 171050 | G19: =MAX(0,IF(F19<=23200,F19*0.1,IF(F19<=94300,23200*0.1+(F19-23200)*0.12,IF(F19<=201050,23200*0.1+71100*0.12+(F19-94300)*0.22,IF(F19<=383900,23200*0.1+71100*0.12+106750*0.22+(F19-201050)*0.24,23200*0.1+71100*0.12+106750*0.22+182850*0.24+(F19-383900)*0.32))))) -> 27737 | H19: =IFERROR(G19/F19,0) -> 0.16215726 | I19: =IF(F19<=206000,"Tier 0 — $0/yr",IF(F19<=258000,"Tier 1 — $594/yr",IF(F19<=322000,"Tier 2 — $1,494/yr",IF(F19<=386000,"Tier 3 — $2,394/yr",IF(F19<=750000,"Tier 4 — $3,270/yr","Tier 5 — $3,564/yr"))))) -> Tier 0 — $0/yr | J19: =MAX(0,B19-E19) -> 818651.25
A20: 82 | B20: =J19 -> 818651.25 | C20: =IF(82>=Inputs!B25,IF(Inputs!B25=65,Inputs!B22*12,IF(Inputs!B25=70,Inputs!B24*12,Inputs!B23*12))*(1+Inputs!B21)^MAX(0,82-Inputs!B25),0) -> 69031.684 | D20: =C20*Inputs!B43 -> 58676.931 | E20: =MAX(0,Inputs!B41-D20-Inputs!B42) -> 112373.07 | F20: =D20+E20 -> 171050 | G20: =MAX(0,IF(F20<=23200,F20*0.1,IF(F20<=94300,23200*0.1+(F20-23200)*0.12,IF(F20<=201050,23200*0.1+71100*0.12+(F20-94300)*0.22,IF(F20<=383900,23200*0.1+71100*0.12+106750*0.22+(F20-201050)*0.24,23200*0.1+71100*0.12+106750*0.22+182850*0.24+(F20-383900)*0.32))))) -> 27737 | H20: =IFERROR(G20/F20,0) -> 0.16215726 | I20: =IF(F20<=206000,"Tier 0 — $0/yr",IF(F20<=258000,"Tier 1 — $594/yr",IF(F20<=322000,"Tier 2 — $1,494/yr",IF(F20<=386000,"Tier 3 — $2,394/yr",IF(F20<=750000,"Tier 4 — $3,270/yr","Tier 5 — $3,564/yr"))))) -> Tier 0 — $0/yr | J20: =MAX(0,B20-E20) -> 706278.18
A21: 83 | B21: =J20 -> 706278.18 | C21: =IF(83>=Inputs!B25,IF(Inputs!B25=65,Inputs!B22*12,IF(Inputs!B25=70,Inputs!B24*12,Inputs!B23*12))*(1+Inputs!B21)^MAX(0,83-Inputs!B25),0) -> 70757.476 | D21: =C21*Inputs!B43 -> 60143.855 | E21: =MAX(0,Inputs!B41-D21-Inputs!B42) -> 110906.15 | F21: =D21+E21 -> 171050 | G21: =MAX(0,IF(F21<=23200,F21*0.1,IF(F21<=94300,23200*0.1+(F21-23200)*0.12,IF(F21<=201050,23200*0.1+71100*0.12+(F21-94300)*0.22,IF(F21<=383900,23200*0.1+71100*0.12+106750*0.22+(F21-201050)*0.24,23200*0.1+71100*0.12+106750*0.22+182850*0.24+(F21-383900)*0.32))))) -> 27737 | H21: =IFERROR(G21/F21,0) -> 0.16215726 | I21: =IF(F21<=206000,"Tier 0 — $0/yr",IF(F21<=258000,"Tier 1 — $594/yr",IF(F21<=322000,"Tier 2 — $1,494/yr",IF(F21<=386000,"Tier 3 — $2,394/yr",IF(F21<=750000,"Tier 4 — $3,270/yr","Tier 5 — $3,564/yr"))))) -> Tier 0 — $0/yr | J21: =MAX(0,B21-E21) -> 595372.04
A22: 84 | B22: =J21 -> 595372.04 | C22: =IF(84>=Inputs!B25,IF(Inputs!B25=65,Inputs!B22*12,IF(Inputs!B25=70,Inputs!B24*12,Inputs!B23*12))*(1+Inputs!B21)^MAX(0,84-Inputs!B25),0) -> 72526.413 | D22: =C22*Inputs!B43 -> 61647.451 | E22: =MAX(0,Inputs!B41-D22-Inputs!B42) -> 109402.55 | F22: =D22+E22 -> 171050 | G22: =MAX(0,IF(F22<=23200,F22*0.1,IF(F22<=94300,23200*0.1+(F22-23200)*0.12,IF(F22<=201050,23200*0.1+71100*0.12+(F22-94300)*0.22,IF(F22<=383900,23200*0.1+71100*0.12+106750*0.22+(F22-201050)*0.24,23200*0.1+71100*0.12+106750*0.22+182850*0.24+(F22-383900)*0.32))))) -> 27737 | H22: =IFERROR(G22/F22,0) -> 0.16215726 | I22: =IF(F22<=206000,"Tier 0 — $0/yr",IF(F22<=258000,"Tier 1 — $594/yr",IF(F22<=322000,"Tier 2 — $1,494/yr",IF(F22<=386000,"Tier 3 — $2,394/yr",IF(F22<=750000,"Tier 4 — $3,270/yr","Tier 5 — $3,564/yr"))))) -> Tier 0 — $0/yr | J22: =MAX(0,B22-E22) -> 485969.49
A23: 85 | B23: =J22 -> 485969.49 | C23: =IF(85>=Inputs!B25,IF(Inputs!B25=65,Inputs!B22*12,IF(Inputs!B25=70,Inputs!B24*12,Inputs!B23*12))*(1+Inputs!B21)^MAX(0,85-Inputs!B25),0) -> 74339.573 | D23: =C23*Inputs!B43 -> 63188.637 | E23: =MAX(0,Inputs!B41-D23-Inputs!B42) -> 107861.36 | F23: =D23+E23 -> 171050 | G23: =MAX(0,IF(F23<=23200,F23*0.1,IF(F23<=94300,23200*0.1+(F23-23200)*0.12,IF(F23<=201050,23200*0.1+71100*0.12+(F23-94300)*0.22,IF(F23<=383900,23200*0.1+71100*0.12+106750*0.22+(F23-201050)*0.24,23200*0.1+71100*0.12+106750*0.22+182850*0.24+(F23-383900)*0.32))))) -> 27737 | H23: =IFERROR(G23/F23,0) -> 0.16215726 | I23: =IF(F23<=206000,"Tier 0 — $0/yr",IF(F23<=258000,"Tier 1 — $594/yr",IF(F23<=322000,"Tier 2 — $1,494/yr",IF(F23<=386000,"Tier 3 — $2,394/yr",IF(F23<=750000,"Tier 4 — $3,270/yr","Tier 5 — $3,564/yr"))))) -> Tier 0 — $0/yr | J23: =MAX(0,B23-E23) -> 378108.12
A25: IRMAA 2025 Tier Legend (MFJ, per-person surcharge/yr):
A26: Base (Tier 0): MAGI ≤ $206,000 — $0 surcharge
A27: Tier 1: MAGI $206,001–$258,000 — $594/person/yr
A28: Tier 2: MAGI $258,001–$322,000 — $1,488/person/yr
A29: Tier 3: MAGI $322,001–$386,000 — $2,382/person/yr
A30: Tier 4: MAGI $386,001–$750,000 — $3,276/person/yr
A31: Tier 5: MAGI > $750,000 — $4,170/person/yr

Sheet Withdrawal Plan
A1: ANNUAL WITHDRAWAL PLAN (Ages 65–85)
A2: Age | B2: Living+Infl ($) | C2: Mortgage ($) [ends at term] | D2: Prop Tax +Ins ($) | E2: Wife Ins ($) | F2: Medicare ($) | G2: Total Needs ($) | H2: Your SS ($) | I2: Wife SS ($) | J2: Trad 401k Draw ($) | K2: Roth IRA Draw ($) | L2: Brokerage Draw ($) | M2: HSA Draw ($) | N2: Fed Tax ($) | O2: State Tax ($) | P2: Net Surplus ($)
A3: 65 | B3: =Inputs!B29*12*(1+Inputs!B20)^0 -> 84000 | C3: =IF(Inputs!B51=1,0,IF((VALUE(A3)-Inputs!B5)>=MAX(0,Inputs!B48-(Inputs!B5-Inputs!B4)),0,Inputs!B30*12)) -> 36000 | D3: =Inputs!B31+Inputs!B32 -> 16500 | E3: =IF(60<65,Inputs!B35*12,0) -> 9600 | F3: =Inputs!B33*12*(1+Inputs!B34)^0 -> 2220 | G3: =B3+C3+D3+E3+F3 -> 148320 | H3: =IF(65>=Inputs!B25,IF(Inputs!B25=65,Inputs!B22*12,IF(Inputs!B25=70,Inputs!B24*12,Inputs!B23*12))*(1+Inputs!B21)^MAX(0,65-Inputs!B25),0) -> 0 | I3: =IF(60>=Inputs!B26,Inputs!B23*12*0.5*(1+Inputs!B21)^MAX(0,60-Inputs!B26),0) -> 0 | J3: ='Roth Conversion'!E3 -> 171050 | K3: =MAX(0,G3-H3-I3-J3)*0.4 -> 0 | L3: =MAX(0,G3-H3-I3-J3-K3) -> 0 | M3: =F3 -> 2220 | N3: =MAX(0,IF((J3+H3*Inputs!B43)<=23200,(J3+H3*Inputs!B43)*0.1,IF((J3+H3*Inputs!B43)<=94300,23200*0.1+((J3+H3*Inputs!B43)-23200)*0.12,IF((J3+H3*Inputs!B43)<=201050,23200*0.1+71100*0.12+((J3+H3*Inputs!B43)-94300)*0.22,23200*0.1+71100*0.12+106750*0.22+((J3+H3*Inputs!B43)-201050)*0.24)))) -> 27737 | O3: =J3*0.0637 -> 10895.885 | P3: =H3+I3+J3+K3+L3-G3-N3-O3 -> -15902.885
A4: 66 | B4: =Inputs!B29*12*(1+Inputs!B20)^1 -> 86520 | C4: =IF(Inputs!B51=1,0,IF((VALUE(A4)-Inputs!B5)>=MAX(0,Inputs!B48-(Inputs!B5-Inputs!B4)),0,Inputs!B30*12)) -> 36000 | D4: =Inputs!B31+Inputs!B32 -> 16500 | E4: =IF(61<65,Inputs!B35*12,0) -> 9600 | F4: =Inputs!B33*12*(1+Inputs!B34)^1 -> 2331 | G4: =B4+C4+D4+E4+F4 -> 150951 | H4: =IF(66>=Inputs!B25,IF(Inputs!B25=65,Inputs!B22*12,IF(Inputs!B25=70,Inputs!B24*12,Inputs!B23*12))*(1+Inputs!B21)^MAX(0,66-Inputs!B25),0) -> 0 | I4: =IF(61>=Inputs!B26,Inputs!B23*12*0.5*(1+Inputs!B21)^MAX(0,61-Inputs!B26),0) -> 0 | J4: ='Roth Conversion'!E4 -> 171050 | K4: =MAX(0,G4-H4-I4-J4)*0.4 -> 0 | L4: =MAX(0,G4-H4-I4-J4-K4) -> 0 | M4: =F4 -> 2331 | N4: =MAX(0,IF((J4+H4*Inputs!B43)<=23200,(J4+H4*Inputs!B43)*0.1,IF((J4+H4*Inputs!B43)<=94300,23200*0.1+((J4+H4*Inputs!B43)-23200)*0.12,IF((J4+H4*Inputs!B43)<=201050,23200*0.1+71100*0.12+((J4+H4*Inputs!B43)-94300)*0.22,23200*0.1+71100*0.12+106750*0.22+((J4+H4*Inputs!B43)-201050)*0.24)))) -> 27737 | O4: =J4*0.0637 -> 10895.885 | P4: =H4+I4+J4+K4+L4-G4-N4-O4 -> -18533.885
A5: 67 | B5: =Inputs!B29*12*(1+Inputs!B20)^2 -> 89115.6 | C5: =IF(Inputs!B51=1,0,IF((VALUE(A5)-Inputs!B5)>=MAX(0,Inputs!B48-(Inputs!B5-Inputs!B4)),0,Inputs!B30*12)) -> 36000 | D5: =Inputs!B31+Inputs!B32 -> 16500 | E5: =IF(62<65,Inputs!B35*12,0) -> 9600 | F5: =Inputs!B33*12*(1+Inputs!B34)^2 -> 2447.55 | G5: =B5+C5+D5+E5+F5 -> 153663.15 | H5: =IF(67>=Inputs!B25,IF(Inputs!B25=65,Inputs!B22*12,IF(Inputs!B25=70,Inputs!B24*12,Inputs!B23*12))*(1+Inputs!B21)^MAX(0,67-Inputs!B25),0) -> 47664 | I5: =IF(62>=Inputs!B26,Inputs!B23*12*0.5*(1+Inputs!B21)^MAX(0,62-Inputs!B26),0) -> 0 | J5: ='Roth Conversion'!E5 -> 130535.6 | K5: =MAX(0,G5-H5-I5-J5)*0.4 -> 0 | L5: =MAX(0,G5-H5-I5-J5-K5) -> 0 | M5: =F5 -> 2447.55 | N5: =MAX(0,IF((J5+H5*Inputs!B43)<=23200,(J5+H5*Inputs!B43)*0.1,IF((J5+H5*Inputs!B43)<=94300,23200*0.1+((J5+H5*Inputs!B43)-23200)*0.12,IF((J5+H5*Inputs!B43)<=201050,23200*0.1+71100*0.12+((J5+H5*Inputs!B43)-94300)*0.22,23200*0.1+71100*0.12+106750*0.22+((J5+H5*Inputs!B43)-201050)*0.24)))) -> 27737 | O5: =J5*0.0637 -> 8315.1177 | P5: =H5+I5+J5+K5+L5-G5-N5-O5 -> -11515.668
A6: 68 | B6: =Inputs!B29*12*(1+Inputs!B20)^3 -> 91789.068 | C6: =IF(Inputs!B51=1,0,IF((VALUE(A6)-Inputs!B5)>=MAX(0,Inputs!B48-(Inputs!B5-Inputs!B4)),0,Inputs!B30*12)) -> 36000 | D6: =Inputs!B31+Inputs!B32 -> 16500 | E6: =IF(63<65,Inputs!B35*12,0) -> 9600 | F6: =Inputs!B33*12*(1+Inputs!B34)^3 -> 2569.9275 | G6: =B6+C6+D6+E6+F6 -> 156459 | H6: =IF(68>=Inputs!B25,IF(Inputs!B25=65,Inputs!B22*12,IF(Inputs!B25=70,Inputs!B24*12,Inputs!B23*12))*(1+Inputs!B21)^MAX(0,68-Inputs!B25),0) -> 48855.6 | I6: =IF(63>=Inputs!B26,Inputs!B23*12*0.5*(1+Inputs!B21)^MAX(0,63-Inputs!B26),0) -> 0 | J6: ='Roth Conversion'!E6 -> 129522.74 | K6: =MAX(0,G6-H6-I6-J6)*0.4 -> 0 | L6: =MAX(0,G6-H6-I6-J6-K6) -> 0 | M6: =F6 -> 2569.9275 | N6: =MAX(0,IF((J6+H6*Inputs!B43)<=23200,(J6+H6*Inputs!B43)*0.1,IF((J6+H6*Inputs!B43)<=94300,23200*0.1+((J6+H6*Inputs!B43)-23200)*0.12,IF((J6+H6*Inputs!B43)<=201050,23200*0.1+71100*0.12+((J6+H6*Inputs!B43)-94300)*0.22,23200*0.1+71100*0.12+106750*0.22+((J6+H6*Inputs!B43)-201050)*0.24)))) -> 27737 | O6: =J6*0.0637 -> 8250.5985 | P6: =H6+I6+J6+K6+L6-G6-N6-O6 -> -14068.254
A7: 69 | B7: =Inputs!B29*12*(1+Inputs!B20)^4 -> 94542.74 | C7: =IF(Inputs!B51=1,0,IF((VALUE(A7)-Inputs!B5)>=MAX(0,Inputs!B48-(Inputs!B5-Inputs!B4)),0,Inputs!B30*12)) -> 36000 | D7: =Inputs!B31+Inputs!B32 -> 16500 | E7: =IF(64<65,Inputs!B35*12,0) -> 9600 | F7: =Inputs!B33*12*(1+Inputs!B34)^4 -> 2698.4239 | G7: =B7+C7+D7+E7+F7 -> 159341.16 | H7: =IF(69>=Inputs!B25,IF(Inputs!B25=65,Inputs!B22*12,IF(Inputs!B25=70,Inputs!B24*12,Inputs!B23*12))*(1+Inputs!B21)^MAX(0,69-Inputs!B25),0) -> 50076.99 | I7: =IF(64>=Inputs!B26,Inputs!B23*12*0.5*(1+Inputs!B21)^MAX(0,64-Inputs!B26),0) -> 0 | J7: ='Roth Conversion'!E7 -> 128484.56 | K7: =MAX(0,G7-H7-I7-J7)*0.4 -> 0 | L7: =MAX(0,G7-H7-I7-J7-K7) -> 0 | M7: =F7 -> 2698.4239 | N7: =MAX(0,IF((J7+H7*Inputs!B43)<=23200,(J7+H7*Inputs!B43)*0.1,IF((J7+H7*Inputs!B43)<=94300,23200*0.1+((J7+H7*Inputs!B43)-23200)*0.12,IF((J7+H7*Inputs!B43)<=201050,23200*0.1+71100*0.12+((J7+H7*Inputs!B43)-94300)*0.22,23200*0.1+71100*0.12+106750*0.22+((J7+H7*Inputs!B43)-201050)*0.24)))) -> 27737 | O7: =J7*0.0637 -> 8184.4664 | P7: =H7+I7+J7+K7+L7-G7-N7-O7 -> -16701.082
A8: 70 | B8: =Inputs!B29*12*(1+Inputs!B20)^5 -> 97379.022 | C8: =IF(Inputs!B51=1,0,IF((VALUE(A8)-Inputs!B5)>=MAX(0,Inputs!B48-(Inputs!B5-Inputs!B4)),0,Inputs!B30*12)) -> 36000 | D8: =Inputs!B31+Inputs!B32 -> 16500 | E8: =IF(65<65,Inputs!B35*12,0) -> 0 | F8: =Inputs!B33*12*(1+Inputs!B34)^5 -> 2833.3451 | G8: =B8+C8+D8+E8+F8 -> 152712.37 | H8: =IF(70>=Inputs!B25,IF(Inputs!B25=65,Inputs!B22*12,IF(Inputs!B25=70,Inputs!B24*12,Inputs!B23*12))*(1+Inputs!B21)^MAX(0,70-Inputs!B25),0) -> 51328.915 | I8: =IF(65>=Inputs!B26,Inputs!B23*12*0.5*(1+Inputs!B21)^MAX(0,65-Inputs!B26),0) -> 23832 | J8: ='Roth Conversion'!E8 -> 127420.42 | K8: =MAX(0,G8-H8-I8-J8)*0.4 -> 0 | L8: =MAX(0,G8-H8-I8-J8-K8) -> 0 | M8: =F8 -> 2833.3451 | N8: =MAX(0,IF((J8+H8*Inputs!B43)<=23200,(J8+H8*Inputs!B43)*0.1,IF((J8+H8*Inputs!B43)<=94300,23200*0.1+((J8+H8*Inputs!B43)-23200)*0.12,IF((J8+H8*Inputs!B43)<=201050,23200*0.1+71100*0.12+((J8+H8*Inputs!B43)-94300)*0.22,23200*0.1+71100*0.12+106750*0.22+((J8+H8*Inputs!B43)-201050)*0.24)))) -> 27737 | O8: =J8*0.0637 -> 8116.6809 | P8: =H8+I8+J8+K8+L8-G8-N8-O8 -> 14015.289
A9: 71 | B9: =Inputs!B29*12*(1+Inputs!B20)^6 -> 100300.39 | C9: =IF(Inputs!B51=1,0,IF((VALUE(A9)-Inputs!B5)>=MAX(0,Inputs!B48-(Inputs!B5-Inputs!B4)),0,Inputs!B30*12)) -> 36000 | D9: =Inputs!B31+Inputs!B32 -> 16500 | E9: =IF(66<65,Inputs!B35*12,0) -> 0 | F9: =Inputs!B33*12*(1+Inputs!B34)^6 -> 2975.0123 | G9: =B9+C9+D9+E9+F9 -> 155775.41 | H9: =IF(71>=Inputs!B25,IF(Inputs!B25=65,Inputs!B22*12,IF(Inputs!B25=70,Inputs!B24*12,Inputs!B23*12))*(1+Inputs!B21)^MAX(0,71-Inputs!B25),0) -> 52612.138 | I9: =IF(66>=Inputs!B26,Inputs!B23*12*0.5*(1+Inputs!B21)^MAX(0,66-Inputs!B26),0) -> 24427.8 | J9: ='Roth Conversion'!E9 -> 126329.68 | K9: =MAX(0,G9-H9-I9-J9)*0.4 -> 0 | L9: =MAX(0,G9-H9-I9-J9-K9) -> 0 | M9: =F9 -> 2975.0123 | N9: =MAX(0,IF((J9+H9*Inputs!B43)<=23200,(J9+H9*Inputs!B43)*0.1,IF((J9+H9*Inputs!B43)<=94300,23200*0.1+((J9+H9*Inputs!B43)-23200)*0.12,IF((J9+H9*Inputs!B43)<=201050,23200*0.1+71100*0.12+((J9+H9*Inputs!B43)-94300)*0.22,23200*0.1+71100*0.12+106750*0.22+((J9+H9*Inputs!B43)-201050)*0.24)))) -> 27737 | O9: =J9*0.0637 -> 8047.2008 | P9: =H9+I9+J9+K9+L9-G9-N9-O9 -> 11810.015
A10: 72 | B10: =Inputs!B29*12*(1+Inputs!B20)^7 -> 103309.4 | C10: =IF(Inputs!B51=1,0,IF((VALUE(A10)-Inputs!B5)>=MAX(0,Inputs!B48-(Inputs!B5-Inputs!B4)),0,Inputs!B30*12)) -> 36000 | D10: =Inputs!B31+Inputs!B32 -> 16500 | E10: =IF(67<65,Inputs!B35*12,0) -> 0 | F10: =Inputs!B33*12*(1+Inputs!B34)^7 -> 3123.7629 | G10: =B10+C10+D10+E10+F10 -> 158933.17 | H10: =IF(72>=Inputs!B25,IF(Inputs!B25=65,Inputs!B22*12,IF(Inputs!B25=70,Inputs!B24*12,Inputs!B23*12))*(1+Inputs!B21)^MAX(0,72-Inputs!B25),0) -> 53927.441 | I10: =IF(67>=Inputs!B26,Inputs!B23*12*0.5*(1+Inputs!B21)^MAX(0,67-Inputs!B26),0) -> 25038.495 | J10: ='Roth Conversion'!E10 -> 125211.68 | K10: =MAX(0,G10-H10-I10-J10)*0.4 -> 0 | L10: =MAX(0,G10-H10-I10-J10-K10) -> 0 | M10: =F10 -> 3123.7629 | N10: =MAX(0,IF((J10+H10*Inputs!B43)<=23200,(J10+H10*Inputs!B43)*0.1,IF((J10+H10*Inputs!B43)<=94300,23200*0.1+((J10+H10*Inputs!B43)-23200)*0.12,IF((J10+H10*Inputs!B43)<=201050,23200*0.1+71100*0.12+((J10+H10*Inputs!B43)-94300)*0.22,23200*0.1+71100*0.12+106750*0.22+((J10+H10*Inputs!B43)-201050)*0.24)))) -> 27737 | O10: =J10*0.0637 -> 7975.9837 | P10: =H10+I10+J10+K10+L10-G10-N10-O10 -> 9531.4598
A11: 73 | B11: =Inputs!B29*12*(1+Inputs!B20)^8 -> 106408.69 | C11: =IF(Inputs!B51=1,0,IF((VALUE(A11)-Inputs!B5)>=MAX(0,Inputs!B48-(Inputs!B5-Inputs!B4)),0,Inputs!B30*12)) -> 36000 | D11: =Inputs!B31+Inputs!B32 -> 16500 | E11: =IF(68<65,Inputs!B35*12,0) -> 0 | F11: =Inputs!B33*12*(1+Inputs!B34)^8 -> 3279.9511 | G11: =B11+C11+D11+E11+F11 -> 162188.64 | H11: =IF(73>=Inputs!B25,IF(Inputs!B25=65,Inputs!B22*12,IF(Inputs!B25=70,Inputs!B24*12,Inputs!B23*12))*(1+Inputs!B21)^MAX(0,73-Inputs!B25),0) -> 55275.627 | I11: =IF(68>=Inputs!B26,Inputs!B23*12*0.5*(1+Inputs!B21)^MAX(0,68-Inputs!B26),0) -> 25664.457 | J11: ='Roth Conversion'!E11 -> 124065.72 | K11: =MAX(0,G11-H11-I11-J11)*0.4 -> 0 | L11: =MAX(0,G11-H11-I11-J11-K11) -> 0 | M11: =F11 -> 3279.9511 | N11: =MAX(0,IF((J11+H11*Inputs!B43)<=23200,(J11+H11*Inputs!B43)*0.1,IF((J11+H11*Inputs!B43)<=94300,23200*0.1+((J11+H11*Inputs!B43)-23200)*0.12,IF((J11+H11*Inputs!B43)<=201050,23200*0.1+71100*0.12+((J11+H11*Inputs!B43)-94300)*0.22,23200*0.1+71100*0.12+106750*0.22+((J11+H11*Inputs!B43)-201050)*0.24)))) -> 27737 | O11: =J11*0.0637 -> 7902.9862 | P11: =H11+I11+J11+K11+L11-G11-N11-O11 -> 7177.1773
A12: 74 | B12: =Inputs!B29*12*(1+Inputs!B20)^9 -> 109600.95 | C12: =IF(Inputs!B51=1,0,IF((VALUE(A12)-Inputs!B5)>=MAX(0,Inputs!B48-(Inputs!B5-Inputs!B4)),0,Inputs!B30*12)) -> 36000 | D12: =Inputs!B31+Inputs!B32 -> 16500 | E12: =IF(69<65,Inputs!B35*12,0) -> 0 | F12: =Inputs!B33*12*(1+Inputs!B34)^9 -> 3443.9486 | G12: =B12+C12+D12+E12+F12 -> 165544.9 | H12: =IF(74>=Inputs!B25,IF(Inputs!B25=65,Inputs!B22*12,IF(Inputs!B25=70,Inputs!B24*12,Inputs!B23*12))*(1+Inputs!B21)^MAX(0,74-Inputs!B25),0) -> 56657.518 | I12: =IF(69>=Inputs!B26,Inputs!B23*12*0.5*(1+Inputs!B21)^MAX(0,69-Inputs!B26),0) -> 26306.069 | J12: ='Roth Conversion'!E12 -> 122891.11 | K12: =MAX(0,G12-H12-I12-J12)*0.4 -> 0 | L12: =MAX(0,G12-H12-I12-J12-K12) -> 0 | M12: =F12 -> 3443.9486 | N12: =MAX(0,IF((J12+H12*Inputs!B43)<=23200,(J12+H12*Inputs!B43)*0.1,IF((J12+H12*Inputs!B43)<=94300,23200*0.1+((J12+H12*Inputs!B43)-23200)*0.12,IF((J12+H12*Inputs!B43)<=201050,23200*0.1+71100*0.12+((J12+H12*Inputs!B43)-94300)*0.22,23200*0.1+71100*0.12+106750*0.22+((J12+H12*Inputs!B43)-201050)*0.24)))) -> 27737 | O12: =J12*0.0637 -> 7828.1637 | P12: =H12+I12+J12+K12+L12-G12-N12-O12 -> 4744.6367
A13: 75 | B13: =Inputs!B29*12*(1+Inputs!B20)^10 -> 112888.98 | C13: =IF(Inputs!B51=1,0,IF((VALUE(A13)-Inputs!B5)>=MAX(0,Inputs!B48-(Inputs!B5-Inputs!B4)),0,Inputs!B30*12)) -> 36000 | D13: =Inputs!B31+Inputs!B32 -> 16500 | E13: =IF(70<65,Inputs!B35*12,0) -> 0 | F13: =Inputs!B33*12*(1+Inputs!B34)^10 -> 3616.1461 | G13: =B13+C13+D13+E13+F13 -> 169005.12 | H13: =IF(75>=Inputs!B25,IF(Inputs!B25=65,Inputs!B22*12,IF(Inputs!B25=70,Inputs!B24*12,Inputs!B23*12))*(1+Inputs!B21)^MAX(0,75-Inputs!B25),0) -> 58073.956 | I13: =IF(70>=Inputs!B26,Inputs!B23*12*0.5*(1+Inputs!B21)^MAX(0,70-Inputs!B26),0) -> 26963.721 | J13: ='Roth Conversion'!E13 -> 121687.14 | K13: =MAX(0,G13-H13-I13-J13)*0.4 -> 0 | L13: =MAX(0,G13-H13-I13-J13-K13) -> 0 | M13: =F13 -> 3616.1461 | N13: =MAX(0,IF((J13+H13*Inputs!B43)<=23200,(J13+H13*Inputs!B43)*0.1,IF((J13+H13*Inputs!B43)<=94300,23200*0.1+((J13+H13*Inputs!B43)-23200)*0.12,IF((J13+H13*Inputs!B43)<=201050,23200*0.1+71100*0.12+((J13+H13*Inputs!B43)-94300)*0.22,23200*0.1+71100*0.12+106750*0.22+((J13+H13*Inputs!B43)-201050)*0.24)))) -> 27737 | O13: =J13*0.0637 -> 7751.4707 | P13: =H13+I13+J13+K13+L13-G13-N13-O13 -> 2231.2213
A14: 76 | B14: =Inputs!B29*12*(1+Inputs!B20)^11 -> 116275.65 | C14: =IF(Inputs!B51=1,0,IF((VALUE(A14)-Inputs!B5)>=MAX(0,Inputs!B48-(Inputs!B5-Inputs!B4)),0,Inputs!B30*12)) -> 36000 | D14: =Inputs!B31+Inputs!B32 -> 16500 | E14: =IF(71<65,Inputs!B35*12,0) -> 0 | F14: =Inputs!B33*12*(1+Inputs!B34)^11 -> 3796.9534 | G14: =B14+C14+D14+E14+F14 -> 172572.6 | H14: =IF(76>=Inputs!B25,IF(Inputs!B25=65,Inputs!B22*12,IF(Inputs!B25=70,Inputs!B24*12,Inputs!B23*12))*(1+Inputs!B21)^MAX(0,76-Inputs!B25),0) -> 59525.805 | I14: =IF(71>=Inputs!B26,Inputs!B23*12*0.5*(1+Inputs!B21)^MAX(0,71-Inputs!B26),0) -> 27637.814 | J14: ='Roth Conversion'!E14 -> 120453.07 | K14: =MAX(0,G14-H14-I14-J14)*0.4 -> 0 | L14: =MAX(0,G14-H14-I14-J14-K14) -> 0 | M14: =F14 -> 3796.9534 | N14: =MAX(0,IF((J14+H14*Inputs!B43)<=23200,(J14+H14*Inputs!B43)*0.1,IF((J14+H14*Inputs!B43)<=94300,23200*0.1+((J14+H14*Inputs!B43)-23200)*0.12,IF((J14+H14*Inputs!B43)<=201050,23200*0.1+71100*0.12+((J14+H14*Inputs!B43)-94300)*0.22,23200*0.1+71100*0.12+106750*0.22+((J14+H14*Inputs!B43)-201050)*0.24)))) -> 27737 | O14: =J14*0.0637 -> 7672.8603 | P14: =H14+I14+J14+K14+L14-G14-N14-O14 -> -365.77459
A15: 77 | B15: =Inputs!B29*12*(1+Inputs!B20)^12 -> 119763.91 | C15: =IF(Inputs!B51=1,0,IF((VALUE(A15)-Inputs!B5)>=MAX(0,Inputs!B48-(Inputs!B5-Inputs!B4)),0,Inputs!B30*12)) -> 36000 | D15: =Inputs!B31+Inputs!B32 -> 16500 | E15: =IF(72<65,Inputs!B35*12,0) -> 0 | F15: =Inputs!B33*12*(1+Inputs!B34)^12 -> 3986.801 | G15: =B15+C15+D15+E15+F15 -> 176250.72 | H15: =IF(77>=Inputs!B25,IF(Inputs!B25=65,Inputs!B22*12,IF(Inputs!B25=70,Inputs!B24*12,Inputs!B23*12))*(1+Inputs!B21)^MAX(0,77-Inputs!B25),0) -> 61013.95 | I15: =IF(72>=Inputs!B26,Inputs!B23*12*0.5*(1+Inputs!B21)^MAX(0,72-Inputs!B26),0) -> 28328.759 | J15: ='Roth Conversion'!E15 -> 119188.14 | K15: =MAX(0,G15-H15-I15-J15)*0.4 -> 0 | L15: =MAX(0,G15-H15-I15-J15-K15) -> 0 | M15: =F15 -> 3986.801 | N15: =MAX(0,IF((J15+H15*Inputs!B43)<=23200,(J15+H15*Inputs!B43)*0.1,IF((J15+H15*Inputs!B43)<=94300,23200*0.1+((J15+H15*Inputs!B43)-23200)*0.12,IF((J15+H15*Inputs!B43)<=201050,23200*0.1+71100*0.12+((J15+H15*Inputs!B43)-94300)*0.22,23200*0.1+71100*0.12+106750*0.22+((J15+H15*Inputs!B43)-201050)*0.24)))) -> 27737 | O15: =J15*0.0637 -> 7592.2847 | P15: =H15+I15+J15+K15+L15-G15-N15-O15 -> -3049.1489
A16: 78 | B16: =Inputs!B29*12*(1+Inputs!B20)^13 -> 123356.83 | C16: =IF(Inputs!B51=1,0,IF((VALUE(A16)-Inputs!B5)>=MAX(0,Inputs!B48-(Inputs!B5-Inputs!B4)),0,Inputs!B30*12)) -> 0 | D16: =Inputs!B31+Inputs!B32 -> 16500 | E16: =IF(73<65,Inputs!B35*12,0) -> 0 | F16: =Inputs!B33*12*(1+Inputs!B34)^13 -> 4186.1411 | G16: =B16+C16+D16+E16+F16 -> 144042.97 | H16: =IF(78>=Inputs!B25,IF(Inputs!B25=65,Inputs!B22*12,IF(Inputs!B25=70,Inputs!B24*12,Inputs!B23*12))*(1+Inputs!B21)^MAX(0,78-Inputs!B25),0) -> 62539.298 | I16: =IF(73>=Inputs!B26,Inputs!B23*12*0.5*(1+Inputs!B21)^MAX(0,73-Inputs!B26),0) -> 29036.978 | J16: ='Roth Conversion'!E16 -> 117891.6 | K16: =MAX(0,G16-H16-I16-J16)*0.4 -> 0 | L16: =MAX(0,G16-H16-I16-J16-K16) -> 0 | M16: =F16 -> 4186.1411 | N16: =MAX(0,IF((J16+H16*Inputs!B43)<=23200,(J16+H16*Inputs!B43)*0.1,IF((J16+H16*Inputs!B43)<=94300,23200*0.1+((J16+H16*Inputs!B43)-23200)*0.12,IF((J16+H16*Inputs!B43)<=201050,23200*0.1+71100*0.12+((J16+H16*Inputs!B43)-94300)*0.22,23200*0.1+71100*0.12+106750*0.22+((J16+H16*Inputs!B43)-201050)*0.24)))) -> 27737 | O16: =J16*0.0637 -> 7509.6947 | P16: =H16+I16+J16+K16+L16-G16-N16-O16 -> 30178.205
A17: 79 | B17: =Inputs!B29*12*(1+Inputs!B20)^14 -> 127057.54 | C17: =IF(Inputs!B51=1,0,IF((VALUE(A17)-Inputs!B5)>=MAX(0,Inputs!B48-(Inputs!B5-Inputs!B4)),0,Inputs!B30*12)) -> 0 | D17: =Inputs!B31+Inputs!B32 -> 16500 | E17: =IF(74<65,Inputs!B35*12,0) -> 0 | F17: =Inputs!B33*12*(1+Inputs!B34)^14 -> 4395.4482 | G17: =B17+C17+D17+E17+F17 -> 147952.99 | H17: =IF(79>=Inputs!B25,IF(Inputs!B25=65,Inputs!B22*12,IF(Inputs!B25=70,Inputs!B24*12,Inputs!B23*12))*(1+Inputs!B21)^MAX(0,79-Inputs!B25),0) -> 64102.781 | I17: =IF(74>=Inputs!B26,Inputs!B23*12*0.5*(1+Inputs!B21)^MAX(0,74-Inputs!B26),0) -> 29762.902 | J17: ='Roth Conversion'!E17 -> 116562.64 | K17: =MAX(0,G17-H17-I17-J17)*0.4 -> 0 | L17: =MAX(0,G17-H17-I17-J17-K17) -> 0 | M17: =F17 -> 4395.4482 | N17: =MAX(0,IF((J17+H17*Inputs!B43)<=23200,(J17+H17*Inputs!B43)*0.1,IF((J17+H17*Inputs!B43)<=94300,23200*0.1+((J17+H17*Inputs!B43)-23200)*0.12,IF((J17+H17*Inputs!B43)<=201050,23200*0.1+71100*0.12+((J17+H17*Inputs!B43)-94300)*0.22,23200*0.1+71100*0.12+106750*0.22+((J17+H17*Inputs!B43)-201050)*0.24)))) -> 27737 | O17: =J17*0.0637 -> 7425.0399 | P17: =H17+I17+J17+K17+L17-G17-N17-O17 -> 27313.294
A18: 80 | B18: =Inputs!B29*12*(1+Inputs!B20)^15 -> 130869.26 | C18: =IF(Inputs!B51=1,0,IF((VALUE(A18)-Inputs!B5)>=MAX(0,Inputs!B48-(Inputs!B5-Inputs!B4)),0,Inputs!B30*12)) -> 0 | D18: =Inputs!B31+Inputs!B32 -> 16500 | E18: =IF(75<65,Inputs!B35*12,0) -> 0 | F18: =Inputs!B33*12*(1+Inputs!B34)^15 -> 4615.2206 | G18: =B18+C18+D18+E18+F18 -> 151984.48 | H18: =IF(80>=Inputs!B25,IF(Inputs!B25=65,Inputs!B22*12,IF(Inputs!B25=70,Inputs!B24*12,Inputs!B23*12))*(1+Inputs!B21)^MAX(0,80-Inputs!B25),0) -> 65705.35 | I18: =IF(75>=Inputs!B26,Inputs!B23*12*0.5*(1+Inputs!B21)^MAX(0,75-Inputs!B26),0) -> 30506.975 | J18: ='Roth Conversion'!E18 -> 115200.45 | K18: =MAX(0,G18-H18-I18-J18)*0.4 -> 0 | L18: =MAX(0,G18-H18-I18-J18-K18) -> 0 | M18: =F18 -> 4615.2206 | N18: =MAX(0,IF((J18+H18*Inputs!B43)<=23200,(J18+H18*Inputs!B43)*0.1,IF((J18+H18*Inputs!B43)<=94300,23200*0.1+((J18+H18*Inputs!B43)-23200)*0.12,IF((J18+H18*Inputs!B43)<=201050,23200*0.1+71100*0.12+((J18+H18*Inputs!B43)-94300)*0.22,23200*0.1+71100*0.12+106750*0.22+((J18+H18*Inputs!B43)-201050)*0.24)))) -> 27737 | O18: =J18*0.0637 -> 7338.2688 | P18: =H18+I18+J18+K18+L18-G18-N18-O18 -> 24353.025
A19: 81 | B19: =Inputs!B29*12*(1+Inputs!B20)^16 -> 134795.34 | C19: =IF(Inputs!B51=1,0,IF((VALUE(A19)-Inputs!B5)>=MAX(0,Inputs!B48-(Inputs!B5-Inputs!B4)),0,Inputs!B30*12)) -> 0 | D19: =Inputs!B31+Inputs!B32 -> 16500 | E19: =IF(76<65,Inputs!B35*12,0) -> 0 | F19: =Inputs!B33*12*(1+Inputs!B34)^16 -> 4845.9816 | G19: =B19+C19+D19+E19+F19 -> 156141.32 | H19: =IF(81>=Inputs!B25,IF(Inputs!B25=65,Inputs!B22*12,IF(Inputs!B25=70,Inputs!B24*12,Inputs!B23*12))*(1+Inputs!B21)^MAX(0,81-Inputs!B25),0) -> 67347.984 | I19: =IF(76>=Inputs!B26,Inputs!B23*12*0.5*(1+Inputs!B21)^MAX(0,76-Inputs!B26),0) -> 31269.649 | J19: ='Roth Conversion'!E19 -> 113804.21 | K19: =MAX(0,G19-H19-I19-J19)*0.4 -> 0 | L19: =MAX(0,G19-H19-I19-J19-K19) -> 0 | M19: =F19 -> 4845.9816 | N19: =MAX(0,IF((J19+H19*Inputs!B43)<=23200,(J19+H19*Inputs!B43)*0.1,IF((J19+H19*Inputs!B43)<=94300,23200*0.1+((J19+H19*Inputs!B43)-23200)*0.12,IF((J19+H19*Inputs!B43)<=201050,23200*0.1+71100*0.12+((J19+H19*Inputs!B43)-94300)*0.22,23200*0.1+71100*0.12+106750*0.22+((J19+H19*Inputs!B43)-201050)*0.24)))) -> 27737 | O19: =J19*0.0637 -> 7249.3284 | P19: =H19+I19+J19+K19+L19-G19-N19-O19 -> 21294.196
A20: 82 | B20: =Inputs!B29*12*(1+Inputs!B20)^17 -> 138839.2 | C20: =IF(Inputs!B51=1,0,IF((VALUE(A20)-Inputs!B5)>=MAX(0,Inputs!B48-(Inputs!B5-Inputs!B4)),0,Inputs!B30*12)) -> 0 | D20: =Inputs!B31+Inputs!B32 -> 16500 | E20: =IF(77<65,Inputs!B35*12,0) -> 0 | F20: =Inputs!B33*12*(1+Inputs!B34)^17 -> 5088.2807 | G20: =B20+C20+D20+E20+F20 -> 160427.48 | H20: =IF(82>=Inputs!B25,IF(Inputs!B25=65,Inputs!B22*12,IF(Inputs!B25=70,Inputs!B24*12,Inputs!B23*12))*(1+Inputs!B21)^MAX(0,82-Inputs!B25),0) -> 69031.684 | I20: =IF(77>=Inputs!B26,Inputs!B23*12*0.5*(1+Inputs!B21)^MAX(0,77-Inputs!B26),0) -> 32051.39 | J20: ='Roth Conversion'!E20 -> 112373.07 | K20: =MAX(0,G20-H20-I20-J20)*0.4 -> 0 | L20: =MAX(0,G20-H20-I20-J20-K20) -> 0 | M20: =F20 -> 5088.2807 | N20: =MAX(0,IF((J20+H20*Inputs!B43)<=23200,(J20+H20*Inputs!B43)*0.1,IF((J20+H20*Inputs!B43)<=94300,23200*0.1+((J20+H20*Inputs!B43)-23200)*0.12,IF((J20+H20*Inputs!B43)<=201050,23200*0.1+71100*0.12+((J20+H20*Inputs!B43)-94300)*0.22,23200*0.1+71100*0.12+106750*0.22+((J20+H20*Inputs!B43)-201050)*0.24)))) -> 27737 | O20: =J20*0.0637 -> 7158.1645 | P20: =H20+I20+J20+K20+L20-G20-N20-O20 -> 18133.497
A21: 83 | B21: =Inputs!B29*12*(1+Inputs!B20)^18 -> 143004.38 | C21: =IF(Inputs!B51=1,0,IF((VALUE(A21)-Inputs!B5)>=MAX(0,Inputs!B48-(Inputs!B5-Inputs!B4)),0,Inputs!B30*12)) -> 0 | D21: =Inputs!B31+Inputs!B32 -> 16500 | E21: =IF(78<65,Inputs!B35*12,0) -> 0 | F21: =Inputs!B33*12*(1+Inputs!B34)^18 -> 5342.6947 | G21: =B21+C21+D21+E21+F21 -> 164847.07 | H21: =IF(83>=Inputs!B25,IF(Inputs!B25=65,Inputs!B22*12,IF(Inputs!B25=70,Inputs!B24*12,Inputs!B23*12))*(1+Inputs!B21)^MAX(0,83-Inputs!B25),0) -> 70757.476 | I21: =IF(78>=Inputs!B26,Inputs!B23*12*0.5*(1+Inputs!B21)^MAX(0,78-Inputs!B26),0) -> 32852.675 | J21: ='Roth Conversion'!E21 -> 110906.15 | K21: =MAX(0,G21-H21-I21-J21)*0.4 -> 0 | L21: =MAX(0,G21-H21-I21-J21-K21) -> 0 | M21: =F21 -> 5342.6947 | N21: =MAX(0,IF((J21+H21*Inputs!B43)<=23200,(J21+H21*Inputs!B43)*0.1,IF((J21+H21*Inputs!B43)<=94300,23200*0.1+((J21+H21*Inputs!B43)-23200)*0.12,IF((J21+H21*Inputs!B43)<=201050,23200*0.1+71100*0.12+((J21+H21*Inputs!B43)-94300)*0.22,23200*0.1+71100*0.12+106750*0.22+((J21+H21*Inputs!B43)-201050)*0.24)))) -> 27737 | O21: =J21*0.0637 -> 7064.7215 | P21: =H21+I21+J21+K21+L21-G21-N21-O21 -> 14867.503
A22: 84 | B22: =Inputs!B29*12*(1+Inputs!B20)^19 -> 147294.51 | C22: =IF(Inputs!B51=1,0,IF((VALUE(A22)-Inputs!B5)>=MAX(0,Inputs!B48-(Inputs!B5-Inputs!B4)),0,Inputs!B30*12)) -> 0 | D22: =Inputs!B31+Inputs!B32 -> 16500 | E22: =IF(79<65,Inputs!B35*12,0) -> 0 | F22: =Inputs!B33*12*(1+Inputs!B34)^19 -> 5609.8294 | G22: =B22+C22+D22+E22+F22 -> 169404.34 | H22: =IF(84>=Inputs!B25,IF(Inputs!B25=65,Inputs!B22*12,IF(Inputs!B25=70,Inputs!B24*12,Inputs!B23*12))*(1+Inputs!B21)^MAX(0,84-Inputs!B25),0) -> 72526.413 | I22: =IF(79>=Inputs!B26,Inputs!B23*12*0.5*(1+Inputs!B21)^MAX(0,79-Inputs!B26),0) -> 33673.992 | J22: ='Roth Conversion'!E22 -> 109402.55 | K22: =MAX(0,G22-H22-I22-J22)*0.4 -> 0 | L22: =MAX(0,G22-H22-I22-J22-K22) -> 0 | M22: =F22 -> 5609.8294 | N22: =MAX(0,IF((J22+H22*Inputs!B43)<=23200,(J22+H22*Inputs!B43)*0.1,IF((J22+H22*Inputs!B43)<=94300,23200*0.1+((J22+H22*Inputs!B43)-23200)*0.12,IF((J22+H22*Inputs!B43)<=201050,23200*0.1+71100*0.12+((J22+H22*Inputs!B43)-94300)*0.22,23200*0.1+71100*0.12+106750*0.22+((J22+H22*Inputs!B43)-201050)*0.24)))) -> 27737 | O22: =J22*0.0637 -> 6968.9424 | P22: =H22+I22+J22+K22+L22-G22-N22-O22 -> 11492.674
A23: 85 | B23: =Inputs!B29*12*(1+Inputs!B20)^20 -> 151713.34 | C23: =IF(Inputs!B51=1,0,IF((VALUE(A23)-Inputs!B5)>=MAX(0,Inputs!B48-(Inputs!B5-Inputs!B4)),0,Inputs!B30*12)) -> 0 | D23: =Inputs!B31+Inputs!B32 -> 16500 | E23: =IF(80<65,Inputs!B35*12,0) -> 0 | F23: =Inputs!B33*12*(1+Inputs!B34)^20 -> 5890.3209 | G23: =B23+C23+D23+E23+F23 -> 174103.66 | H23: =IF(85>=Inputs!B25,IF(Inputs!B25=65,Inputs!B22*12,IF(Inputs!B25=70,Inputs!B24*12,Inputs!B23*12))*(1+Inputs!B21)^MAX(0,85-Inputs!B25),0) -> 74339.573 | I23: =IF(80>=Inputs!B26,Inputs!B23*12*0.5*(1+Inputs!B21)^MAX(0,80-Inputs!B26),0) -> 34515.842 | J23: ='Roth Conversion'!E23 -> 107861.36 | K23: =MAX(0,G23-H23-I23-J23)*0.4 -> 0 | L23: =MAX(0,G23-H23-I23-J23-K23) -> 0 | M23: =F23 -> 5890.3209 | N23: =MAX(0,IF((J23+H23*Inputs!B43)<=23200,(J23+H23*Inputs!B43)*0.1,IF((J23+H23*Inputs!B43)<=94300,23200*0.1+((J23+H23*Inputs!B43)-23200)*0.12,IF((J23+H23*Inputs!B43)<=201050,23200*0.1+71100*0.12+((J23+H23*Inputs!B43)-94300)*0.22,23200*0.1+71100*0.12+106750*0.22+((J23+H23*Inputs!B43)-201050)*0.24)))) -> 27737 | O23: =J23*0.0637 -> 6870.7688 | P23: =H23+I23+J23+K23+L23-G23-N23-O23 -> 8005.3444

Sheet RMD
A1: REQUIRED MINIMUM DISTRIBUTIONS (Ages 73–85) | L1: IRS Uniform Lifetime Table
A2: RMDs begin at age 73 (SECURE 2.0). RMD = Trad 401k balance ÷ IRS Uniform Lifetime Factor. Roth conversion is done first; any remaining capacity can add extra conversions above RMD. RMD is mandatory income — taxed as ordinary income.
A3: Age | B3: Trad 401k Jan 1 ($) | C3: IRS Factor | D3: RMD Required ($) | E3: Roth Conv Done ($) | F3: Extra Conv Possible ($) | G3: Total Trad Draw ($) | H3: Fed Tax on Draw ($) | I3: State Tax ($) | J3: Net After Tax ($)
A4: 73 | B4: ='Roth Conversion'!B11 -> 1890395.3 | C4: =VLOOKUP(A4,L$4:M$16,2,0) -> 26.5 | D4: =IFERROR(ROUND(B4/C4,0),0) -> 71336 | E4: ='Roth Conversion'!E11 -> 124065.72 | F4: =MAX(0,D4-E4) -> 0 | G4: =MAX(D4,E4) -> 124065.72 | H4: =MAX(0,IF((G4+'Withdrawal Plan'!H11*Inputs!B43)<=23200,(G4+'Withdrawal Plan'!H11*Inputs!B43)*0.1,IF((G4+'Withdrawal Plan'!H11*Inputs!B43)<=94300,23200*0.1+(G4+'Withdrawal Plan'!H11*Inputs!B43-23200)*0.12,IF((G4+'Withdrawal Plan'!H11*Inputs!B43)<=201050,23200*0.1+71100*0.12+(G4+'Withdrawal Plan'!H11*Inputs!B43-94300)*0.22,23200*0.1+71100*0.12+106750*0.22+(G4+'Withdrawal Plan'!H11*Inputs!B43-201050)*0.24)))) -> 27737 | I4: =ROUND(G4*0.0637,0) -> 7903 | J4: =G4-H4-I4 -> 88425.717 | L4: 73 | M4: 26.5
A5: 74 | B5: ='Roth Conversion'!B12 -> 1766329.6 | C5: =VLOOKUP(A5,L$4:M$16,2,0) -> 25.5 | D5: =IFERROR(ROUND(B5/C5,0),0) -> 69268 | E5: ='Roth Conversion'!E12 -> 122891.11 | F5: =MAX(0,D5-E5) -> 0 | G5: =MAX(D5,E5) -> 122891.11 | H5: =MAX(0,IF((G5+'Withdrawal Plan'!H12*Inputs!B43)<=23200,(G5+'Withdrawal Plan'!H12*Inputs!B43)*0.1,IF((G5+'Withdrawal Plan'!H12*Inputs!B43)<=94300,23200*0.1+(G5+'Withdrawal Plan'!H12*Inputs!B43-23200)*0.12,IF((G5+'Withdrawal Plan'!H12*Inputs!B43)<=201050,23200*0.1+71100*0.12+(G5+'Withdrawal Plan'!H12*Inputs!B43-94300)*0.22,23200*0.1+71100*0.12+106750*0.22+(G5+'Withdrawal Plan'!H12*Inputs!B43-201050)*0.24)))) -> 27737 | I5: =ROUND(G5*0.0637,0) -> 7828 | J5: =G5-H5-I5 -> 87326.11 | L5: 74 | M5: 25.5
A6: 75 | B6: ='Roth Conversion'!B13 -> 1643438.5 | C6: =VLOOKUP(A6,L$4:M$16,2,0) -> 24.6 | D6: =IFERROR(ROUND(B6/C6,0),0) -> 66806 | E6: ='Roth Conversion'!E13 -> 121687.14 | F6: =MAX(0,D6-E6) -> 0 | G6: =MAX(D6,E6) -> 121687.14 | H6: =MAX(0,IF((G6+'Withdrawal Plan'!H13*Inputs!B43)<=23200,(G6+'Withdrawal Plan'!H13*Inputs!B43)*0.1,IF((G6+'Withdrawal Plan'!H13*Inputs!B43)<=94300,23200*0.1+(G6+'Withdrawal Plan'!H13*Inputs!B43-23200)*0.12,IF((G6+'Withdrawal Plan'!H13*Inputs!B43)<=201050,23200*0.1+71100*0.12+(G6+'Withdrawal Plan'!H13*Inputs!B43-94300)*0.22,23200*0.1+71100*0.12+106750*0.22+(G6+'Withdrawal Plan'!H13*Inputs!B43-201050)*0.24)))) -> 27737 | I6: =ROUND(G6*0.0637,0) -> 7751 | J6: =G6-H6-I6 -> 86199.138 | L6: 75 | M6: 24.6
A7: 76 | B7: ='Roth Conversion'!B14 -> 1521751.4 | C7: =VLOOKUP(A7,L$4:M$16,2,0) -> 23.7 | D7: =IFERROR(ROUND(B7/C7,0),0) -> 64209 | E7: ='Roth Conversion'!E14 -> 120453.07 | F7: =MAX(0,D7-E7) -> 0 | G7: =MAX(D7,E7) -> 120453.07 | H7: =MAX(0,IF((G7+'Withdrawal Plan'!H14*Inputs!B43)<=23200,(G7+'Withdrawal Plan'!H14*Inputs!B43)*0.1,IF((G7+'Withdrawal Plan'!H14*Inputs!B43)<=94300,23200*0.1+(G7+'Withdrawal Plan'!H14*Inputs!B43-23200)*0.12,IF((G7+'Withdrawal Plan'!H14*Inputs!B43)<=201050,23200*0.1+71100*0.12+(G7+'Withdrawal Plan'!H14*Inputs!B43-94300)*0.22,23200*0.1+71100*0.12+106750*0.22+(G7+'Withdrawal Plan'!H14*Inputs!B43-201050)*0.24)))) -> 27737 | I7: =ROUND(G7*0.0637,0) -> 7673 | J7: =G7-H7-I7 -> 85043.066 | L7: 76 | M7: 23.7
A8: 77 | B8: ='Roth Conversion'!B15 -> 1401298.3 | C8: =VLOOKUP(A8,L$4:M$16,2,0) -> 22.9 | D8: =IFERROR(ROUND(B8/C8,0),0) -> 61192 | E8: ='Roth Conversion'!E15 -> 119188.14 | F8: =MAX(0,D8-E8) -> 0 | G8: =MAX(D8,E8) -> 119188.14 | H8: =MAX(0,IF((G8+'Withdrawal Plan'!H15*Inputs!B43)<=23200,(G8+'Withdrawal Plan'!H15*Inputs!B43)*0.1,IF((G8+'Withdrawal Plan'!H15*Inputs!B43)<=94300,23200*0.1+(G8+'Withdrawal Plan'!H15*Inputs!B43-23200)*0.12,IF((G8+'Withdrawal Plan'!H15*Inputs!B43)<=201050,23200*0.1+71100*0.12+(G8+'Withdrawal Plan'!H15*Inputs!B43-94300)*0.22,23200*0.1+71100*0.12+106750*0.22+(G8+'Withdrawal Plan'!H15*Inputs!B43-201050)*0.24)))) -> 27737 | I8: =ROUND(G8*0.0637,0) -> 7592 | J8: =G8-H8-I8 -> 83859.143 | L8: 77 | M8: 22.9
A9: 78 | B9: ='Roth Conversion'!B16 -> 1282110.1 | C9: =VLOOKUP(A9,L$4:M$16,2,0) -> 22 | D9: =IFERROR(ROUND(B9/C9,0),0) -> 58278 | E9: ='Roth Conversion'!E16 -> 117891.6 | F9: =MAX(0,D9-E9) -> 0 | G9: =MAX(D9,E9) -> 117891.6 | H9: =MAX(0,IF((G9+'Withdrawal Plan'!H16*Inputs!B43)<=23200,(G9+'Withdrawal Plan'!H16*Inputs!B43)*0.1,IF((G9+'Withdrawal Plan'!H16*Inputs!B43)<=94300,23200*0.1+(G9+'Withdrawal Plan'!H16*Inputs!B43-23200)*0.12,IF((G9+'Withdrawal Plan'!H16*Inputs!B43)<=201050,23200*0.1+71100*0.12+(G9+'Withdrawal Plan'!H16*Inputs!B43-94300)*0.22,23200*0.1+71100*0.12+106750*0.22+(G9+'Withdrawal Plan'!H16*Inputs!B43-201050)*0.24)))) -> 27737 | I9: =ROUND(G9*0.0637,0) -> 7510 | J9: =G9-H9-I9 -> 82644.596 | L9: 78 | M9: 22
A10: 79 | B10: ='Roth Conversion'!B17 -> 1164218.6 | C10: =VLOOKUP(A10,L$4:M$16,2,0) -> 21.1 | D10: =IFERROR(ROUND(B10/C10,0),0) -> 55176 | E10: ='Roth Conversion'!E17 -> 116562.64 | F10: =MAX(0,D10-E10) -> 0 | G10: =MAX(D10,E10) -> 116562.64 | H10: =MAX(0,IF((G10+'Withdrawal Plan'!H17*Inputs!B43)<=23200,(G10+'Withdrawal Plan'!H17*Inputs!B43)*0.1,IF((G10+'Withdrawal Plan'!H17*Inputs!B43)<=94300,23200*0.1+(G10+'Withdrawal Plan'!H17*Inputs!B43-23200)*0.12,IF((G10+'Withdrawal Plan'!H17*Inputs!B43)<=201050,23200*0.1+71100*0.12+(G10+'Withdrawal Plan'!H17*Inputs!B43-94300)*0.22,23200*0.1+71100*0.12+106750*0.22+(G10+'Withdrawal Plan'!H17*Inputs!B43-201050)*0.24)))) -> 27737 | I10: =ROUND(G10*0.0637,0) -> 7425 | J10: =G10-H10-I10 -> 81400.636 | L10: 79 | M10: 21.1
A11: 80 | B11: ='Roth Conversion'!B18 -> 1047655.9 | C11: =VLOOKUP(A11,L$4:M$16,2,0) -> 20.2 | D11: =IFERROR(ROUND(B11/C11,0),0) -> 51864 | E11: ='Roth Conversion'!E18 -> 115200.45 | F11: =MAX(0,D11-E11) -> 0 | G11: =MAX(D11,E11) -> 115200.45 | H11: =MAX(0,IF((G11+'Withdrawal Plan'!H18*Inputs!B43)<=23200,(G11+'Withdrawal Plan'!H18*Inputs!B43)*0.1,IF((G11+'Withdrawal Plan'!H18*Inputs!B43)<=94300,23200*0.1+(G11+'Withdrawal Plan'!H18*Inputs!B43-23200)*0.12,IF((G11+'Withdrawal Plan'!H18*Inputs!B43)<=201050,23200*0.1+71100*0.12+(G11+'Withdrawal Plan'!H18*Inputs!B43-94300)*0.22,23200*0.1+71100*0.12+106750*0.22+(G11+'Withdrawal Plan'!H18*Inputs!B43-201050)*0.24)))) -> 27737 | I11: =ROUND(G11*0.0637,0) -> 7338 | J11: =G11-H11-I11 -> 80125.452 | L11: 80 | M11: 20.2
A12: 81 | B12: ='Roth Conversion'!B19 -> 932455.46 | C12: =VLOOKUP(A12,L$4:M$16,2,0) -> 19.4 | D12: =IFERROR(ROUND(B12/C12,0),0) -> 48065 | E12: ='Roth Conversion'!E19 -> 113804.21 | F12: =MAX(0,D12-E12) -> 0 | G12: =MAX(D12,E12) -> 113804.21 | H12: =MAX(0,IF((G12+'Withdrawal Plan'!H19*Inputs!B43)<=23200,(G12+'Withdrawal Plan'!H19*Inputs!B43)*0.1,IF((G12+'Withdrawal Plan'!H19*Inputs!B43)<=94300,23200*0.1+(G12+'Withdrawal Plan'!H19*Inputs!B43-23200)*0.12,IF((G12+'Withdrawal Plan'!H19*Inputs!B43)<=201050,23200*0.1+71100*0.12+(G12+'Withdrawal Plan'!H19*Inputs!B43-94300)*0.22,23200*0.1+71100*0.12+106750*0.22+(G12+'Withdrawal Plan'!H19*Inputs!B43-201050)*0.24)))) -> 27737 | I12: =ROUND(G12*0.0637,0) -> 7249 | J12: =G12-H12-I12 -> 78818.213 | L12: 81 | M12: 19.4
A13: 82 | B13: ='Roth Conversion'!B20 -> 818651.25 | C13: =VLOOKUP(A13,L$4:M$16,2,0) -> 18.5 | D13: =IFERROR(ROUND(B13/C13,0),0) -> 44251 | E13: ='Roth Conversion'!E20 -> 112373.07 | F13: =MAX(0,D13-E13) -> 0 | G13: =MAX(D13,E13) -> 112373.07 | H13: =MAX(0,IF((G13+'Withdrawal Plan'!H20*Inputs!B43)<=23200,(G13+'Withdrawal Plan'!H20*Inputs!B43)*0.1,IF((G13+'Withdrawal Plan'!H20*Inputs!B43)<=94300,23200*0.1+(G13+'Withdrawal Plan'!H20*Inputs!B43-23200)*0.12,IF((G13+'Withdrawal Plan'!H20*Inputs!B43)<=201050,23200*0.1+71100*0.12+(G13+'Withdrawal Plan'!H20*Inputs!B43-94300)*0.22,23200*0.1+71100*0.12+106750*0.22+(G13+'Withdrawal Plan'!H20*Inputs!B43-201050)*0.24)))) -> 27737 | I13: =ROUND(G13*0.0637,0) -> 7158 | J13: =G13-H13-I13 -> 77478.069 | L13: 82 | M13: 18.5
A14: 83 | B14: ='Roth Conversion'!B21 -> 706278.18 | C14: =VLOOKUP(A14,L$4:M$16,2,0) -> 17.7 | D14: =IFERROR(ROUND(B14/C14,0),0) -> 39903 | E14: ='Roth Conversion'!E21 -> 110906.15 | F14: =MAX(0,D14-E14) -> 0 | G14: =MAX(D14,E14) -> 110906.15 | H14: =MAX(0,IF((G14+'Withdrawal Plan'!H21*Inputs!B43)<=23200,(G14+'Withdrawal Plan'!H21*Inputs!B43)*0.1,IF((G14+'Withdrawal Plan'!H21*Inputs!B43)<=94300,23200*0.1+(G14+'Withdrawal Plan'!H21*Inputs!B43-23200)*0.12,IF((G14+'Withdrawal Plan'!H21*Inputs!B43)<=201050,23200*0.1+71100*0.12+(G14+'Withdrawal Plan'!H21*Inputs!B43-94300)*0.22,23200*0.1+71100*0.12+106750*0.22+(G14+'Withdrawal Plan'!H21*Inputs!B43-201050)*0.24)))) -> 27737 | I14: =ROUND(G14*0.0637,0) -> 7065 | J14: =G14-H14-I14 -> 76104.145 | L14: 83 | M14: 17.7
A15: 84 | B15: ='Roth Conversion'!B22 -> 595372.04 | C15: =VLOOKUP(A15,L$4:M$16,2,0) -> 16.8 | D15: =IFERROR(ROUND(B15/C15,0),0) -> 35439 | E15: ='Roth Conversion'!E22 -> 109402.55 | F15: =MAX(0,D15-E15) -> 0 | G15: =MAX(D15,E15) -> 109402.55 | H15: =MAX(0,IF((G15+'Withdrawal Plan'!H22*Inputs!B43)<=23200,(G15+'Withdrawal Plan'!H22*Inputs!B43)*0.1,IF((G15+'Withdrawal Plan'!H22*Inputs!B43)<=94300,23200*0.1+(G15+'Withdrawal Plan'!H22*Inputs!B43-23200)*0.12,IF((G15+'Withdrawal Plan'!H22*Inputs!B43)<=201050,23200*0.1+71100*0.12+(G15+'Withdrawal Plan'!H22*Inputs!B43-94300)*0.22,23200*0.1+71100*0.12+106750*0.22+(G15+'Withdrawal Plan'!H22*Inputs!B43-201050)*0.24)))) -> 27737 | I15: =ROUND(G15*0.0637,0) -> 6969 | J15: =G15-H15-I15 -> 74696.549 | L15: 84 | M15: 16.8
A16: 85 | B16: ='Roth Conversion'!B23 -> 485969.49 | C16: =VLOOKUP(A16,L$4:M$16,2,0) -> 16 | D16: =IFERROR(ROUND(B16/C16,0),0) -> 30373 | E16: ='Roth Conversion'!E23 -> 107861.36 | F16: =MAX(0,D16-E16) -> 0 | G16: =MAX(D16,E16) -> 107861.36 | H16: =MAX(0,IF((G16+'Withdrawal Plan'!H23*Inputs!B43)<=23200,(G16+'Withdrawal Plan'!H23*Inputs!B43)*0.1,IF((G16+'Withdrawal Plan'!H23*Inputs!B43)<=94300,23200*0.1+(G16+'Withdrawal Plan'!H23*Inputs!B43-23200)*0.12,IF((G16+'Withdrawal Plan'!H23*Inputs!B43)<=201050,23200*0.1+71100*0.12+(G16+'Withdrawal Plan'!H23*Inputs!B43-94300)*0.22,23200*0.1+71100*0.12+106750*0.22+(G16+'Withdrawal Plan'!H23*Inputs!B43-201050)*0.24)))) -> 27737 | I16: =ROUND(G16*0.0637,0) -> 6871 | J16: =G16-H16-I16 -> 73253.363 | L16: 85 | M16: 16
A17: TOTALS | B17: =SUM(B4:B16) -> 15255924 | C17: =SUM(C4:C16) -> 274.9 | D17: =SUM(D4:D16) -> 696160 | E17: =SUM(E4:E16) -> 1512287.2 | F17: =SUM(F4:F16) -> 0 | G17: =SUM(G4:G16) -> 1512287.2 | H17: =SUM(H4:H16) -> 360581 | I17: =SUM(I4:I16) -> 96332 | J17: =SUM(J4:J16) -> 1055374.2

Sheet Tax Projection
A1: ANNUAL TAX PROJECTION (Ages 65–85)
A2: Full simulated tax return for each retirement year. Marginal rate = highest bracket reached. Effective rate = total fed tax ÷ total taxable income. IRMAA thresholds: Base ≤$206k, T1 ≤$258k, T2 ≤$322k, T3 ≤$386k, T4 ≤$750k, T5 >$750k (per person surcharge).
A3: Age | B3: Your SS ($) | C3: Wife SS ($) | D3: Roth Conv ($) | E3: SS Taxable ($) | F3: Gross Taxable ($) | G3: Std Ded ($) | H3: Net Taxable ($) | I3: Marginal Rate | J3: Fed Tax ($) | K3: Eff Rate | L3: IRMAA Tier | M3: NJ State Tax ($) | N3: Total Tax ($)
A4: 65 | B4: ='Withdrawal Plan'!H3 -> 0 | C4: ='Withdrawal Plan'!I3 -> 0 | D4: ='Roth Conversion'!E3 -> 171050 | E4: =(B4+C4)*Inputs!B43 -> 0 | F4: =D4+E4 -> 171050 | G4: =Inputs!B42 -> 30000 | H4: =MAX(0,F4-G4) -> 141050 | I4: =IF(H4<=23200,"10%",IF(H4<=94300,"12%",IF(H4<=201050,"22%",IF(H4<=383900,"24%","32%+")))) -> 22% | J4: =MAX(0,IF(H4<=23200,H4*0.1,IF(H4<=94300,23200*0.1+(H4-23200)*0.12,IF(H4<=201050,23200*0.1+71100*0.12+(H4-94300)*0.22,23200*0.1+71100*0.12+106750*0.22+(H4-201050)*0.24)))) -> 21137 | K4: =IFERROR(J4/MAX(1,H4),0) -> 0.14985466 | L4: =IF(F4<=206000,"Base $0",IF(F4<=258000,"T1 $594",IF(F4<=322000,"T2 $1,488",IF(F4<=386000,"T3 $2,382",IF(F4<=750000,"T4 $3,276","T5 $4,170"))))) -> Base $0 | M4: =ROUND(D4*0.0637,0) -> 10896 | N4: =J4+M4 -> 32033
A5: 66 | B5: ='Withdrawal Plan'!H4 -> 0 | C5: ='Withdrawal Plan'!I4 -> 0 | D5: ='Roth Conversion'!E4 -> 171050 | E5: =(B5+C5)*Inputs!B43 -> 0 | F5: =D5+E5 -> 171050 | G5: =Inputs!B42 -> 30000 | H5: =MAX(0,F5-G5) -> 141050 | I5: =IF(H5<=23200,"10%",IF(H5<=94300,"12%",IF(H5<=201050,"22%",IF(H5<=383900,"24%","32%+")))) -> 22% | J5: =MAX(0,IF(H5<=23200,H5*0.1,IF(H5<=94300,23200*0.1+(H5-23200)*0.12,IF(H5<=201050,23200*0.1+71100*0.12+(H5-94300)*0.22,23200*0.1+71100*0.12+106750*0.22+(H5-201050)*0.24)))) -> 21137 | K5: =IFERROR(J5/MAX(1,H5),0) -> 0.14985466 | L5: =IF(F5<=206000,"Base $0",IF(F5<=258000,"T1 $594",IF(F5<=322000,"T2 $1,488",IF(F5<=386000,"T3 $2,382",IF(F5<=750000,"T4 $3,276","T5 $4,170"))))) -> Base $0 | M5: =ROUND(D5*0.0637,0) -> 10896 | N5: =J5+M5 -> 32033
A6: 67 | B6: ='Withdrawal Plan'!H5 -> 47664 | C6: ='Withdrawal Plan'!I5 -> 0 | D6: ='Roth Conversion'!E5 -> 130535.6 | E6: =(B6+C6)*Inputs!B43 -> 40514.4 | F6: =D6+E6 -> 171050 | G6: =Inputs!B42 -> 30000 | H6: =MAX(0,F6-G6) -> 141050 | I6: =IF(H6<=23200,"10%",IF(H6<=94300,"12%",IF(H6<=201050,"22%",IF(H6<=383900,"24%","32%+")))) -> 22% | J6: =MAX(0,IF(H6<=23200,H6*0.1,IF(H6<=94300,23200*0.1+(H6-23200)*0.12,IF(H6<=201050,23200*0.1+71100*0.12+(H6-94300)*0.22,23200*0.1+71100*0.12+106750*0.22+(H6-201050)*0.24)))) -> 21137 | K6: =IFERROR(J6/MAX(1,H6),0) -> 0.14985466 | L6: =IF(F6<=206000,"Base $0",IF(F6<=258000,"T1 $594",IF(F6<=322000,"T2 $1,488",IF(F6<=386000,"T3 $2,382",IF(F6<=750000,"T4 $3,276","T5 $4,170"))))) -> Base $0 | M6: =ROUND(D6*0.0637,0) -> 8315 | N6: =J6+M6 -> 29452
A7: 68 | B7: ='Withdrawal Plan'!H6 -> 48855.6 | C7: ='Withdrawal Plan'!I6 -> 0 | D7: ='Roth Conversion'!E6 -> 129522.74 | E7: =(B7+C7)*Inputs!B43 -> 41527.26 | F7: =D7+E7 -> 171050 | G7: =Inputs!B42 -> 30000 | H7: =MAX(0,F7-G7) -> 141050 | I7: =IF(H7<=23200,"10%",IF(H7<=94300,"12%",IF(H7<=201050,"22%",IF(H7<=383900,"24%","32%+")))) -> 22% | J7: =MAX(0,IF(H7<=23200,H7*0.1,IF(H7<=94300,23200*0.1+(H7-23200)*0.12,IF(H7<=201050,23200*0.1+71100*0.12+(H7-94300)*0.22,23200*0.1+71100*0.12+106750*0.22+(H7-201050)*0.24)))) -> 21137 | K7: =IFERROR(J7/MAX(1,H7),0) -> 0.14985466 | L7: =IF(F7<=206000,"Base $0",IF(F7<=258000,"T1 $594",IF(F7<=322000,"T2 $1,488",IF(F7<=386000,"T3 $2,382",IF(F7<=750000,"T4 $3,276","T5 $4,170"))))) -> Base $0 | M7: =ROUND(D7*0.0637,0) -> 8251 | N7: =J7+M7 -> 29388
A8: 69 | B8: ='Withdrawal Plan'!H7 -> 50076.99 | C8: ='Withdrawal Plan'!I7 -> 0 | D8: ='Roth Conversion'!E7 -> 128484.56 | E8: =(B8+C8)*Inputs!B43 -> 42565.442 | F8: =D8+E8 -> 171050 | G8: =Inputs!B42 -> 30000 | H8: =MAX(0,F8-G8) -> 141050 | I8: =IF(H8<=23200,"10%",IF(H8<=94300,"12%",IF(H8<=201050,"22%",IF(H8<=383900,"24%","32%+")))) -> 22% | J8: =MAX(0,IF(H8<=23200,H8*0.1,IF(H8<=94300,23200*0.1+(H8-23200)*0.12,IF(H8<=201050,23200*0.1+71100*0.12+(H8-94300)*0.22,23200*0.1+71100*0.12+106750*0.22+(H8-201050)*0.24)))) -> 21137 | K8: =IFERROR(J8/MAX(1,H8),0) -> 0.14985466 | L8: =IF(F8<=206000,"Base $0",IF(F8<=258000,"T1 $594",IF(F8<=322000,"T2 $1,488",IF(F8<=386000,"T3 $2,382",IF(F8<=750000,"T4 $3,276","T5 $4,170"))))) -> Base $0 | M8: =ROUND(D8*0.0637,0) -> 8184 | N8: =J8+M8 -> 29321
A9: 70 | B9: ='Withdrawal Plan'!H8 -> 51328.915 | C9: ='Withdrawal Plan'!I8 -> 23832 | D9: ='Roth Conversion'!E8 -> 127420.42 | E9: =(B9+C9)*Inputs!B43 -> 63886.778 | F9: =D9+E9 -> 191307.2 | G9: =Inputs!B42 -> 30000 | H9: =MAX(0,F9-G9) -> 161307.2 | I9: =IF(H9<=23200,"10%",IF(H9<=94300,"12%",IF(H9<=201050,"22%",IF(H9<=383900,"24%","32%+")))) -> 22% | J9: =MAX(0,IF(H9<=23200,H9*0.1,IF(H9<=94300,23200*0.1+(H9-23200)*0.12,IF(H9<=201050,23200*0.1+71100*0.12+(H9-94300)*0.22,23200*0.1+71100*0.12+106750*0.22+(H9-201050)*0.24)))) -> 25593.584 | K9: =IFERROR(J9/MAX(1,H9),0) -> 0.15866362 | L9: =IF(F9<=206000,"Base $0",IF(F9<=258000,"T1 $594",IF(F9<=322000,"T2 $1,488",IF(F9<=386000,"T3 $2,382",IF(F9<=750000,"T4 $3,276","T5 $4,170"))))) -> Base $0 | M9: =ROUND(D9*0.0637,0) -> 8117 | N9: =J9+M9 -> 33710.584
A10: 71 | B10: ='Withdrawal Plan'!H9 -> 52612.138 | C10: ='Withdrawal Plan'!I9 -> 24427.8 | D10: ='Roth Conversion'!E9 -> 126329.68 | E10: =(B10+C10)*Inputs!B43 -> 65483.947 | F10: =D10+E10 -> 191813.63 | G10: =Inputs!B42 -> 30000 | H10: =MAX(0,F10-G10) -> 161813.63 | I10: =IF(H10<=23200,"10%",IF(H10<=94300,"12%",IF(H10<=201050,"22%",IF(H10<=383900,"24%","32%+")))) -> 22% | J10: =MAX(0,IF(H10<=23200,H10*0.1,IF(H10<=94300,23200*0.1+(H10-23200)*0.12,IF(H10<=201050,23200*0.1+71100*0.12+(H10-94300)*0.22,23200*0.1+71100*0.12+106750*0.22+(H10-201050)*0.24)))) -> 25704.999 | K10: =IFERROR(J10/MAX(1,H10),0) -> 0.15885558 | L10: =IF(F10<=206000,"Base $0",IF(F10<=258000,"T1 $594",IF(F10<=322000,"T2 $1,488",IF(F10<=386000,"T3 $2,382",IF(F10<=750000,"T4 $3,276","T5 $4,170"))))) -> Base $0 | M10: =ROUND(D10*0.0637,0) -> 8047 | N10: =J10+M10 -> 33751.999
A11: 72 | B11: ='Withdrawal Plan'!H10 -> 53927.441 | C11: ='Withdrawal Plan'!I10 -> 25038.495 | D11: ='Roth Conversion'!E10 -> 125211.68 | E11: =(B11+C11)*Inputs!B43 -> 67121.046 | F11: =D11+E11 -> 192332.72 | G11: =Inputs!B42 -> 30000 | H11: =MAX(0,F11-G11) -> 162332.72 | I11: =IF(H11<=23200,"10%",IF(H11<=94300,"12%",IF(H11<=201050,"22%",IF(H11<=383900,"24%","32%+")))) -> 22% | J11: =MAX(0,IF(H11<=23200,H11*0.1,IF(H11<=94300,23200*0.1+(H11-23200)*0.12,IF(H11<=201050,23200*0.1+71100*0.12+(H11-94300)*0.22,23200*0.1+71100*0.12+106750*0.22+(H11-201050)*0.24)))) -> 25819.199 | K11: =IFERROR(J11/MAX(1,H11),0) -> 0.1590511 | L11: =IF(F11<=206000,"Base $0",IF(F11<=258000,"T1 $594",IF(F11<=322000,"T2 $1,488",IF(F11<=386000,"T3 $2,382",IF(F11<=750000,"T4 $3,276","T5 $4,170"))))) -> Base $0 | M11: =ROUND(D11*0.0637,0) -> 7976 | N11: =J11+M11 -> 33795.199
A12: 73 | B12: ='Withdrawal Plan'!H11 -> 55275.627 | C12: ='Withdrawal Plan'!I11 -> 25664.457 | D12: ='Roth Conversion'!E11 -> 124065.72 | E12: =(B12+C12)*Inputs!B43 -> 68799.072 | F12: =D12+E12 -> 192864.79 | G12: =Inputs!B42 -> 30000 | H12: =MAX(0,F12-G12) -> 162864.79 | I12: =IF(H12<=23200,"10%",IF(H12<=94300,"12%",IF(H12<=201050,"22%",IF(H12<=383900,"24%","32%+")))) -> 22% | J12: =MAX(0,IF(H12<=23200,H12*0.1,IF(H12<=94300,23200*0.1+(H12-23200)*0.12,IF(H12<=201050,23200*0.1+71100*0.12+(H12-94300)*0.22,23200*0.1+71100*0.12+106750*0.22+(H12-201050)*0.24)))) -> 25936.254 | K12: =IFERROR(J12/MAX(1,H12),0) -> 0.15925022 | L12: =IF(F12<=206000,"Base $0",IF(F12<=258000,"T1 $594",IF(F12<=322000,"T2 $1,488",IF(F12<=386000,"T3 $2,382",IF(F12<=750000,"T4 $3,276","T5 $4,170"))))) -> Base $0 | M12: =ROUND(D12*0.0637,0) -> 7903 | N12: =J12+M12 -> 33839.254
A13: 74 | B13: ='Withdrawal Plan'!H12 -> 56657.518 | C13: ='Withdrawal Plan'!I12 -> 26306.069 | D13: ='Roth Conversion'!E12 -> 122891.11 | E13: =(B13+C13)*Inputs!B43 -> 70519.049 | F13: =D13+E13 -> 193410.16 | G13: =Inputs!B42 -> 30000 | H13: =MAX(0,F13-G13) -> 163410.16 | I13: =IF(H13<=23200,"10%",IF(H13<=94300,"12%",IF(H13<=201050,"22%",IF(H13<=383900,"24%","32%+")))) -> 22% | J13: =MAX(0,IF(H13<=23200,H13*0.1,IF(H13<=94300,23200*0.1+(H13-23200)*0.12,IF(H13<=201050,23200*0.1+71100*0.12+(H13-94300)*0.22,23200*0.1+71100*0.12+106750*0.22+(H13-201050)*0.24)))) -> 26056.235 | K13: =IFERROR(J13/MAX(1,H13),0) -> 0.15945297 | L13: =IF(F13<=206000,"Base $0",IF(F13<=258000,"T1 $594",IF(F13<=322000,"T2 $1,488",IF(F13<=386000,"T3 $2,382",IF(F13<=750000,"T4 $3,276","T5 $4,170"))))) -> Base $0 | M13: =ROUND(D13*0.0637,0) -> 7828 | N13: =J13+M13 -> 33884.235
A14: 75 | B14: ='Withdrawal Plan'!H13 -> 58073.956 | C14: ='Withdrawal Plan'!I13 -> 26963.721 | D14: ='Roth Conversion'!E13 -> 121687.14 | E14: =(B14+C14)*Inputs!B43 -> 72282.025 | F14: =D14+E14 -> 193969.16 | G14: =Inputs!B42 -> 30000 | H14: =MAX(0,F14-G14) -> 163969.16 | I14: =IF(H14<=23200,"10%",IF(H14<=94300,"12%",IF(H14<=201050,"22%",IF(H14<=383900,"24%","32%+")))) -> 22% | J14: =MAX(0,IF(H14<=23200,H14*0.1,IF(H14<=94300,23200*0.1+(H14-23200)*0.12,IF(H14<=201050,23200*0.1+71100*0.12+(H14-94300)*0.22,23200*0.1+71100*0.12+106750*0.22+(H14-201050)*0.24)))) -> 26179.216 | K14: =IFERROR(J14/MAX(1,H14),0) -> 0.15965939 | L14: =IF(F14<=206000,"Base $0",IF(F14<=258000,"T1 $594",IF(F14<=322000,"T2 $1,488",IF(F14<=386000,"T3 $2,382",IF(F14<=750000,"T4 $3,276","T5 $4,170"))))) -> Base $0 | M14: =ROUND(D14*0.0637,0) -> 7751 | N14: =J14+M14 -> 33930.216
A15: 76 | B15: ='Withdrawal Plan'!H14 -> 59525.805 | C15: ='Withdrawal Plan'!I14 -> 27637.814 | D15: ='Roth Conversion'!E14 -> 120453.07 | E15: =(B15+C15)*Inputs!B43 -> 74089.075 | F15: =D15+E15 -> 194542.14 | G15: =Inputs!B42 -> 30000 | H15: =MAX(0,F15-G15) -> 164542.14 | I15: =IF(H15<=23200,"10%",IF(H15<=94300,"12%",IF(H15<=201050,"22%",IF(H15<=383900,"24%","32%+")))) -> 22% | J15: =MAX(0,IF(H15<=23200,H15*0.1,IF(H15<=94300,23200*0.1+(H15-23200)*0.12,IF(H15<=201050,23200*0.1+71100*0.12+(H15-94300)*0.22,23200*0.1+71100*0.12+106750*0.22+(H15-201050)*0.24)))) -> 26305.271 | K15: =IFERROR(J15/MAX(1,H15),0) -> 0.15986951 | L15: =IF(F15<=206000,"Base $0",IF(F15<=258000,"T1 $594",IF(F15<=322000,"T2 $1,488",IF(F15<=386000,"T3 $2,382",IF(F15<=750000,"T4 $3,276","T5 $4,170"))))) -> Base $0 | M15: =ROUND(D15*0.0637,0) -> 7673 | N15: =J15+M15 -> 33978.271
A16: 77 | B16: ='Withdrawal Plan'!H15 -> 61013.95 | C16: ='Withdrawal Plan'!I15 -> 28328.759 | D16: ='Roth Conversion'!E15 -> 119188.14 | E16: =(B16+C16)*Inputs!B43 -> 75941.302 | F16: =D16+E16 -> 195129.45 | G16: =Inputs!B42 -> 30000 | H16: =MAX(0,F16-G16) -> 165129.45 | I16: =IF(H16<=23200,"10%",IF(H16<=94300,"12%",IF(H16<=201050,"22%",IF(H16<=383900,"24%","32%+")))) -> 22% | J16: =MAX(0,IF(H16<=23200,H16*0.1,IF(H16<=94300,23200*0.1+(H16-23200)*0.12,IF(H16<=201050,23200*0.1+71100*0.12+(H16-94300)*0.22,23200*0.1+71100*0.12+106750*0.22+(H16-201050)*0.24)))) -> 26434.478 | K16: =IFERROR(J16/MAX(1,H16),0) -> 0.16008337 | L16: =IF(F16<=206000,"Base $0",IF(F16<=258000,"T1 $594",IF(F16<=322000,"T2 $1,488",IF(F16<=386000,"T3 $2,382",IF(F16<=750000,"T4 $3,276","T5 $4,170"))))) -> Base $0 | M16: =ROUND(D16*0.0637,0) -> 7592 | N16: =J16+M16 -> 34026.478
A17: 78 | B17: ='Withdrawal Plan'!H16 -> 62539.298 | C17: ='Withdrawal Plan'!I16 -> 29036.978 | D17: ='Roth Conversion'!E16 -> 117891.6 | E17: =(B17+C17)*Inputs!B43 -> 77839.835 | F17: =D17+E17 -> 195731.43 | G17: =Inputs!B42 -> 30000 | H17: =MAX(0,F17-G17) -> 165731.43 | I17: =IF(H17<=23200,"10%",IF(H17<=94300,"12%",IF(H17<=201050,"22%",IF(H17<=383900,"24%","32%+")))) -> 22% | J17: =MAX(0,IF(H17<=23200,H17*0.1,IF(H17<=94300,23200*0.1+(H17-23200)*0.12,IF(H17<=201050,23200*0.1+71100*0.12+(H17-94300)*0.22,23200*0.1+71100*0.12+106750*0.22+(H17-201050)*0.24)))) -> 26566.915 | K17: =IFERROR(J17/MAX(1,H17),0) -> 0.160301 | L17: =IF(F17<=206000,"Base $0",IF(F17<=258000,"T1 $594",IF(F17<=322000,"T2 $1,488",IF(F17<=386000,"T3 $2,382",IF(F17<=750000,"T4 $3,276","T5 $4,170"))))) -> Base $0 | M17: =ROUND(D17*0.0637,0) -> 7510 | N17: =J17+M17 -> 34076.915
A18: 79 | B18: ='Withdrawal Plan'!H17 -> 64102.781 | C18: ='Withdrawal Plan'!I17 -> 29762.902 | D18: ='Roth Conversion'!E17 -> 116562.64 | E18: =(B18+C18)*Inputs!B43 -> 79785.831 | F18: =D18+E18 -> 196348.47 | G18: =Inputs!B42 -> 30000 | H18: =MAX(0,F18-G18) -> 166348.47 | I18: =IF(H18<=23200,"10%",IF(H18<=94300,"12%",IF(H18<=201050,"22%",IF(H18<=383900,"24%","32%+")))) -> 22% | J18: =MAX(0,IF(H18<=23200,H18*0.1,IF(H18<=94300,23200*0.1+(H18-23200)*0.12,IF(H18<=201050,23200*0.1+71100*0.12+(H18-94300)*0.22,23200*0.1+71100*0.12+106750*0.22+(H18-201050)*0.24)))) -> 26702.663 | K18: =IFERROR(J18/MAX(1,H18),0) -> 0.16052245 | L18: =IF(F18<=206000,"Base $0",IF(F18<=258000,"T1 $594",IF(F18<=322000,"T2 $1,488",IF(F18<=386000,"T3 $2,382",IF(F18<=750000,"T4 $3,276","T5 $4,170"))))) -> Base $0 | M18: =ROUND(D18*0.0637,0) -> 7425 | N18: =J18+M18 -> 34127.663
A19: 80 | B19: ='Withdrawal Plan'!H18 -> 65705.35 | C19: ='Withdrawal Plan'!I18 -> 30506.975 | D19: ='Roth Conversion'!E18 -> 115200.45 | E19: =(B19+C19)*Inputs!B43 -> 81780.477 | F19: =D19+E19 -> 196980.93 | G19: =Inputs!B42 -> 30000 | H19: =MAX(0,F19-G19) -> 166980.93 | I19: =IF(H19<=23200,"10%",IF(H19<=94300,"12%",IF(H19<=201050,"22%",IF(H19<=383900,"24%","32%+")))) -> 22% | J19: =MAX(0,IF(H19<=23200,H19*0.1,IF(H19<=94300,23200*0.1+(H19-23200)*0.12,IF(H19<=201050,23200*0.1+71100*0.12+(H19-94300)*0.22,23200*0.1+71100*0.12+106750*0.22+(H19-201050)*0.24)))) -> 26841.804 | K19: =IFERROR(J19/MAX(1,H19),0) -> 0.16074772 | L19: =IF(F19<=206000,"Base $0",IF(F19<=258000,"T1 $594",IF(F19<=322000,"T2 $1,488",IF(F19<=386000,"T3 $2,382",IF(F19<=750000,"T4 $3,276","T5 $4,170"))))) -> Base $0 | M19: =ROUND(D19*0.0637,0) -> 7338 | N19: =J19+M19 -> 34179.804
A20: 81 | B20: ='Withdrawal Plan'!H19 -> 67347.984 | C20: ='Withdrawal Plan'!I19 -> 31269.649 | D20: ='Roth Conversion'!E19 -> 113804.21 | E20: =(B20+C20)*Inputs!B43 -> 83824.988 | F20: =D20+E20 -> 197629.2 | G20: =Inputs!B42 -> 30000 | H20: =MAX(0,F20-G20) -> 167629.2 | I20: =IF(H20<=23200,"10%",IF(H20<=94300,"12%",IF(H20<=201050,"22%",IF(H20<=383900,"24%","32%+")))) -> 22% | J20: =MAX(0,IF(H20<=23200,H20*0.1,IF(H20<=94300,23200*0.1+(H20-23200)*0.12,IF(H20<=201050,23200*0.1+71100*0.12+(H20-94300)*0.22,23200*0.1+71100*0.12+106750*0.22+(H20-201050)*0.24)))) -> 26984.424 | K20: =IFERROR(J20/MAX(1,H20),0) -> 0.16097687 | L20: =IF(F20<=206000,"Base $0",IF(F20<=258000,"T1 $594",IF(F20<=322000,"T2 $1,488",IF(F20<=386000,"T3 $2,382",IF(F20<=750000,"T4 $3,276","T5 $4,170"))))) -> Base $0 | M20: =ROUND(D20*0.0637,0) -> 7249 | N20: =J20+M20 -> 34233.424
A21: 82 | B21: ='Withdrawal Plan'!H20 -> 69031.684 | C21: ='Withdrawal Plan'!I20 -> 32051.39 | D21: ='Roth Conversion'!E20 -> 112373.07 | E21: =(B21+C21)*Inputs!B43 -> 85920.613 | F21: =D21+E21 -> 198293.68 | G21: =Inputs!B42 -> 30000 | H21: =MAX(0,F21-G21) -> 168293.68 | I21: =IF(H21<=23200,"10%",IF(H21<=94300,"12%",IF(H21<=201050,"22%",IF(H21<=383900,"24%","32%+")))) -> 22% | J21: =MAX(0,IF(H21<=23200,H21*0.1,IF(H21<=94300,23200*0.1+(H21-23200)*0.12,IF(H21<=201050,23200*0.1+71100*0.12+(H21-94300)*0.22,23200*0.1+71100*0.12+106750*0.22+(H21-201050)*0.24)))) -> 27130.61 | K21: =IFERROR(J21/MAX(1,H21),0) -> 0.16120991 | L21: =IF(F21<=206000,"Base $0",IF(F21<=258000,"T1 $594",IF(F21<=322000,"T2 $1,488",IF(F21<=386000,"T3 $2,382",IF(F21<=750000,"T4 $3,276","T5 $4,170"))))) -> Base $0 | M21: =ROUND(D21*0.0637,0) -> 7158 | N21: =J21+M21 -> 34288.61
A22: 83 | B22: ='Withdrawal Plan'!H21 -> 70757.476 | C22: ='Withdrawal Plan'!I21 -> 32852.675 | D22: ='Roth Conversion'!E21 -> 110906.15 | E22: =(B22+C22)*Inputs!B43 -> 88068.628 | F22: =D22+E22 -> 198974.77 | G22: =Inputs!B42 -> 30000 | H22: =MAX(0,F22-G22) -> 168974.77 | I22: =IF(H22<=23200,"10%",IF(H22<=94300,"12%",IF(H22<=201050,"22%",IF(H22<=383900,"24%","32%+")))) -> 22% | J22: =MAX(0,IF(H22<=23200,H22*0.1,IF(H22<=94300,23200*0.1+(H22-23200)*0.12,IF(H22<=201050,23200*0.1+71100*0.12+(H22-94300)*0.22,23200*0.1+71100*0.12+106750*0.22+(H22-201050)*0.24)))) -> 27280.45 | K22: =IFERROR(J22/MAX(1,H22),0) -> 0.16144688 | L22: =IF(F22<=206000,"Base $0",IF(F22<=258000,"T1 $594",IF(F22<=322000,"T2 $1,488",IF(F22<=386000,"T3 $2,382",IF(F22<=750000,"T4 $3,276","T5 $4,170"))))) -> Base $0 | M22: =ROUND(D22*0.0637,0) -> 7065 | N22: =J22+M22 -> 34345.45
A23: 84 | B23: ='Withdrawal Plan'!H22 -> 72526.413 | C23: ='Withdrawal Plan'!I22 -> 33673.992 | D23: ='Roth Conversion'!E22 -> 109402.55 | E23: =(B23+C23)*Inputs!B43 -> 90270.344 | F23: =D23+E23 -> 199672.89 | G23: =Inputs!B42 -> 30000 | H23: =MAX(0,F23-G23) -> 169672.89 | I23: =IF(H23<=23200,"10%",IF(H23<=94300,"12%",IF(H23<=201050,"22%",IF(H23<=383900,"24%","32%+")))) -> 22% | J23: =MAX(0,IF(H23<=23200,H23*0.1,IF(H23<=94300,23200*0.1+(H23-23200)*0.12,IF(H23<=201050,23200*0.1+71100*0.12+(H23-94300)*0.22,23200*0.1+71100*0.12+106750*0.22+(H23-201050)*0.24)))) -> 27434.037 | K23: =IFERROR(J23/MAX(1,H23),0) -> 0.1616878 | L23: =IF(F23<=206000,"Base $0",IF(F23<=258000,"T1 $594",IF(F23<=322000,"T2 $1,488",IF(F23<=386000,"T3 $2,382",IF(F23<=750000,"T4 $3,276","T5 $4,170"))))) -> Base $0 | M23: =ROUND(D23*0.0637,0) -> 6969 | N23: =J23+M23 -> 34403.037
A24: 85 | B24: ='Withdrawal Plan'!H23 -> 74339.573 | C24: ='Withdrawal Plan'!I23 -> 34515.842 | D24: ='Roth Conversion'!E23 -> 107861.36 | E24: =(B24+C24)*Inputs!B43 -> 92527.103 | F24: =D24+E24 -> 200388.47 | G24: =Inputs!B42 -> 30000 | H24: =MAX(0,F24-G24) -> 170388.47 | I24: =IF(H24<=23200,"10%",IF(H24<=94300,"12%",IF(H24<=201050,"22%",IF(H24<=383900,"24%","32%+")))) -> 22% | J24: =MAX(0,IF(H24<=23200,H24*0.1,IF(H24<=94300,23200*0.1+(H24-23200)*0.12,IF(H24<=201050,23200*0.1+71100*0.12+(H24-94300)*0.22,23200*0.1+71100*0.12+106750*0.22+(H24-201050)*0.24)))) -> 27591.462 | K24: =IFERROR(J24/MAX(1,H24),0) -> 0.16193269 | L24: =IF(F24<=206000,"Base $0",IF(F24<=258000,"T1 $594",IF(F24<=322000,"T2 $1,488",IF(F24<=386000,"T3 $2,382",IF(F24<=750000,"T4 $3,276","T5 $4,170"))))) -> Base $0 | M24: =ROUND(D24*0.0637,0) -> 6871 | N24: =J24+M24 -> 34462.462

Sheet Stress Test
A1: PORTFOLIO STRESS TEST — Growth Rate Sensitivity (Ages 65–85)
A2: Shows portfolio trajectory under 4 growth scenarios. Bear = 4%, Conservative = 6%, Base = 8% (your assumption), Bull = 10%. Withdrawals are held constant at base amounts. Portfolio = prior balance × (1+rate) − annual withdrawal from all accounts.
A3: Age | B3: Annual Withdrawal ($) | C3: Bear 4% Portfolio ($) | D3: Conservative 6% Portfolio ($) | E3: Base 8% Portfolio ($) | F3: Bull 10% Portfolio ($) | G3: Bear vs Base ($) | H3: Bull vs Base ($)
A4: 65 | B4: ='Withdrawal Plan'!J3+'Withdrawal Plan'!K3+'Withdrawal Plan'!L3+'Withdrawal Plan'!M3 -> 173270 | C4: =MAX(0,Portfolio!H11*(1+0.04)-B4) -> 9132439.1 | D4: =MAX(0,Portfolio!H11*(1+0.06)-B4) -> 9311395 | E4: =MAX(0,Portfolio!H11*(1+0.08)-B4) -> 9490351 | F4: =MAX(0,Portfolio!H11*(1+0.1)-B4) -> 9669306.9 | G4: =C4-E4 -> -357911.89 | H4: =F4-E4 -> 178955.94
A5: 66 | B5: ='Withdrawal Plan'!J4+'Withdrawal Plan'!K4+'Withdrawal Plan'!L4+'Withdrawal Plan'!M4 -> 173381 | C5: =MAX(0,C4*(1+0.04)-B5) -> 9324355.7 | D5: =MAX(0,D4*(1+0.06)-B5) -> 9696697.8 | E5: =MAX(0,E4*(1+0.08)-B5) -> 10076198 | F5: =MAX(0,F4*(1+0.1)-B5) -> 10462857 | G5: =C5-E5 -> -751842.4 | H5: =F5-E5 -> 386658.56
A6: 67 | B6: ='Withdrawal Plan'!J5+'Withdrawal Plan'!K5+'Withdrawal Plan'!L5+'Withdrawal Plan'!M5 -> 132983.15 | C6: =MAX(0,C5*(1+0.04)-B6) -> 9564346.7 | D6: =MAX(0,D5*(1+0.06)-B6) -> 10145516 | E6: =MAX(0,E5*(1+0.08)-B6) -> 10749311 | F6: =MAX(0,F5*(1+0.1)-B6) -> 11376159 | G6: =C6-E6 -> -1184964 | H6: =F6-E6 -> 626848.38
A7: 68 | B7: ='Withdrawal Plan'!J6+'Withdrawal Plan'!K6+'Withdrawal Plan'!L6+'Withdrawal Plan'!M6 -> 132092.67 | C7: =MAX(0,C6*(1+0.04)-B7) -> 9814827.9 | D7: =MAX(0,D6*(1+0.06)-B7) -> 10622155 | E7: =MAX(0,E6*(1+0.08)-B7) -> 11477163 | F7: =MAX(0,F6*(1+0.1)-B7) -> 12381682 | G7: =C7-E7 -> -1662335 | H7: =F7-E7 -> 904519.43
A8: 69 | B8: ='Withdrawal Plan'!J7+'Withdrawal Plan'!K7+'Withdrawal Plan'!L7+'Withdrawal Plan'!M7 -> 131182.98 | C8: =MAX(0,C7*(1+0.04)-B8) -> 10076238 | D8: =MAX(0,D7*(1+0.06)-B8) -> 11128301 | E8: =MAX(0,E7*(1+0.08)-B8) -> 12264153 | F8: =MAX(0,F7*(1+0.1)-B8) -> 13488668 | G8: =C8-E8 -> -2187914.9 | H8: =F8-E8 -> 1224514.6
A9: 70 | B9: ='Withdrawal Plan'!J8+'Withdrawal Plan'!K8+'Withdrawal Plan'!L8+'Withdrawal Plan'!M8 -> 130253.77 | C9: =MAX(0,C8*(1+0.04)-B9) -> 10349034 | D9: =MAX(0,D8*(1+0.06)-B9) -> 11665745 | E9: =MAX(0,E8*(1+0.08)-B9) -> 13115031 | F9: =MAX(0,F8*(1+0.1)-B9) -> 14707281 | G9: =C9-E9 -> -2765997.7 | H9: =F9-E9 -> 1592249.2
A10: 71 | B10: ='Withdrawal Plan'!J9+'Withdrawal Plan'!K9+'Withdrawal Plan'!L9+'Withdrawal Plan'!M9 -> 129304.7 | C10: =MAX(0,C9*(1+0.04)-B10) -> 10633690 | D10: =MAX(0,D9*(1+0.06)-B10) -> 12236385 | E10: =MAX(0,E9*(1+0.08)-B10) -> 14034929 | F10: =MAX(0,F9*(1+0.1)-B10) -> 16048704 | G10: =C10-E10 -> -3401238.8 | H10: =F10-E10 -> 2013774.7
A11: 72 | B11: ='Withdrawal Plan'!J10+'Withdrawal Plan'!K10+'Withdrawal Plan'!L10+'Withdrawal Plan'!M10 -> 128335.44 | C11: =MAX(0,C10*(1+0.04)-B11) -> 10930703 | D11: =MAX(0,D10*(1+0.06)-B11) -> 12842233 | E11: =MAX(0,E10*(1+0.08)-B11) -> 15029388 | F11: =MAX(0,F10*(1+0.1)-B11) -> 17525239 | G11: =C11-E11 -> -4098685.5 | H11: =F11-E11 -> 2495850.8
A12: 73 | B12: ='Withdrawal Plan'!J11+'Withdrawal Plan'!K11+'Withdrawal Plan'!L11+'Withdrawal Plan'!M11 -> 127345.67 | C12: =MAX(0,C11*(1+0.04)-B12) -> 11240585 | D12: =MAX(0,D11*(1+0.06)-B12) -> 13485421 | E12: =MAX(0,E11*(1+0.08)-B12) -> 16104394 | F12: =MAX(0,F11*(1+0.1)-B12) -> 19150417 | G12: =C12-E12 -> -4863808.5 | H12: =F12-E12 -> 3046023.6
A13: 74 | B13: ='Withdrawal Plan'!J12+'Withdrawal Plan'!K12+'Withdrawal Plan'!L12+'Withdrawal Plan'!M12 -> 126335.06 | C13: =MAX(0,C12*(1+0.04)-B13) -> 11563873 | D13: =MAX(0,D12*(1+0.06)-B13) -> 14168212 | E13: =MAX(0,E12*(1+0.08)-B13) -> 17266410 | F13: =MAX(0,F12*(1+0.1)-B13) -> 20939124 | G13: =C13-E13 -> -5702536.6 | H13: =F13-E13 -> 3672713.8
A14: 75 | B14: ='Withdrawal Plan'!J13+'Withdrawal Plan'!K13+'Withdrawal Plan'!L13+'Withdrawal Plan'!M13 -> 125303.28 | C14: =MAX(0,C13*(1+0.04)-B14) -> 11901125 | D14: =MAX(0,D13*(1+0.06)-B14) -> 14893001 | E14: =MAX(0,E13*(1+0.08)-B14) -> 18522420 | F14: =MAX(0,F13*(1+0.1)-B14) -> 22907733 | G14: =C14-E14 -> -6621294.4 | H14: =F14-E14 -> 4385313.4
A15: 76 | B15: ='Withdrawal Plan'!J14+'Withdrawal Plan'!K14+'Withdrawal Plan'!L14+'Withdrawal Plan'!M14 -> 124250.02 | C15: =MAX(0,C14*(1+0.04)-B15) -> 12252920 | D15: =MAX(0,D14*(1+0.06)-B15) -> 15662331 | E15: =MAX(0,E14*(1+0.08)-B15) -> 19879963 | F15: =MAX(0,F14*(1+0.1)-B15) -> 25074256 | G15: =C15-E15 -> -7627043 | H15: =F15-E15 -> 5194293.1
A16: 77 | B16: ='Withdrawal Plan'!J15+'Withdrawal Plan'!K15+'Withdrawal Plan'!L15+'Withdrawal Plan'!M15 -> 123174.94 | C16: =MAX(0,C15*(1+0.04)-B16) -> 12619862 | D16: =MAX(0,D15*(1+0.06)-B16) -> 16478896 | E16: =MAX(0,E15*(1+0.08)-B16) -> 21347185 | F16: =MAX(0,F15*(1+0.1)-B16) -> 27458507 | G16: =C16-E16 -> -8727323.2 | H16: =F16-E16 -> 6111321.7
... A24: 85 | B24: ='Withdrawal Plan'!J23+'Withdrawal Plan'!K23+'Withdrawal Plan'!L23+'Withdrawal Plan'!M23 -> 113751.68 | C24: =MAX(0,C23*(1+0.04)-B24) -> 16181651 | D24: =MAX(0,D23*(1+0.06)-B24) -> 25093402 | E24: =MAX(0,E23*(1+0.08)-B24) -> 38251989 | F24: =MAX(0,F23*(1+0.1)-B24) -> 57503621 | G24: =C24-E24 -> -22070338 | H24: =F24-E24 -> 19251632
A26: Final Portfolio at Age 85: | C26: Bear 4% | D26: Conservative 6% | E26: Base 8% | F26: Bull 10%
C27: =C24 -> 16181651 | D27: =D24 -> 25093402 | E27: =E24 -> 38251989 | F27: =F24 -> 57503621
A28: ⚠ Note: Withdrawals held at base-rate amounts for simplicity. Under Bear scenario, actual withdrawals from Trad 401k/Roth may differ. Use as directional stress test, not precise forecast.

Sheet Survivor
A1: SURVIVOR SCENARIO — If Spouse Passes First
A2: Models financial impact if spouse predeceases you. Filing status → Single (brackets ~50% of MFJ). SS: you keep the HIGHER benefit (survivor benefit). Spouse SS and insurance cost drop to zero. Expenses reduced by 20% to reflect single-person household. RMD rules unchanged.
A4: Spouse passes at age (your age): | C4: 75 | D4: ← Change this cell
A5: Expense reduction after spouse passes (%): | C5: 0.2 | D5: ← Default 20%
A6: Age | B6: Filing Status | C6: Your SS ($) | D6: Wife SS ($) | E6: Total SS ($) | F6: Living Exp ($) | G6: Mortgage ($) | H6: Total Needs ($) | I6: Trad Draw ($) | J6: Fed Tax (Single) ($) | K6: State Tax ($) | L6: Net Surplus ($)
A7: 65 | B7: =IF(A7>=C4,"Single","MFJ") -> MFJ | C7: ='Withdrawal Plan'!H3 -> 0 | D7: =IF(A7>=C4,0,'Withdrawal Plan'!I3) -> 0 | E7: =C7+D7 -> 0 | F7: ='Withdrawal Plan'!B3*IF(A7>=$C$4,1-$C$5,1) -> 84000 | G7: ='Withdrawal Plan'!C3 -> 36000 | H7: =F7+G7+'Withdrawal Plan'!D3+IF(A7>=C4,0,'Withdrawal Plan'!E3)+'Withdrawal Plan'!F3 -> 148320 | I7: ='Roth Conversion'!E3 -> 171050 | J7: =IF(A7>=$C$4,MAX(0,IF(MAX(0,I7+E7*Inputs!B43-Inputs!B42)<=11600,MAX(0,I7+E7*Inputs!B43-Inputs!B42)*0.1,IF(MAX(0,I7+E7*Inputs!B43-Inputs!B42)<=47150,11600*0.1+(MAX(0,I7+E7*Inputs!B43-Inputs!B42)-11600)*0.12,IF(MAX(0,I7+E7*Inputs!B43-Inputs!B42)<=100525,11600*0.1+35550*0.12+(MAX(0,I7+E7*Inputs!B43-Inputs!B42)-47150)*0.22,11600*0.1+35550*0.12+53375*0.22+(MAX(0,I7+E7*Inputs!B43-Inputs!B42)-100525)*0.24)))),MAX(0,IF(MAX(0,I7+E7*Inputs!B43-Inputs!B42)<=23200,MAX(0,I7+E7*Inputs!B43-Inputs!B42)*0.1,IF(MAX(0,I7+E7*Inputs!B43-Inputs!B42)<=94300,23200*0.1+(MAX(0,I7+E7*Inputs!B43-Inputs!B42)-23200)*0.12,IF(MAX(0,I7+E7*Inputs!B43-Inputs!B42)<=201050,23200*0.1+71100*0.12+(MAX(0,I7+E7*Inputs!B43-Inputs!B42)-94300)*0.22,23200*0.1+71100*0.12+106750*0.22+(MAX(0,I7+E7*Inputs!B43-Inputs!B42)-201050)*0.24))))) -> 21137 | K7: =ROUND(I7*0.0637,0) -> 10896 | L7: =E7+I7-H7-J7-K7 -> -9303
A8: 66 | B8: =IF(A8>=C4,"Single","MFJ") -> MFJ | C8: ='Withdrawal Plan'!H4 -> 0 | D8: =IF(A8>=C4,0,'Withdrawal Plan'!I4) -> 0 | E8: =C8+D8 -> 0 | F8: ='Withdrawal Plan'!B4*IF(A8>=$C$4,1-$C$5,1) -> 86520 | G8: ='Withdrawal Plan'!C4 -> 36000 | H8: =F8+G8+'Withdrawal Plan'!D4+IF(A8>=C4,0,'Withdrawal Plan'!E4)+'Withdrawal Plan'!F4 -> 150951 | I8: ='Roth Conversion'!E4 -> 171050 | J8: =IF(A8>=$C$4,MAX(0,IF(MAX(0,I8+E8*Inputs!B43-Inputs!B42)<=11600,MAX(0,I8+E8*Inputs!B43-Inputs!B42)*0.1,IF(MAX(0,I8+E8*Inputs!B43-Inputs!B42)<=47150,11600*0.1+(MAX(0,I8+E8*Inputs!B43-Inputs!B42)-11600)*0.12,IF(MAX(0,I8+E8*Inputs!B43-Inputs!B42)<=100525,11600*0.1+35550*0.12+(MAX(0,I8+E8*Inputs!B43-Inputs!B42)-47150)*0.22,11600*0.1+35550*0.12+53375*0.22+(MAX(0,I8+E8*Inputs!B43-Inputs!B42)-100525)*0.24)))),MAX(0,IF(MAX(0,I8+E8*Inputs!B43-Inputs!B42)<=23200,MAX(0,I8+E8*Inputs!B43-Inputs!B42)*0.1,IF(MAX(0,I8+E8*Inputs!B43-Inputs!B42)<=94300,23200*0.1+(MAX(0,I8+E8*Inputs!B43-Inputs!B42)-23200)*0.12,IF(MAX(0,I8+E8*Inputs!B43-Inputs!B42)<=201050,23200*0.1+71100*0.12+(MAX(0,I8+E8*Inputs!B43-Inputs!B42)-94300)*0.22,23200*0.1+71100*0.12+106750*0.22+(MAX(0,I8+E8*Inputs!B43-Inputs!B42)-201050)*0.24))))) -> 21137 | K8: =ROUND(I8*0.0637,0) -> 10896 | L8: =E8+I8-H8-J8-K8 -> -11934
A9: 67 | B9: =IF(A9>=C4,"Single","MFJ") -> MFJ | C9: ='Withdrawal Plan'!H5 -> 47664 | D9: =IF(A9>=C4,0,'Withdrawal Plan'!I5) -> 0 | E9: =C9+D9 -> 47664 | F9: ='Withdrawal Plan'!B5*IF(A9>=$C$4,1-$C$5,1) -> 89115.6 | G9: ='Withdrawal Plan'!C5 -> 36000 | H9: =F9+G9+'Withdrawal Plan'!D5+IF(A9>=C4,0,'Withdrawal Plan'!E5)+'Withdrawal Plan'!F5 -> 153663.15 | I9: ='Roth Conversion'!E5 -> 130535.6 | J9: =IF(A9>=$C$4,MAX(0,IF(MAX(0,I9+E9*Inputs!B43-Inputs!B42)<=11600,MAX(0,I9+E9*Inputs!B43-Inputs!B42)*0.1,IF(MAX(0,I9+E9*Inputs!B43-Inputs!B42)<=47150,11600*0.1+(MAX(0,I9+E9*Inputs!B43-Inputs!B42)-11600)*0.12,IF(MAX(0,I9+E9*Inputs!B43-Inputs!B42)<=100525,11600*0.1+35550*0.12+(MAX(0,I9+E9*Inputs!B43-Inputs!B42)-47150)*0.22,11600*0.1+35550*0.12+53375*0.22+(MAX(0,I9+E9*Inputs!B43-Inputs!B42)-100525)*0.24)))),MAX(0,IF(MAX(0,I9+E9*Inputs!B43-Inputs!B42)<=23200,MAX(0,I9+E9*Inputs!B43-Inputs!B42)*0.1,IF(MAX(0,I9+E9*Inputs!B43-Inputs!B42)<=94300,23200*0.1+(MAX(0,I9+E9*Inputs!B43-Inputs!B42)-23200)*0.12,IF(MAX(0,I9+E9*Inputs!B43-Inputs!B42)<=201050,23200*0.1+71100*0.12+(MAX(0,I9+E9*Inputs!B43-Inputs!B42)-94300)*0.22,23200*0.1+71100*0.12+106750*0.22+(MAX(0,I9+E9*Inputs!B43-Inputs!B42)-201050)*0.24))))) -> 21137 | K9: =ROUND(I9*0.0637,0) -> 8315 | L9: =E9+I9-H9-J9-K9 -> -4915.55
A10: 68 | B10: =IF(A10>=C4,"Single","MFJ") -> MFJ | C10: ='Withdrawal Plan'!H6 -> 48855.6 | D10: =IF(A10>=C4,0,'Withdrawal Plan'!I6) -> 0 | E10: =C10+D10 -> 48855.6 | F10: ='Withdrawal Plan'!B6*IF(A10>=$C$4,1-$C$5,1) -> 91789.068 | G10: ='Withdrawal Plan'!C6 -> 36000 | H10: =F10+G10+'Withdrawal Plan'!D6+IF(A10>=C4,0,'Withdrawal Plan'!E6)+'Withdrawal Plan'!F6 -> 156459 | I10: ='Roth Conversion'!E6 -> 129522.74 | J10: =IF(A10>=$C$4,MAX(0,IF(MAX(0,I10+E10*Inputs!B43-Inputs!B42)<=11600,MAX(0,I10+E10*Inputs!B43-Inputs!B42)*0.1,IF(MAX(0,I10+E10*Inputs!B43-Inputs!B42)<=47150,11600*0.1+(MAX(0,I10+E10*Inputs!B43-Inputs!B42)-11600)*0.12,IF(MAX(0,I10+E10*Inputs!B43-Inputs!B42)<=100525,11600*0.1+35550*0.12+(MAX(0,I10+E10*Inputs!B43-Inputs!B42)-47150)*0.22,11600*0.1+35550*0.12+53375*0.22+(MAX(0,I10+E10*Inputs!B43-Inputs!B42)-100525)*0.24)))),MAX(0,IF(MAX(0,I10+E10*Inputs!B43-Inputs!B42)<=23200,MAX(0,I10+E10*Inputs!B43-Inputs!B42)*0.1,IF(MAX(0,I10+E10*Inputs!B43-Inputs!B42)<=94300,23200*0.1+(MAX(0,I10+E10*Inputs!B43-Inputs!B42)-23200)*0.12,IF(MAX(0,I10+E10*Inputs!B43-Inputs!B42)<=201050,23200*0.1+71100*0.12+(MAX(0,I10+E10*Inputs!B43-Inputs!B42)-94300)*0.22,23200*0.1+71100*0.12+106750*0.22+(MAX(0,I10+E10*Inputs!B43-Inputs!B42)-201050)*0.24))))) -> 21137 | K10: =ROUND(I10*0.0637,0) -> 8251 | L10: =E10+I10-H10-J10-K10 -> -7468.6555
A11: 69 | B11: =IF(A11>=C4,"Single","MFJ") -> MFJ | C11: ='Withdrawal Plan'!H7 -> 50076.99 | D11: =IF(A11>=C4,0,'Withdrawal Plan'!I7) -> 0 | E11: =C11+D11 -> 50076.99 | F11: ='Withdrawal Plan'!B7*IF(A11>=$C$4,1-$C$5,1) -> 94542.74 | G11: ='Withdrawal Plan'!C7 -> 36000 | H11: =F11+G11+'Withdrawal Plan'!D7+IF(A11>=C4,0,'Withdrawal Plan'!E7)+'Withdrawal Plan'!F7 -> 159341.16 | I11: ='Roth Conversion'!E7 -> 128484.56 | J11: =IF(A11>=$C$4,MAX(0,IF(MAX(0,I11+E11*Inputs!B43-Inputs!B42)<=11600,MAX(0,I11+E11*Inputs!B43-Inputs!B42)*0.1,IF(MAX(0,I11+E11*Inputs!B43-Inputs!B42)<=47150,11600*0.1+(MAX(0,I11+E11*Inputs!B43-Inputs!B42)-11600)*0.12,IF(MAX(0,I11+E11*Inputs!B43-Inputs!B42)<=100525,11600*0.1+35550*0.12+(MAX(0,I11+E11*Inputs!B43-Inputs!B42)-47150)*0.22,11600*0.1+35550*0.12+53375*0.22+(MAX(0,I11+E11*Inputs!B43-Inputs!B42)-100525)*0.24)))),MAX(0,IF(MAX(0,I11+E11*Inputs!B43-Inputs!B42)<=23200,MAX(0,I11+E11*Inputs!B43-Inputs!B42)*0.1,IF(MAX(0,I11+E11*Inputs!B43-Inputs!B42)<=94300,23200*0.1+(MAX(0,I11+E11*Inputs!B43-Inputs!B42)-23200)*0.12,IF(MAX(0,I11+E11*Inputs!B43-Inputs!B42)<=201050,23200*0.1+71100*0.12+(MAX(0,I11+E11*Inputs!B43-Inputs!B42)-94300)*0.22,23200*0.1+71100*0.12+106750*0.22+(MAX(0,I11+E11*Inputs!B43-Inputs!B42)-201050)*0.24))))) -> 21137 | K11: =ROUND(I11*0.0637,0) -> 8184 | L11: =E11+I11-H11-J11-K11 -> -10100.615
A12: 70 | B12: =IF(A12>=C4,"Single","MFJ") -> MFJ | C12: ='Withdrawal Plan'!H8 -> 51328.915 | D12: =IF(A12>=C4,0,'Withdrawal Plan'!I8) -> 23832 | E12: =C12+D12 -> 75160.915 | F12: ='Withdrawal Plan'!B8*IF(A12>=$C$4,1-$C$5,1) -> 97379.022 | G12: ='Withdrawal Plan'!C8 -> 36000 | H12: =F12+G12+'Withdrawal Plan'!D8+IF(A12>=C4,0,'Withdrawal Plan'!E8)+'Withdrawal Plan'!F8 -> 152712.37 | I12: ='Roth Conversion'!E8 -> 127420.42 | J12: =IF(A12>=$C$4,MAX(0,IF(MAX(0,I12+E12*Inputs!B43-Inputs!B42)<=11600,MAX(0,I12+E12*Inputs!B43-Inputs!B42)*0.1,IF(MAX(0,I12+E12*Inputs!B43-Inputs!B42)<=47150,11600*0.1+(MAX(0,I12+E12*Inputs!B43-Inputs!B42)-11600)*0.12,IF(MAX(0,I12+E12*Inputs!B43-Inputs!B42)<=100525,11600*0.1+35550*0.12+(MAX(0,I12+E12*Inputs!B43-Inputs!B42)-47150)*0.22,11600*0.1+35550*0.12+53375*0.22+(MAX(0,I12+E12*Inputs!B43-Inputs!B42)-100525)*0.24)))),MAX(0,IF(MAX(0,I12+E12*Inputs!B43-Inputs!B42)<=23200,MAX(0,I12+E12*Inputs!B43-Inputs!B42)*0.1,IF(MAX(0,I12+E12*Inputs!B43-Inputs!B42)<=94300,23200*0.1+(MAX(0,I12+E12*Inputs!B43-Inputs!B42)-23200)*0.12,IF(MAX(0,I12+E12*Inputs!B43-Inputs!B42)<=201050,23200*0.1+71100*0.12+(MAX(0,I12+E12*Inputs!B43-Inputs!B42)-94300)*0.22,23200*0.1+71100*0.12+106750*0.22+(MAX(0,I12+E12*Inputs!B43-Inputs!B42)-201050)*0.24))))) -> 25593.584 | K12: =ROUND(I12*0.0637,0) -> 8117 | L12: =E12+I12-H12-J12-K12 -> 16158.386
A13: 71 | B13: =IF(A13>=C4,"Single","MFJ") -> MFJ | C13: ='Withdrawal Plan'!H9 -> 52612.138 | D13: =IF(A13>=C4,0,'Withdrawal Plan'!I9) -> 24427.8 | E13: =C13+D13 -> 77039.938 | F13: ='Withdrawal Plan'!B9*IF(A13>=$C$4,1-$C$5,1) -> 100300.39 | G13: ='Withdrawal Plan'!C9 -> 36000 | H13: =F13+G13+'Withdrawal Plan'!D9+IF(A13>=C4,0,'Withdrawal Plan'!E9)+'Withdrawal Plan'!F9 -> 155775.41 | I13: ='Roth Conversion'!E9 -> 126329.68 | J13: =IF(A13>=$C$4,MAX(0,IF(MAX(0,I13+E13*Inputs!B43-Inputs!B42)<=11600,MAX(0,I13+E13*Inputs!B43-Inputs!B42)*0.1,IF(MAX(0,I13+E13*Inputs!B43-Inputs!B42)<=47150,11600*0.1+(MAX(0,I13+E13*Inputs!B43-Inputs!B42)-11600)*0.12,IF(MAX(0,I13+E13*Inputs!B43-Inputs!B42)<=100525,11600*0.1+35550*0.12+(MAX(0,I13+E13*Inputs!B43-Inputs!B42)-47150)*0.22,11600*0.1+35550*0.12+53375*0.22+(MAX(0,I13+E13*Inputs!B43-Inputs!B42)-100525)*0.24)))),MAX(0,IF(MAX(0,I13+E13*Inputs!B43-Inputs!B42)<=23200,MAX(0,I13+E13*Inputs!B43-Inputs!B42)*0.1,IF(MAX(0,I13+E13*Inputs!B43-Inputs!B42)<=94300,23200*0.1+(MAX(0,I13+E13*Inputs!B43-Inputs!B42)-23200)*0.12,IF(MAX(0,I13+E13*Inputs!B43-Inputs!B42)<=201050,23200*0.1+71100*0.12+(MAX(0,I13+E13*Inputs!B43-Inputs!B42)-94300)*0.22,23200*0.1+71100*0.12+106750*0.22+(MAX(0,I13+E13*Inputs!B43-Inputs!B42)-201050)*0.24))))) -> 25704.999 | K13: =ROUND(I13*0.0637,0) -> 8047 | L13: =E13+I13-H13-J13-K13 -> 13842.217
A14: 72 | B14: =IF(A14>=C4,"Single","MFJ") -> MFJ | C14: ='Withdrawal Plan'!H10 -> 53927.441 | D14: =IF(A14>=C4,0,'Withdrawal Plan'!I10) -> 25038.495 | E14: =C14+D14 -> 78965.936 | F14: ='Withdrawal Plan'!B10*IF(A14>=$C$4,1-$C$5,1) -> 103309.4 | G14: ='Withdrawal Plan'!C10 -> 36000 | H14: =F14+G14+'Withdrawal Plan'!D10+IF(A14>=C4,0,'Withdrawal Plan'!E10)+'Withdrawal Plan'!F10 -> 158933.17 | I14: ='Roth Conversion'!E10 -> 125211.68 | J14: =IF(A14>=$C$4,MAX(0,IF(MAX(0,I14+E14*Inputs!B43-Inputs!B42)<=11600,MAX(0,I14+E14*Inputs!B43-Inputs!B42)*0.1,IF(MAX(0,I14+E14*Inputs!B43-Inputs!B42)<=47150,11600*0.1+(MAX(0,I14+E14*Inputs!B43-Inputs!B42)-11600)*0.12,IF(MAX(0,I14+E14*Inputs!B43-Inputs!B42)<=100525,11600*0.1+35550*0.12+(MAX(0,I14+E14*Inputs!B43-Inputs!B42)-47150)*0.22,11600*0.1+35550*0.12+53375*0.22+(MAX(0,I14+E14*Inputs!B43-Inputs!B42)-100525)*0.24)))),MAX(0,IF(MAX(0,I14+E14*Inputs!B43-Inputs!B42)<=23200,MAX(0,I14+E14*Inputs!B43-Inputs!B42)*0.1,IF(MAX(0,I14+E14*Inputs!B43-Inputs!B42)<=94300,23200*0.1+(MAX(0,I14+E14*Inputs!B43-Inputs!B42)-23200)*0.12,IF(MAX(0,I14+E14*Inputs!B43-Inputs!B42)<=201050,23200*0.1+71100*0.12+(MAX(0,I14+E14*Inputs!B43-Inputs!B42)-94300)*0.22,23200*0.1+71100*0.12+106750*0.22+(MAX(0,I14+E14*Inputs!B43-Inputs!B42)-201050)*0.24))))) -> 25819.199 | K14: =ROUND(I14*0.0637,0) -> 7976 | L14: =E14+I14-H14-J14-K14 -> 11449.245
A15: 73 | B15: =IF(A15>=C4,"Single","MFJ") -> MFJ | C15: ='Withdrawal Plan'!H11 -> 55275.627 | D15: =IF(A15>=C4,0,'Withdrawal Plan'!I11) -> 25664.457 | E15: =C15+D15 -> 80940.084 | F15: ='Withdrawal Plan'!B11*IF(A15>=$C$4,1-$C$5,1) -> 106408.69 | G15: ='Withdrawal Plan'!C11 -> 36000 | H15: =F15+G15+'Withdrawal Plan'!D11+IF(A15>=C4,0,'Withdrawal Plan'!E11)+'Withdrawal Plan'!F11 -> 162188.64 | I15: ='Roth Conversion'!E11 -> 124065.72 | J15: =IF(A15>=$C$4,MAX(0,IF(MAX(0,I15+E15*Inputs!B43-Inputs!B42)<=11600,MAX(0,I15+E15*Inputs!B43-Inputs!B42)*0.1,IF(MAX(0,I15+E15*Inputs!B43-Inputs!B42)<=47150,11600*0.1+(MAX(0,I15+E15*Inputs!B43-Inputs!B42)-11600)*0.12,IF(MAX(0,I15+E15*Inputs!B43-Inputs!B42)<=100525,11600*0.1+35550*0.12+(MAX(0,I15+E15*Inputs!B43-Inputs!B42)-47150)*0.22,11600*0.1+35550*0.12+53375*0.22+(MAX(0,I15+E15*Inputs!B43-Inputs!B42)-100525)*0.24)))),MAX(0,IF(MAX(0,I15+E15*Inputs!B43-Inputs!B42)<=23200,MAX(0,I15+E15*Inputs!B43-Inputs!B42)*0.1,IF(MAX(0,I15+E15*Inputs!B43-Inputs!B42)<=94300,23200*0.1+(MAX(0,I15+E15*Inputs!B43-Inputs!B42)-23200)*0.12,IF(MAX(0,I15+E15*Inputs!B43-Inputs!B42)<=201050,23200*0.1+71100*0.12+(MAX(0,I15+E15*Inputs!B43-Inputs!B42)-94300)*0.22,23200*0.1+71100*0.12+106750*0.22+(MAX(0,I15+E15*Inputs!B43-Inputs!B42)-201050)*0.24))))) -> 25936.254 | K15: =ROUND(I15*0.0637,0) -> 7903 | L15: =E15+I15-H15-J15-K15 -> 8977.91
A16: 74 | B16: =IF(A16>=C4,"Single","MFJ") -> MFJ | C16: ='Withdrawal Plan'!H12 -> 56657.518 | D16: =IF(A16>=C4,0,'Withdrawal Plan'!I12) -> 26306.069 | E16: =C16+D16 -> 82963.587 | F16: ='Withdrawal Plan'!B12*IF(A16>=$C$4,1-$C$5,1) -> 109600.95 | G16: ='Withdrawal Plan'!C12 -> 36000 | H16: =F16+G16+'Withdrawal Plan'!D12+IF(A16>=C4,0,'Withdrawal Plan'!E12)+'Withdrawal Plan'!F12 -> 165544.9 | I16: ='Roth Conversion'!E12 -> 122891.11 | J16: =IF(A16>=$C$4,MAX(0,IF(MAX(0,I16+E16*Inputs!B43-Inputs!B42)<=11600,MAX(0,I16+E16*Inputs!B43-Inputs!B42)*0.1,IF(MAX(0,I16+E16*Inputs!B43-Inputs!B42)<=47150,11600*0.1+(MAX(0,I16+E16*Inputs!B43-Inputs!B42)-11600)*0.12,IF(MAX(0,I16+E16*Inputs!B43-Inputs!B42)<=100525,11600*0.1+35550*0.12+(MAX(0,I16+E16*Inputs!B43-Inputs!B42)-47150)*0.22,11600*0.1+35550*0.12+53375*0.22+(MAX(0,I16+E16*Inputs!B43-Inputs!B42)-100525)*0.24)))),MAX(0,IF(MAX(0,I16+E16*Inputs!B43-Inputs!B42)<=23200,MAX(0,I16+E16*Inputs!B43-Inputs!B42)*0.1,IF(MAX(0,I16+E16*Inputs!B43-Inputs!B42)<=94300,23200*0.1+(MAX(0,I16+E16*Inputs!B43-Inputs!B42)-23200)*0.12,IF(MAX(0,I16+E16*Inputs!B43-Inputs!B42)<=201050,23200*0.1+71100*0.12+(MAX(0,I16+E16*Inputs!B43-Inputs!B42)-94300)*0.22,23200*0.1+71100*0.12+106750*0.22+(MAX(0,I16+E16*Inputs!B43-Inputs!B42)-201050)*0.24))))) -> 26056.235 | K16: =ROUND(I16*0.0637,0) -> 7828 | L16: =E16+I16-H16-J16-K16 -> 6425.5655
A17: 75 | B17: =IF(A17>=C4,"Single","MFJ") -> Single | C17: ='Withdrawal Plan'!H13 -> 58073.956 | D17: =IF(A17>=C4,0,'Withdrawal Plan'!I13) -> 0 | E17: =C17+D17 -> 58073.956 | F17: ='Withdrawal Plan'!B13*IF(A17>=$C$4,1-$C$5,1) -> 90311.181 | G17: ='Withdrawal Plan'!C13 -> 36000 | H17: =F17+G17+'Withdrawal Plan'!D13+IF(A17>=C4,0,'Withdrawal Plan'!E13)+'Withdrawal Plan'!F13 -> 146427.33 | I17: ='Roth Conversion'!E13 -> 121687.14 | J17: =IF(A17>=$C$4,MAX(0,IF(MAX(0,I17+E17*Inputs!B43-Inputs!B42)<=11600,MAX(0,I17+E17*Inputs!B43-Inputs!B42)*0.1,IF(MAX(0,I17+E17*Inputs!B43-Inputs!B42)<=47150,11600*0.1+(MAX(0,I17+E17*Inputs!B43-Inputs!B42)-11600)*0.12,IF(MAX(0,I17+E17*Inputs!B43-Inputs!B42)<=100525,11600*0.1+35550*0.12+(MAX(0,I17+E17*Inputs!B43-Inputs!B42)-47150)*0.22,11600*0.1+35550*0.12+53375*0.22+(MAX(0,I17+E17*Inputs!B43-Inputs!B42)-100525)*0.24)))),MAX(0,IF(MAX(0,I17+E17*Inputs!B43-Inputs!B42)<=23200,MAX(0,I17+E17*Inputs!B43-Inputs!B42)*0.1,IF(MAX(0,I17+E17*Inputs!B43-Inputs!B42)<=94300,23200*0.1+(MAX(0,I17+E17*Inputs!B43-Inputs!B42)-23200)*0.12,IF(MAX(0,I17+E17*Inputs!B43-Inputs!B42)<=201050,23200*0.1+71100*0.12+(MAX(0,I17+E17*Inputs!B43-Inputs!B42)-94300)*0.22,23200*0.1+71100*0.12+106750*0.22+(MAX(0,I17+E17*Inputs!B43-Inputs!B42)-201050)*0.24))))) -> 26894.5 | K17: =ROUND(I17*0.0637,0) -> 7751 | L17: =E17+I17-H17-J17-K17 -> -1311.7334
A18: 76 | B18: =IF(A18>=C4,"Single","MFJ") -> Single | C18: ='Withdrawal Plan'!H14 -> 59525.805 | D18: =IF(A18>=C4,0,'Withdrawal Plan'!I14) -> 0 | E18: =C18+D18 -> 59525.805 | F18: ='Withdrawal Plan'!B14*IF(A18>=$C$4,1-$C$5,1) -> 93020.516 | G18: ='Withdrawal Plan'!C14 -> 36000 | H18: =F18+G18+'Withdrawal Plan'!D14+IF(A18>=C4,0,'Withdrawal Plan'!E14)+'Withdrawal Plan'!F14 -> 149317.47 | I18: ='Roth Conversion'!E14 -> 120453.07 | J18: =IF(A18>=$C$4,MAX(0,IF(MAX(0,I18+E18*Inputs!B43-Inputs!B42)<=11600,MAX(0,I18+E18*Inputs!B43-Inputs!B42)*0.1,IF(MAX(0,I18+E18*Inputs!B43-Inputs!B42)<=47150,11600*0.1+(MAX(0,I18+E18*Inputs!B43-Inputs!B42)-11600)*0.12,IF(MAX(0,I18+E18*Inputs!B43-Inputs!B42)<=100525,11600*0.1+35550*0.12+(MAX(0,I18+E18*Inputs!B43-Inputs!B42)-47150)*0.22,11600*0.1+35550*0.12+53375*0.22+(MAX(0,I18+E18*Inputs!B43-Inputs!B42)-100525)*0.24)))),MAX(0,IF(MAX(0,I18+E18*Inputs!B43-Inputs!B42)<=23200,MAX(0,I18+E18*Inputs!B43-Inputs!B42)*0.1,IF(MAX(0,I18+E18*Inputs!B43-Inputs!B42)<=94300,23200*0.1+(MAX(0,I18+E18*Inputs!B43-Inputs!B42)-23200)*0.12,IF(MAX(0,I18+E18*Inputs!B43-Inputs!B42)<=201050,23200*0.1+71100*0.12+(MAX(0,I18+E18*Inputs!B43-Inputs!B42)-94300)*0.22,23200*0.1+71100*0.12+106750*0.22+(MAX(0,I18+E18*Inputs!B43-Inputs!B42)-201050)*0.24))))) -> 26894.5 | K18: =ROUND(I18*0.0637,0) -> 7673 | L18: =E18+I18-H18-J18-K18 -> -3906.0988
A19: 77 | B19: =IF(A19>=C4,"Single","MFJ") -> Single | C19: ='Withdrawal Plan'!H15 -> 61013.95 | D19: =IF(A19>=C4,0,'Withdrawal Plan'!I15) -> 0 | E19: =C19+D19 -> 61013.95 | F19: ='Withdrawal Plan'!B15*IF(A19>=$C$4,1-$C$5,1) -> 95811.132 | G19: ='Withdrawal Plan'!C15 -> 36000 | H19: =F19+G19+'Withdrawal Plan'!D15+IF(A19>=C4,0,'Withdrawal Plan'!E15)+'Withdrawal Plan'!F15 -> 152297.93 | I19: ='Roth Conversion'!E15 -> 119188.14 | J19: =IF(A19>=$C$4,MAX(0,IF(MAX(0,I19+E19*Inputs!B43-Inputs!B42)<=11600,MAX(0,I19+E19*Inputs!B43-Inputs!B42)*0.1,IF(MAX(0,I19+E19*Inputs!B43-Inputs!B42)<=47150,11600*0.1+(MAX(0,I19+E19*Inputs!B43-Inputs!B42)-11600)*0.12,IF(MAX(0,I19+E19*Inputs!B43-Inputs!B42)<=100525,11600*0.1+35550*0.12+(MAX(0,I19+E19*Inputs!B43-Inputs!B42)-47150)*0.22,11600*0.1+35550*0.12+53375*0.22+(MAX(0,I19+E19*Inputs!B43-Inputs!B42)-100525)*0.24)))),MAX(0,IF(MAX(0,I19+E19*Inputs!B43-Inputs!B42)<=23200,MAX(0,I19+E19*Inputs!B43-Inputs!B42)*0.1,IF(MAX(0,I19+E19*Inputs!B43-Inputs!B42)<=94300,23200*0.1+(MAX(0,I19+E19*Inputs!B43-Inputs!B42)-23200)*0.12,IF(MAX(0,I19+E19*Inputs!B43-Inputs!B42)<=201050,23200*0.1+71100*0.12+(MAX(0,I19+E19*Inputs!B43-Inputs!B42)-94300)*0.22,23200*0.1+71100*0.12+106750*0.22+(MAX(0,I19+E19*Inputs!B43-Inputs!B42)-201050)*0.24))))) -> 26894.5 | K19: =ROUND(I19*0.0637,0) -> 7592 | L19: =E19+I19-H19-J19-K19 -> -6582.3402
A20: 78 | B20: =IF(A20>=C4,"Single","MFJ") -> Single | C20: ='Withdrawal Plan'!H16 -> 62539.298 | D20: =IF(A20>=C4,0,'Withdrawal Plan'!I16) -> 0 | E20: =C20+D20 -> 62539.298 | F20: ='Withdrawal Plan'!B16*IF(A20>=$C$4,1-$C$5,1) -> 98685.466 | G20: ='Withdrawal Plan'!C16 -> 0 | H20: =F20+G20+'Withdrawal Plan'!D16+IF(A20>=C4,0,'Withdrawal Plan'!E16)+'Withdrawal Plan'!F16 -> 119371.61 | I20: ='Roth Conversion'!E16 -> 117891.6 | J20: =IF(A20>=$C$4,MAX(0,IF(MAX(0,I20+E20*Inputs!B43-Inputs!B42)<=11600,MAX(0,I20+E20*Inputs!B43-Inputs!B42)*0.1,IF(MAX(0,I20+E20*Inputs!B43-Inputs!B42)<=47150,11600*0.1+(MAX(0,I20+E20*Inputs!B43-Inputs!B42)-11600)*0.12,IF(MAX(0,I20+E20*Inputs!B43-Inputs!B42)<=100525,11600*0.1+35550*0.12+(MAX(0,I20+E20*Inputs!B43-Inputs!B42)-47150)*0.22,11600*0.1+35550*0.12+53375*0.22+(MAX(0,I20+E20*Inputs!B43-Inputs!B42)-100525)*0.24)))),MAX(0,IF(MAX(0,I20+E20*Inputs!B43-Inputs!B42)<=23200,MAX(0,I20+E20*Inputs!B43-Inputs!B42)*0.1,IF(MAX(0,I20+E20*Inputs!B43-Inputs!B42)<=94300,23200*0.1+(MAX(0,I20+E20*Inputs!B43-Inputs!B42)-23200)*0.12,IF(MAX(0,I20+E20*Inputs!B43-Inputs!B42)<=201050,23200*0.1+71100*0.12+(MAX(0,I20+E20*Inputs!B43-Inputs!B42)-94300)*0.22,23200*0.1+71100*0.12+106750*0.22+(MAX(0,I20+E20*Inputs!B43-Inputs!B42)-201050)*0.24))))) -> 26894.5 | K20: =ROUND(I20*0.0637,0) -> 7510 | L20: =E20+I20-H20-J20-K20 -> 26654.788
A21: 79 | B21: =IF(A21>=C4,"Single","MFJ") -> Single | C21: ='Withdrawal Plan'!H17 -> 64102.781 | D21: =IF(A21>=C4,0,'Withdrawal Plan'!I17) -> 0 | E21: =C21+D21 -> 64102.781 | F21: ='Withdrawal Plan'!B17*IF(A21>=$C$4,1-$C$5,1) -> 101646.03 | G21: ='Withdrawal Plan'!C17 -> 0 | H21: =F21+G21+'Withdrawal Plan'!D17+IF(A21>=C4,0,'Withdrawal Plan'!E17)+'Withdrawal Plan'!F17 -> 122541.48 | I21: ='Roth Conversion'!E17 -> 116562.64 | J21: =IF(A21>=$C$4,MAX(0,IF(MAX(0,I21+E21*Inputs!B43-Inputs!B42)<=11600,MAX(0,I21+E21*Inputs!B43-Inputs!B42)*0.1,IF(MAX(0,I21+E21*Inputs!B43-Inputs!B42)<=47150,11600*0.1+(MAX(0,I21+E21*Inputs!B43-Inputs!B42)-11600)*0.12,IF(MAX(0,I21+E21*Inputs!B43-Inputs!B42)<=100525,11600*0.1+35550*0.12+(MAX(0,I21+E21*Inputs!B43-Inputs!B42)-47150)*0.22,11600*0.1+35550*0.12+53375*0.22+(MAX(0,I21+E21*Inputs!B43-Inputs!B42)-100525)*0.24)))),MAX(0,IF(MAX(0,I21+E21*Inputs!B43-Inputs!B42)<=23200,MAX(0,I21+E21*Inputs!B43-Inputs!B42)*0.1,IF(MAX(0,I21+E21*Inputs!B43-Inputs!B42)<=94300,23200*0.1+(MAX(0,I21+E21*Inputs!B43-Inputs!B42)-23200)*0.12,IF(MAX(0,I21+E21*Inputs!B43-Inputs!B42)<=201050,23200*0.1+71100*0.12+(MAX(0,I21+E21*Inputs!B43-Inputs!B42)-94300)*0.22,23200*0.1+71100*0.12+106750*0.22+(MAX(0,I21+E21*Inputs!B43-Inputs!B42)-201050)*0.24))))) -> 26894.5 | K21: =ROUND(I21*0.0637,0) -> 7425 | L21: =E21+I21-H21-J21-K21 -> 23804.439
A22: 80 | B22: =IF(A22>=C4,"Single","MFJ") -> Single | C22: ='Withdrawal Plan'!H18 -> 65705.35 | D22: =IF(A22>=C4,0,'Withdrawal Plan'!I18) -> 0 | E22: =C22+D22 -> 65705.35 | F22: ='Withdrawal Plan'!B18*IF(A22>=$C$4,1-$C$5,1) -> 104695.41 | G22: ='Withdrawal Plan'!C18 -> 0 | H22: =F22+G22+'Withdrawal Plan'!D18+IF(A22>=C4,0,'Withdrawal Plan'!E18)+'Withdrawal Plan'!F18 -> 125810.63 | I22: ='Roth Conversion'!E18 -> 115200.45 | J22: =IF(A22>=$C$4,MAX(0,IF(MAX(0,I22+E22*Inputs!B43-Inputs!B42)<=11600,MAX(0,I22+E22*Inputs!B43-Inputs!B42)*0.1,IF(MAX(0,I22+E22*Inputs!B43-Inputs!B42)<=47150,11600*0.1+(MAX(0,I22+E22*Inputs!B43-Inputs!B42)-11600)*0.12,IF(MAX(0,I22+E22*Inputs!B43-Inputs!B42)<=100525,11600*0.1+35550*0.12+(MAX(0,I22+E22*Inputs!B43-Inputs!B42)-47150)*0.22,11600*0.1+35550*0.12+53375*0.22+(MAX(0,I22+E22*Inputs!B43-Inputs!B42)-100525)*0.24)))),MAX(0,IF(MAX(0,I22+E22*Inputs!B43-Inputs!B42)<=23200,MAX(0,I22+E22*Inputs!B43-Inputs!B42)*0.1,IF(MAX(0,I22+E22*Inputs!B43-Inputs!B42)<=94300,23200*0.1+(MAX(0,I22+E22*Inputs!B43-Inputs!B42)-23200)*0.12,IF(MAX(0,I22+E22*Inputs!B43-Inputs!B42)<=201050,23200*0.1+71100*0.12+(MAX(0,I22+E22*Inputs!B43-Inputs!B42)-94300)*0.22,23200*0.1+71100*0.12+106750*0.22+(MAX(0,I22+E22*Inputs!B43-Inputs!B42)-201050)*0.24))))) -> 26894.5 | K22: =ROUND(I22*0.0637,0) -> 7338 | L22: =E22+I22-H22-J22-K22 -> 20862.672
A23: 81 | B23: =IF(A23>=C4,"Single","MFJ") -> Single | C23: ='Withdrawal Plan'!H19 -> 67347.984 | D23: =IF(A23>=C4,0,'Withdrawal Plan'!I19) -> 0 | E23: =C23+D23 -> 67347.984 | F23: ='Withdrawal Plan'!B19*IF(A23>=$C$4,1-$C$5,1) -> 107836.27 | G23: ='Withdrawal Plan'!C19 -> 0 | H23: =F23+G23+'Withdrawal Plan'!D19+IF(A23>=C4,0,'Withdrawal Plan'!E19)+'Withdrawal Plan'!F19 -> 129182.25 | I23: ='Roth Conversion'!E19 -> 113804.21 | J23: =IF(A23>=$C$4,MAX(0,IF(MAX(0,I23+E23*Inputs!B43-Inputs!B42)<=11600,MAX(0,I23+E23*Inputs!B43-Inputs!B42)*0.1,IF(MAX(0,I23+E23*Inputs!B43-Inputs!B42)<=47150,11600*0.1+(MAX(0,I23+E23*Inputs!B43-Inputs!B42)-11600)*0.12,IF(MAX(0,I23+E23*Inputs!B43-Inputs!B42)<=100525,11600*0.1+35550*0.12+(MAX(0,I23+E23*Inputs!B43-Inputs!B42)-47150)*0.22,11600*0.1+35550*0.12+53375*0.22+(MAX(0,I23+E23*Inputs!B43-Inputs!B42)-100525)*0.24)))),MAX(0,IF(MAX(0,I23+E23*Inputs!B43-Inputs!B42)<=23200,MAX(0,I23+E23*Inputs!B43-Inputs!B42)*0.1,IF(MAX(0,I23+E23*Inputs!B43-Inputs!B42)<=94300,23200*0.1+(MAX(0,I23+E23*Inputs!B43-Inputs!B42)-23200)*0.12,IF(MAX(0,I23+E23*Inputs!B43-Inputs!B42)<=201050,23200*0.1+71100*0.12+(MAX(0,I23+E23*Inputs!B43-Inputs!B42)-94300)*0.22,23200*0.1+71100*0.12+106750*0.22+(MAX(0,I23+E23*Inputs!B43-Inputs!B42)-201050)*0.24))))) -> 26894.5 | K23: =ROUND(I23*0.0637,0) -> 7249 | L23: =E23+I23-H23-J23-K23 -> 17826.443
A24: 82 | B24: =IF(A24>=C4,"Single","MFJ") -> Single | C24: ='Withdrawal Plan'!H20 -> 69031.684 | D24: =IF(A24>=C4,0,'Withdrawal Plan'!I20) -> 0 | E24: =C24+D24 -> 69031.684 | F24: ='Withdrawal Plan'!B20*IF(A24>=$C$4,1-$C$5,1) -> 111071.36 | G24: ='Withdrawal Plan'!C20 -> 0 | H24: =F24+G24+'Withdrawal Plan'!D20+IF(A24>=C4,0,'Withdrawal Plan'!E20)+'Withdrawal Plan'!F20 -> 132659.64 | I24: ='Roth Conversion'!E20 -> 112373.07 | J24: =IF(A24>=$C$4,MAX(0,IF(MAX(0,I24+E24*Inputs!B43-Inputs!B42)<=11600,MAX(0,I24+E24*Inputs!B43-Inputs!B42)*0.1,IF(MAX(0,I24+E24*Inputs!B43-Inputs!B42)<=47150,11600*0.1+(MAX(0,I24+E24*Inputs!B43-Inputs!B42)-11600)*0.12,IF(MAX(0,I24+E24*Inputs!B43-Inputs!B42)<=100525,11600*0.1+35550*0.12+(MAX(0,I24+E24*Inputs!B43-Inputs!B42)-47150)*0.22,11600*0.1+35550*0.12+53375*0.22+(MAX(0,I24+E24*Inputs!B43-Inputs!B42)-100525)*0.24)))),MAX(0,IF(MAX(0,I24+E24*Inputs!B43-Inputs!B42)<=23200,MAX(0,I24+E24*Inputs!B43-Inputs!B42)*0.1,IF(MAX(0,I24+E24*Inputs!B43-Inputs!B42)<=94300,23200*0.1+(MAX(0,I24+E24*Inputs!B43-Inputs!B42)-23200)*0.12,IF(MAX(0,I24+E24*Inputs!B43-Inputs!B42)<=201050,23200*0.1+71100*0.12+(MAX(0,I24+E24*Inputs!B43-Inputs!B42)-94300)*0.22,23200*0.1+71100*0.12+106750*0.22+(MAX(0,I24+E24*Inputs!B43-Inputs!B42)-201050)*0.24))))) -> 26894.5 | K24: =ROUND(I24*0.0637,0) -> 7158 | L24: =E24+I24-H24-J24-K24 -> 14692.611
A25: 83 | B25: =IF(A25>=C4,"Single","MFJ") -> Single | C25: ='Withdrawal Plan'!H21 -> 70757.476 | D25: =IF(A25>=C4,0,'Withdrawal Plan'!I21) -> 0 | E25: =C25+D25 -> 70757.476 | F25: ='Withdrawal Plan'!B21*IF(A25>=$C$4,1-$C$5,1) -> 114403.5 | G25: ='Withdrawal Plan'!C21 -> 0 | H25: =F25+G25+'Withdrawal Plan'!D21+IF(A25>=C4,0,'Withdrawal Plan'!E21)+'Withdrawal Plan'!F21 -> 136246.2 | I25: ='Roth Conversion'!E21 -> 110906.15 | J25: =IF(A25>=$C$4,MAX(0,IF(MAX(0,I25+E25*Inputs!B43-Inputs!B42)<=11600,MAX(0,I25+E25*Inputs!B43-Inputs!B42)*0.1,IF(MAX(0,I25+E25*Inputs!B43-Inputs!B42)<=47150,11600*0.1+(MAX(0,I25+E25*Inputs!B43-Inputs!B42)-11600)*0.12,IF(MAX(0,I25+E25*Inputs!B43-Inputs!B42)<=100525,11600*0.1+35550*0.12+(MAX(0,I25+E25*Inputs!B43-Inputs!B42)-47150)*0.22,11600*0.1+35550*0.12+53375*0.22+(MAX(0,I25+E25*Inputs!B43-Inputs!B42)-100525)*0.24)))),MAX(0,IF(MAX(0,I25+E25*Inputs!B43-Inputs!B42)<=23200,MAX(0,I25+E25*Inputs!B43-Inputs!B42)*0.1,IF(MAX(0,I25+E25*Inputs!B43-Inputs!B42)<=94300,23200*0.1+(MAX(0,I25+E25*Inputs!B43-Inputs!B42)-23200)*0.12,IF(MAX(0,I25+E25*Inputs!B43-Inputs!B42)<=201050,23200*0.1+71100*0.12+(MAX(0,I25+E25*Inputs!B43-Inputs!B42)-94300)*0.22,23200*0.1+71100*0.12+106750*0.22+(MAX(0,I25+E25*Inputs!B43-Inputs!B42)-201050)*0.24))))) -> 26894.5 | K25: =ROUND(I25*0.0637,0) -> 7065 | L25: =E25+I25-H25-J25-K25 -> 11457.925
A26: 84 | B26: =IF(A26>=C4,"Single","MFJ") -> Single | C26: ='Withdrawal Plan'!H22 -> 72526.413 | D26: =IF(A26>=C4,0,'Withdrawal Plan'!I22) -> 0 | E26: =C26+D26 -> 72526.413 | F26: ='Withdrawal Plan'!B22*IF(A26>=$C$4,1-$C$5,1) -> 117835.61 | G26: ='Withdrawal Plan'!C22 -> 0 | H26: =F26+G26+'Withdrawal Plan'!D22+IF(A26>=C4,0,'Withdrawal Plan'!E22)+'Withdrawal Plan'!F22 -> 139945.44 | I26: ='Roth Conversion'!E22 -> 109402.55 | J26: =IF(A26>=$C$4,MAX(0,IF(MAX(0,I26+E26*Inputs!B43-Inputs!B42)<=11600,MAX(0,I26+E26*Inputs!B43-Inputs!B42)*0.1,IF(MAX(0,I26+E26*Inputs!B43-Inputs!B42)<=47150,11600*0.1+(MAX(0,I26+E26*Inputs!B43-Inputs!B42)-11600)*0.12,IF(MAX(0,I26+E26*Inputs!B43-Inputs!B42)<=100525,11600*0.1+35550*0.12+(MAX(0,I26+E26*Inputs!B43-Inputs!B42)-47150)*0.22,11600*0.1+35550*0.12+53375*0.22+(MAX(0,I26+E26*Inputs!B43-Inputs!B42)-100525)*0.24)))),MAX(0,IF(MAX(0,I26+E26*Inputs!B43-Inputs!B42)<=23200,MAX(0,I26+E26*Inputs!B43-Inputs!B42)*0.1,IF(MAX(0,I26+E26*Inputs!B43-Inputs!B42)<=94300,23200*0.1+(MAX(0,I26+E26*Inputs!B43-Inputs!B42)-23200)*0.12,IF(MAX(0,I26+E26*Inputs!B43-Inputs!B42)<=201050,23200*0.1+71100*0.12+(MAX(0,I26+E26*Inputs!B43-Inputs!B42)-94300)*0.22,23200*0.1+71100*0.12+106750*0.22+(MAX(0,I26+E26*Inputs!B43-Inputs!B42)-201050)*0.24))))) -> 26894.5 | K26: =ROUND(I26*0.0637,0) -> 6969 | L26: =E26+I26-H26-J26-K26 -> 8120.0257
A27: 85 | B27: =IF(A27>=C4,"Single","MFJ") -> Single | C27: ='Withdrawal Plan'!H23 -> 74339.573 | D27: =IF(A27>=C4,0,'Withdrawal Plan'!I23) -> 0 | E27: =C27+D27 -> 74339.573 | F27: ='Withdrawal Plan'!B23*IF(A27>=$C$4,1-$C$5,1) -> 121370.67 | G27: ='Withdrawal Plan'!C23 -> 0 | H27: =F27+G27+'Withdrawal Plan'!D23+IF(A27>=C4,0,'Withdrawal Plan'!E23)+'Withdrawal Plan'!F23 -> 143761 | I27: ='Roth Conversion'!E23 -> 107861.36 | J27: =IF(A27>=$C$4,MAX(0,IF(MAX(0,I27+E27*Inputs!B43-Inputs!B42)<=11600,MAX(0,I27+E27*Inputs!B43-Inputs!B42)*0.1,IF(MAX(0,I27+E27*Inputs!B43-Inputs!B42)<=47150,11600*0.1+(MAX(0,I27+E27*Inputs!B43-Inputs!B42)-11600)*0.12,IF(MAX(0,I27+E27*Inputs!B43-Inputs!B42)<=100525,11600*0.1+35550*0.12+(MAX(0,I27+E27*Inputs!B43-Inputs!B42)-47150)*0.22,11600*0.1+35550*0.12+53375*0.22+(MAX(0,I27+E27*Inputs!B43-Inputs!B42)-100525)*0.24)))),MAX(0,IF(MAX(0,I27+E27*Inputs!B43-Inputs!B42)<=23200,MAX(0,I27+E27*Inputs!B43-Inputs!B42)*0.1,IF(MAX(0,I27+E27*Inputs!B43-Inputs!B42)<=94300,23200*0.1+(MAX(0,I27+E27*Inputs!B43-Inputs!B42)-23200)*0.12,IF(MAX(0,I27+E27*Inputs!B43-Inputs!B42)<=201050,23200*0.1+71100*0.12+(MAX(0,I27+E27*Inputs!B43-Inputs!B42)-94300)*0.22,23200*0.1+71100*0.12+106750*0.22+(MAX(0,I27+E27*Inputs!B43-Inputs!B42)-201050)*0.24))))) -> 26894.5 | K27: =ROUND(I27*0.0637,0) -> 6871 | L27: =E27+I27-H27-J27-K27 -> 4674.4401

Sheet Portfolio
A1: PORTFOLIO BALANCE PROJECTION (Ages 56–85)
A2: Age | B2: Trad 401k ($) | C2: Your Roth ($) | D2: Wife Roth ($) | E2: Wife Trad ($) | F2: HSA ($) | G2: Brokerage ($) | H2: Total Portfolio ($) | I2: Net Worth +Home ($) (home appreciates)
A3: 56 | B3: =Inputs!B9+Inputs!B11*(1+Inputs!B12/100) -> 3037518.8 | C3: =(Inputs!B10+Inputs!B13)*(1+Inputs!B19) -> 810000 | D3: =Inputs!E11*(1+Inputs!B19) -> 10800 | E3: =Inputs!E10*(1+Inputs!B19) -> 54000 | F3: =(Inputs!B14+Inputs!B15)*(1+Inputs!B19) -> 116640 | G3: =Inputs!B16*(1+Inputs!B19) -> 540000 | H3: =SUM(B3:G3) -> 4568958.8 | I3: =H3+Inputs!B36*POWER(1+Inputs!B52,VALUE(A3)-Inputs!B4) -> 5368958.8
A4: 57 | B4: =B3*(1+Inputs!B19)+Inputs!B11*(1+Inputs!B12/100) -> 3318039 | C4: =C3*(1+Inputs!B19) -> 874800 | D4: =D3*(1+Inputs!B19) -> 11664 | E4: =E3*(1+Inputs!B19) -> 58320 | F4: =(F3+Inputs!B15)*(1+Inputs!B19) -> 134611.2 | G4: =G3*(1+Inputs!B19) -> 583200 | H4: =SUM(B4:G4) -> 4980634.2 | I4: =H4+Inputs!B36*POWER(1+Inputs!B52,VALUE(A4)-Inputs!B4) -> 5816634.2
A5: 58 | B5: =B4*(1+Inputs!B19)+Inputs!B11*(1+Inputs!B12/100) -> 3621000.9 | C5: =C4*(1+Inputs!B19) -> 944784 | D5: =D4*(1+Inputs!B19) -> 12597.12 | E5: =E4*(1+Inputs!B19) -> 62985.6 | F5: =(F4+Inputs!B15)*(1+Inputs!B19) -> 154020.1 | G5: =G4*(1+Inputs!B19) -> 629856 | H5: =SUM(B5:G5) -> 5425243.7 | I5: =H5+Inputs!B36*POWER(1+Inputs!B52,VALUE(A5)-Inputs!B4) -> 6298863.7
A6: 59 | B6: =B5*(1+Inputs!B19)+Inputs!B11*(1+Inputs!B12/100) -> 3948199.7 | C6: =C5*(1+Inputs!B19) -> 1020366.7 | D6: =D5*(1+Inputs!B19) -> 13604.89 | E6: =E5*(1+Inputs!B19) -> 68024.448 | F6: =(F5+Inputs!B15)*(1+Inputs!B19) -> 174981.7 | G6: =G5*(1+Inputs!B19) -> 680244.48 | H6: =SUM(B6:G6) -> 5905421.9 | I6: =H6+Inputs!B36*POWER(1+Inputs!B52,VALUE(A6)-Inputs!B4) -> 6818354.8
A7: 60 | B7: =B6*(1+Inputs!B19)+Inputs!B11*(1+Inputs!B12/100) -> 4301574.4 | C7: =C6*(1+Inputs!B19) -> 1101996.1 | D7: =D6*(1+Inputs!B19) -> 14693.281 | E7: =E6*(1+Inputs!B19) -> 73466.404 | F7: =(F6+Inputs!B15)*(1+Inputs!B19) -> 197620.24 | G7: =G6*(1+Inputs!B19) -> 734664.04 | H7: =SUM(B7:G7) -> 6424014.4 | I7: =H7+Inputs!B36*POWER(1+Inputs!B52,VALUE(A7)-Inputs!B4) -> 7378029.3
A8: 61 | B8: =B7*(1+Inputs!B19)+Inputs!B11*(1+Inputs!B12/100) -> 4683219.1 | C8: =C7*(1+Inputs!B19) -> 1190155.7 | D8: =D7*(1+Inputs!B19) -> 15868.743 | E8: =E7*(1+Inputs!B19) -> 79343.716 | F8: =(F7+Inputs!B15)*(1+Inputs!B19) -> 222069.86 | G8: =G7*(1+Inputs!B19) -> 793437.16 | H8: =SUM(B8:G8) -> 6984094.3 | I8: =H8+Inputs!B36*POWER(1+Inputs!B52,VALUE(A8)-Inputs!B4) -> 7981039.9
A9: 62 | B9: =B8*(1+Inputs!B19)+Inputs!B11*(1+Inputs!B12/100) -> 5095395.4 | C9: =C8*(1+Inputs!B19) -> 1285368.2 | D9: =D8*(1+Inputs!B19) -> 17138.243 | E9: =E8*(1+Inputs!B19) -> 85691.213 | F9: =(F8+Inputs!B15)*(1+Inputs!B19) -> 248475.45 | G9: =G8*(1+Inputs!B19) -> 856912.13 | H9: =SUM(B9:G9) -> 7588980.6 | I9: =H9+Inputs!B36*POWER(1+Inputs!B52,VALUE(A9)-Inputs!B4) -> 8630788.7
A10: 63 | B10: =B9*(1+Inputs!B19)+Inputs!B11*(1+Inputs!B12/100) -> 5540545.8 | C10: =C9*(1+Inputs!B19) -> 1388197.7 | D10: =D9*(1+Inputs!B19) -> 18509.302 | E10: =E9*(1+Inputs!B19) -> 92546.511 | F10: =(F9+Inputs!B15)*(1+Inputs!B19) -> 276993.48 | G10: =G9*(1+Inputs!B19) -> 925465.11 | H10: =SUM(B10:G10) -> 8242257.8 | I10: =H10+Inputs!B36*POWER(1+Inputs!B52,VALUE(A10)-Inputs!B4) -> 9330947.3
A11: 64 | B11: =B10*(1+Inputs!B19)+Inputs!B11*(1+Inputs!B12/100) -> 6021308.2 | C11: =C10*(1+Inputs!B19) -> 1499253.5 | D11: =D10*(1+Inputs!B19) -> 19990.046 | E11: =E10*(1+Inputs!B19) -> 99950.231 | F11: =(F10+Inputs!B15)*(1+Inputs!B19) -> 307792.96 | G11: =G10*(1+Inputs!B19) -> 999502.31 | H11: =SUM(B11:G11) -> 8947797.2 | I11: =H11+Inputs!B36*POWER(1+Inputs!B52,VALUE(A11)-Inputs!B4) -> 10085478
A12: 65 | B12: ='Roth Conversion'!J3 -> 2828950 | C12: =MAX(0,C11*(1+Inputs!B19)-'Withdrawal Plan'!K3) -> 1619193.7 | D12: =D11*(1+Inputs!B19) -> 21589.25 | E12: =E11*(1+Inputs!B19) -> 107946.25 | F12: =MAX(0,F11*(1+Inputs!B19)-'Withdrawal Plan'!M3) -> 330196.4 | G12: =MAX(0,G11*(1+Inputs!B19)-Inputs!B50*Inputs!B51-'Withdrawal Plan'!L3) -> 1079462.5 | H12: =SUM(B12:G12) -> 5987338.1 | I12: =H12+Inputs!B36*POWER(1+Inputs!B52,VALUE(A12)-Inputs!B4) -> 7176214.3
A13: 66 | B13: ='Roth Conversion'!J4 -> 2657900 | C13: =MAX(0,C12*(1+Inputs!B19)-'Withdrawal Plan'!K4) -> 1748729.2 | D13: =D12*(1+Inputs!B19) -> 23316.39 | E13: =E12*(1+Inputs!B19) -> 116581.95 | F13: =MAX(0,F12*(1+Inputs!B19)-'Withdrawal Plan'!M4) -> 354281.11 | G13: =MAX(0,G12*(1+Inputs!B19)-'Withdrawal Plan'!L4) -> 1165819.5 | H13: =SUM(B13:G13) -> 6066628.2 | I13: =H13+Inputs!B36*POWER(1+Inputs!B52,VALUE(A13)-Inputs!B4) -> 7309003.7
A14: 67 | B14: ='Roth Conversion'!J5 -> 2527364.4 | C14: =MAX(0,C13*(1+Inputs!B19)-'Withdrawal Plan'!K5) -> 1888627.6 | D14: =D13*(1+Inputs!B19) -> 25181.701 | E14: =E13*(1+Inputs!B19) -> 125908.51 | F14: =MAX(0,F13*(1+Inputs!B19)-'Withdrawal Plan'!M5) -> 380176.05 | G14: =MAX(0,G13*(1+Inputs!B19)-'Withdrawal Plan'!L5) -> 1259085.1 | H14: =SUM(B14:G14) -> 6206343.3 | I14: =H14+Inputs!B36*POWER(1+Inputs!B52,VALUE(A14)-Inputs!B4) -> 7504625.7
A15: 68 | B15: ='Roth Conversion'!J6 -> 2397841.7 | C15: =MAX(0,C14*(1+Inputs!B19)-'Withdrawal Plan'!K6) -> 2039717.8 | D15: =D14*(1+Inputs!B19) -> 27196.237 | E15: =E14*(1+Inputs!B19) -> 135981.19 | F15: =MAX(0,F14*(1+Inputs!B19)-'Withdrawal Plan'!M6) -> 408020.21 | G15: =MAX(0,G14*(1+Inputs!B19)-'Withdrawal Plan'!L6) -> 1359811.9 | H15: =SUM(B15:G15) -> 6368568.9 | I15: =H15+Inputs!B36*POWER(1+Inputs!B52,VALUE(A15)-Inputs!B4) -> 7725274.1
A16: 69 | B16: ='Roth Conversion'!J7 -> 2269357.1 | C16: =MAX(0,C15*(1+Inputs!B19)-'Withdrawal Plan'!K7) -> 2202895.2 | D16: =D15*(1+Inputs!B19) -> 29371.936 | E16: =E15*(1+Inputs!B19) -> 146859.68 | F16: =MAX(0,F15*(1+Inputs!B19)-'Withdrawal Plan'!M7) -> 437963.4 | G16: =MAX(0,G15*(1+Inputs!B19)-'Withdrawal Plan'!L7) -> 1468596.8 | H16: =SUM(B16:G16) -> 6555044.1 | I16: =H16+Inputs!B36*POWER(1+Inputs!B52,VALUE(A16)-Inputs!B4) -> 7972801
A17: 70 | B17: ='Roth Conversion'!J8 -> 2141936.7 | C17: =MAX(0,C16*(1+Inputs!B19)-'Withdrawal Plan'!K8) -> 2379126.8 | D17: =D16*(1+Inputs!B19) -> 31721.691 | E17: =E16*(1+Inputs!B19) -> 158608.46 | F17: =MAX(0,F16*(1+Inputs!B19)-'Withdrawal Plan'!M8) -> 470167.13 | G17: =MAX(0,G16*(1+Inputs!B19)-'Withdrawal Plan'!L8) -> 1586084.6 | H17: =SUM(B17:G17) -> 6767645.3 | I17: =H17+Inputs!B36*POWER(1+Inputs!B52,VALUE(A17)-Inputs!B4) -> 8249201.3
A18: 71 | B18: ='Roth Conversion'!J9 -> 2015607 | C18: =MAX(0,C17*(1+Inputs!B19)-'Withdrawal Plan'!K9) -> 2569457 | D18: =D17*(1+Inputs!B19) -> 34259.426 | E18: =E17*(1+Inputs!B19) -> 171297.13 | F18: =MAX(0,F17*(1+Inputs!B19)-'Withdrawal Plan'!M9) -> 504805.48 | G18: =MAX(0,G17*(1+Inputs!B19)-'Withdrawal Plan'!L9) -> 1712971.3 | H18: =SUM(B18:G18) -> 7008397.3 | I18: =H18+Inputs!B36*POWER(1+Inputs!B52,VALUE(A18)-Inputs!B4) -> 8556623.3
A19: 72 | B19: ='Roth Conversion'!J10 -> 1890395.3 | C19: =MAX(0,C18*(1+Inputs!B19)-'Withdrawal Plan'!K10) -> 2775013.5 | D19: =D18*(1+Inputs!B19) -> 37000.181 | E19: =E18*(1+Inputs!B19) -> 185000.9 | F19: =MAX(0,F18*(1+Inputs!B19)-'Withdrawal Plan'!M10) -> 542066.16 | G19: =MAX(0,G18*(1+Inputs!B19)-'Withdrawal Plan'!L10) -> 1850009 | H19: =SUM(B19:G19) -> 7279485.1 | I19: =H19+Inputs!B36*POWER(1+Inputs!B52,VALUE(A19)-Inputs!B4) -> 8897381.3
A20: 73 | B20: ='Roth Conversion'!J11 -> 1766329.6 | C20: =MAX(0,C19*(1+Inputs!B19)-'Withdrawal Plan'!K11) -> 2997014.6 | D20: =D19*(1+Inputs!B19) -> 39960.195 | E20: =E19*(1+Inputs!B19) -> 199800.97 | F20: =MAX(0,F19*(1+Inputs!B19)-'Withdrawal Plan'!M11) -> 582151.5 | G20: =MAX(0,G19*(1+Inputs!B19)-'Withdrawal Plan'!L11) -> 1998009.7 | H20: =SUM(B20:G20) -> 7583266.6 | I20: =H20+Inputs!B36*POWER(1+Inputs!B52,VALUE(A20)-Inputs!B4) -> 9273968.1
A21: 74 | B21: ='Roth Conversion'!J12 -> 1643438.5 | C21: =MAX(0,C20*(1+Inputs!B19)-'Withdrawal Plan'!K12) -> 3236775.8 | D21: =D20*(1+Inputs!B19) -> 43157.011 | E21: =E20*(1+Inputs!B19) -> 215785.05 | F21: =MAX(0,F20*(1+Inputs!B19)-'Withdrawal Plan'!M12) -> 625279.67 | G21: =MAX(0,G20*(1+Inputs!B19)-'Withdrawal Plan'!L12) -> 2157850.5 | H21: =SUM(B21:G21) -> 7922286.6 | I21: =H21+Inputs!B36*POWER(1+Inputs!B52,VALUE(A21)-Inputs!B4) -> 9689069.6
A22: 75 | B22: ='Roth Conversion'!J13 -> 1521751.4 | C22: =MAX(0,C21*(1+Inputs!B19)-'Withdrawal Plan'!K13) -> 3495717.9 | D22: =D21*(1+Inputs!B19) -> 46609.571 | E22: =E21*(1+Inputs!B19) -> 233047.86 | F22: =MAX(0,F21*(1+Inputs!B19)-'Withdrawal Plan'!M13) -> 671685.9 | G22: =MAX(0,G21*(1+Inputs!B19)-'Withdrawal Plan'!L13) -> 2330478.6 | H22: =SUM(B22:G22) -> 8299291.1 | I22: =H22+Inputs!B36*POWER(1+Inputs!B52,VALUE(A22)-Inputs!B4) -> 10145579
A23: 76 | B23: ='Roth Conversion'!J14 -> 1401298.3 | C23: =MAX(0,C22*(1+Inputs!B19)-'Withdrawal Plan'!K14) -> 3775375.3 | D23: =D22*(1+Inputs!B19) -> 50338.337 | E23: =E22*(1+Inputs!B19) -> 251691.69 | F23: =MAX(0,F22*(1+Inputs!B19)-'Withdrawal Plan'!M14) -> 721623.82 | G23: =MAX(0,G22*(1+Inputs!B19)-'Withdrawal Plan'!L14) -> 2516916.9 | H23: =SUM(B23:G23) -> 8717244.3 | I23: =H23+Inputs!B36*POWER(1+Inputs!B52,VALUE(A23)-Inputs!B4) -> 10646615
A24: 77 | B24: ='Roth Conversion'!J15 -> 1282110.1 | C24: =MAX(0,C23*(1+Inputs!B19)-'Withdrawal Plan'!K15) -> 4077405.3 | D24: =D23*(1+Inputs!B19) -> 54365.404 | E24: =E23*(1+Inputs!B19) -> 271827.02 | F24: =MAX(0,F23*(1+Inputs!B19)-'Withdrawal Plan'!M15) -> 775366.92 | G24: =MAX(0,G23*(1+Inputs!B19)-'Withdrawal Plan'!L15) -> 2718270.2 | H24: =SUM(B24:G24) -> 9179345 | I24: =H24+Inputs!B36*POWER(1+Inputs!B52,VALUE(A24)-Inputs!B4) -> 11195538
A25: 78 | B25: ='Roth Conversion'!J16 -> 1164218.6 | C25: =MAX(0,C24*(1+Inputs!B19)-'Withdrawal Plan'!K16) -> 4403597.7 | D25: =D24*(1+Inputs!B19) -> 58714.636 | E25: =E24*(1+Inputs!B19) -> 293573.18 | F25: =MAX(0,F24*(1+Inputs!B19)-'Withdrawal Plan'!M16) -> 833210.14 | G25: =MAX(0,G24*(1+Inputs!B19)-'Withdrawal Plan'!L16) -> 2935731.8 | H25: =SUM(B25:G25) -> 9689046.1 | I25: =H25+Inputs!B36*POWER(1+Inputs!B52,VALUE(A25)-Inputs!B4) -> 11795968
A26: 79 | B26: ='Roth Conversion'!J17 -> 1047655.9 | C26: =MAX(0,C25*(1+Inputs!B19)-'Withdrawal Plan'!K17) -> 4755885.6 | D26: =D25*(1+Inputs!B19) -> 63411.807 | E26: =E25*(1+Inputs!B19) -> 317059.04 | F26: =MAX(0,F25*(1+Inputs!B19)-'Withdrawal Plan'!M17) -> 895471.5 | G26: =MAX(0,G25*(1+Inputs!B19)-'Withdrawal Plan'!L17) -> 3170590.4 | H26: =SUM(B26:G26) -> 10250074 | I26: =H26+Inputs!B36*POWER(1+Inputs!B52,VALUE(A26)-Inputs!B4) -> 12451807
A27: 80 | B27: ='Roth Conversion'!J18 -> 932455.46 | C27: =MAX(0,C26*(1+Inputs!B19)-'Withdrawal Plan'!K18) -> 5136356.4 | D27: =D26*(1+Inputs!B19) -> 68484.752 | E27: =E26*(1+Inputs!B19) -> 342423.76 | F27: =MAX(0,F26*(1+Inputs!B19)-'Withdrawal Plan'!M18) -> 962494 | G27: =MAX(0,G26*(1+Inputs!B19)-'Withdrawal Plan'!L18) -> 3424237.6 | H27: =SUM(B27:G27) -> 10866452 | I27: =H27+Inputs!B36*POWER(1+Inputs!B52,VALUE(A27)-Inputs!B4) -> 13167263
A28: 81 | B28: ='Roth Conversion'!J19 -> 818651.25 | C28: =MAX(0,C27*(1+Inputs!B19)-'Withdrawal Plan'!K19) -> 5547264.9 | D28: =D27*(1+Inputs!B19) -> 73963.532 | E28: =E27*(1+Inputs!B19) -> 369817.66 | F28: =MAX(0,F27*(1+Inputs!B19)-'Withdrawal Plan'!M19) -> 1034647.5 | G28: =MAX(0,G27*(1+Inputs!B19)-'Withdrawal Plan'!L19) -> 3698176.6 | H28: =SUM(B28:G28) -> 11542521 | I28: =H28+Inputs!B36*POWER(1+Inputs!B52,VALUE(A28)-Inputs!B4) -> 13946869
A29: 82 | B29: ='Roth Conversion'!J20 -> 706278.18 | C29: =MAX(0,C28*(1+Inputs!B19)-'Withdrawal Plan'!K20) -> 5991046.1 | D29: =D28*(1+Inputs!B19) -> 79880.615 | E29: =E28*(1+Inputs!B19) -> 399403.07 | F29: =MAX(0,F28*(1+Inputs!B19)-'Withdrawal Plan'!M20) -> 1112331.1 | G29: =MAX(0,G28*(1+Inputs!B19)-'Withdrawal Plan'!L20) -> 3994030.7 | H29: =SUM(B29:G29) -> 12282970 | I29: =H29+Inputs!B36*POWER(1+Inputs!B52,VALUE(A29)-Inputs!B4) -> 14795513
A30: 83 | B30: ='Roth Conversion'!J21 -> 595372.04 | C30: =MAX(0,C29*(1+Inputs!B19)-'Withdrawal Plan'!K21) -> 6470329.8 | D30: =D29*(1+Inputs!B19) -> 86271.064 | E30: =E29*(1+Inputs!B19) -> 431355.32 | F30: =MAX(0,F29*(1+Inputs!B19)-'Withdrawal Plan'!M21) -> 1195974.9 | G30: =MAX(0,G29*(1+Inputs!B19)-'Withdrawal Plan'!L21) -> 4313553.2 | H30: =SUM(B30:G30) -> 13092856 | I30: =H30+Inputs!B36*POWER(1+Inputs!B52,VALUE(A30)-Inputs!B4) -> 15718464
A31: 84 | B31: ='Roth Conversion'!J22 -> 485969.49 | C31: =MAX(0,C30*(1+Inputs!B19)-'Withdrawal Plan'!K22) -> 6987956.2 | D31: =D30*(1+Inputs!B19) -> 93172.749 | E31: =E30*(1+Inputs!B19) -> 465863.74 | F31: =MAX(0,F30*(1+Inputs!B19)-'Withdrawal Plan'!M22) -> 1286043 | G31: =MAX(0,G30*(1+Inputs!B19)-'Withdrawal Plan'!L22) -> 4658637.4 | H31: =SUM(B31:G31) -> 13977643 | I31: =H31+Inputs!B36*POWER(1+Inputs!B52,VALUE(A31)-Inputs!B4) -> 16721403
A32: 85 | B32: ='Roth Conversion'!J23 -> 378108.12 | C32: =MAX(0,C31*(1+Inputs!B19)-'Withdrawal Plan'!K23) -> 7546992.7 | D32: =D31*(1+Inputs!B19) -> 100626.57 | E32: =E31*(1+Inputs!B19) -> 503132.84 | F32: =MAX(0,F31*(1+Inputs!B19)-'Withdrawal Plan'!M23) -> 1383036.1 | G32: =MAX(0,G31*(1+Inputs!B19)-'Withdrawal Plan'!L23) -> 5031328.4 | H32: =SUM(B32:G32) -> 14943225 | I32: =H32+Inputs!B36*POWER(1+Inputs!B52,VALUE(A32)-Inputs!B4) -> 17810454
A34: Blue rows = working years (accumulation) · Orange rows = RMD years (age 73+) · White/cream = retirement years · Net Worth includes home value appreciating at Inputs!B52 rate per year

Sheet SS Comparison
A1: SOCIAL SECURITY START AGE COMPARISON
A2: Metric | B2: Age 65 | C2: Age 67 | D2: Age 70
A3: Monthly Benefit ($) | B3: =Inputs!B22 -> 3330 | C3: =Inputs!B23 -> 3972 | D3: =Inputs!B24 -> 5200
A4: Annual Benefit ($) | B4: =Inputs!B22*12 -> 39960 | C4: =Inputs!B23*12 -> 47664 | D4: =Inputs!B24*12 -> 62400
A5: Years of Benefits (to age 85) | B5: =85-65 -> 20 | C5: =85-67 -> 18 | D5: =85-70 -> 15
A6: Total SS to Age 85 ($) | B6: =Inputs!B22*12*20 -> 799200 | C6: =Inputs!B23*12*18 -> 857952 | D6: =Inputs!B24*12*15 -> 936000
A7: Approx Break-even vs Age 70 | B7: ~Age 77 | C7: ~Age 80 | D7: N/A
A8: Recommended? | B8: No — lower lifetime | C8: Possible | D8: Yes — maximises benefit

Sheet Advice
A1: RETIREMENT STRATEGY — KEY ADVICE
A2: TOPIC | B2: RECOMMENDATION
A3: Roth Conversion Window | B3: Ages 65–72: Convert up to top of 22% bracket (~$201k taxable income) each year before RMDs begin at 73. This lowers your future Traditional IRA balance and reduces mandatory RMD amounts.
A4: Social Security Timing | B4: Delay SS to age 70 to maximise benefit ($5,200/mo vs $3,330 at 65). Bridge the gap using brokerage and Roth draws. Break-even vs claiming at 67 is around age 80.
A5: Withdrawal Sequence | B5: Order: Traditional 401k (Roth conversions pre-73) → Brokerage (living expenses) → Roth IRA (tax-free, let it grow last) → HSA for Medicare premiums only.
A6: HSA Strategy | B6: Use HSA exclusively for YOUR Medicare Part B premiums + IRMAA surcharges (IRS-qualified, tax-free). Wife insurance from brokerage (not HSA-eligible). Estimated depletion ~age 78–80.
A7: IRMAA Management | B7: Keep MAGI ≤ $206k (MFJ) to avoid IRMAA surcharges, OR accept Tier 1 ($594/yr) to enable higher Roth conversions. If extra $30k conversion saves $6k in future taxes, the IRMAA cost is worth it.
A8: NJ vs Washington State | B8: Moving to WA (0% income tax) saves ~$6,000–$10,000/yr on Roth conversion income taxed at NJ ~6.37%. 10-year tax savings: ~$80–$100K. Factor in cost of living and housing trade-offs.
A9: RMDs at Age 73 | B9: Traditional 401k RMDs begin at 73. Pre-73 Roth conversions reduce this balance. Target Traditional balance ≤ $800K by age 73 to manage RMD size and avoid bracket creep.
A10: Portfolio Sustainability | B10: Retire with ~$3.2M+ total portfolio. At 8% growth and 3–4% withdrawal rate, portfolio sustains to age 90+. Run a 6% growth stress test to confirm resilience.
A11: NJ Property | B11: Daughter stays in NJ home. Continue paying mortgage ($2,250/mo) + property tax ($13,500/yr). Home value (~$650K) adds to net worth but is excluded from investable portfolio.
A12: Wife Insurance (Pre-Medicare) | B12: Wife needs private health insurance from YOUR retirement until she turns 65 (~$800/mo). Fund from brokerage — NOT HSA (spouse insurance is not an HSA-qualified expense).

Sheet Charts
A1: RETIREMENT CHARTS — data pulls live from other tabs
A3: Age | B3: Trad 401k | C3: Your Roth | D3: Wife Roth | E3: Wife Trad | F3: HSA | G3: Brokerage | H3: Net Worth
A4: =Portfolio!A3 -> 56 | B4: =Portfolio!B3 -> 3037518.8 | C4: =Portfolio!C3 -> 810000 | D4: =Portfolio!D3 -> 10800 | E4: =Portfolio!E3 -> 54000 | F4: =Portfolio!F3 -> 116640 | G4: =Portfolio!G3 -> 540000 | H4: =Portfolio!I3 -> 5368958.8
A5: =Portfolio!A4 -> 57 | B5: =Portfolio!B4 -> 3318039 | C5: =Portfolio!C4 -> 874800 | D5: =Portfolio!D4 -> 11664 | E5: =Portfolio!E4 -> 58320 | F5: =Portfolio!F4 -> 134611.2 | G5: =Portfolio!G4 -> 583200 | H5: =Portfolio!I4 -> 5816634.2
A6: =Portfolio!A5 -> 58 | B6: =Portfolio!B5 -> 3621000.9 | C6: =Portfolio!C5 -> 944784 | D6: =Portfolio!D5 -> 12597.12 | E6: =Portfolio!E5 -> 62985.6 | F6: =Portfolio!F5 -> 154020.1 | G6: =Portfolio!G5 -> 629856 | H6: =Portfolio!I5 -> 6298863.7
A7: =Portfolio!A6 -> 59 | B7: =Portfolio!B6 -> 3948199.7 | C7: =Portfolio!C6 -> 1020366.7 | D7: =Portfolio!D6 -> 13604.89 | E7: =Portfolio!E6 -> 68024.448 | F7: =Portfolio!F6 -> 174981.7 | G7: =Portfolio!G6 -> 680244.48 | H7: =Portfolio!I6 -> 6818354.8
A8: =Portfolio!A7 -> 60 | B8: =Portfolio!B7 -> 4301574.4 | C8: =Portfolio!C7 -> 1101996.1 | D8: =Portfolio!D7 -> 14693.281 | E8: =Portfolio!E7 -> 73466.404 | F8: =Portfolio!F7 -> 197620.24 | G8: =Portfolio!G7 -> 734664.04 | H8: =Portfolio!I7 -> 7378029.3
A9: =Portfolio!A8 -> 61 | B9: =Portfolio!B8 -> 4683219.1 | C9: =Portfolio!C8 -> 1190155.7 | D9: =Portfolio!D8 -> 15868.743 | E9: =Portfolio!E8 -> 79343.716 | F9: =Portfolio!F8 -> 222069.86 | G9: =Portfolio!G8 -> 793437.16 | H9: =Portfolio!I8 -> 7981039.9
A10: =Portfolio!A9 -> 62 | B10: =Portfolio!B9 -> 5095395.4 | C10: =Portfolio!C9 -> 1285368.2 | D10: =Portfolio!D9 -> 17138.243 | E10: =Portfolio!E9 -> 85691.213 | F10: =Portfolio!F9 -> 248475.45 | G10: =Portfolio!G9 -> 856912.13 | H10: =Portfolio!I9 -> 8630788.7
A11: =Portfolio!A10 -> 63 | B11: =Portfolio!B10 -> 5540545.8 | C11: =Portfolio!C10 -> 1388197.7 | D11: =Portfolio!D10 -> 18509.302 | E11: =Portfolio!E10 -> 92546.511 | F11: =Portfolio!F10 -> 276993.48 | G11: =Portfolio!G10 -> 925465.11 | H11: =Portfolio!I10 -> 9330947.3
A12: =Portfolio!A11 -> 64 | B12: =Portfolio!B11 -> 6021308.2 | C12: =Portfolio!C11 -> 1499253.5 | D12: =Portfolio!D11 -> 19990.046 | E12: =Portfolio!E11 -> 99950.231 | F12: =Portfolio!F11 -> 307792.96 | G12: =Portfolio!G11 -> 999502.31 | H12: =Portfolio!I11 -> 10085478
A13: =Portfolio!A12 -> 65 | B13: =Portfolio!B12 -> 2828950 | C13: =Portfolio!C12 -> 1619193.7 | D13: =Portfolio!D12 -> 21589.25 | E13: =Portfolio!E12 -> 107946.25 | F13: =Portfolio!F12 -> 330196.4 | G13: =Portfolio!G12 -> 1079462.5 | H13: =Portfolio!I12 -> 7176214.3
A14: =Portfolio!A13 -> 66 | B14: =Portfolio!B13 -> 2657900 | C14: =Portfolio!C13 -> 1748729.2 | D14: =Portfolio!D13 -> 23316.39 | E14: =Portfolio!E13 -> 116581.95 | F14: =Portfolio!F13 -> 354281.11 | G14: =Portfolio!G13 -> 1165819.5 | H14: =Portfolio!I13 -> 7309003.7
A15: =Portfolio!A14 -> 67 | B15: =Portfolio!B14 -> 2527364.4 | C15: =Portfolio!C14 -> 1888627.6 | D15: =Portfolio!D14 -> 25181.701 | E15: =Portfolio!E14 -> 125908.51 | F15: =Portfolio!F14 -> 380176.05 | G15: =Portfolio!G14 -> 1259085.1 | H15: =Portfolio!I14 -> 7504625.7
... A33: =Portfolio!A32 -> 85 | B33: =Portfolio!B32 -> 378108.12 | C33: =Portfolio!C32 -> 7546992.7 | D33: =Portfolio!D32 -> 100626.57 | E33: =Portfolio!E32 -> 503132.84 | F33: =Portfolio!F32 -> 1383036.1 | G33: =Portfolio!G32 -> 5031328.4 | H33: =Portfolio!I32 -> 17810454
A35: Age | B35: Your SS | C35: Wife SS | D35: Trad Draw | E35: Roth Draw | F35: Brok Draw | G35: Total Income | H35: Total Needs | I35: Fed Tax | J35: State Tax | K35: Surplus
A36: ='Withdrawal Plan'!A3 -> 65 | B36: ='Withdrawal Plan'!H3 -> 0 | C36: ='Withdrawal Plan'!I3 -> 0 | D36: ='Withdrawal Plan'!J3 -> 171050 | E36: ='Withdrawal Plan'!K3 -> 0 | F36: ='Withdrawal Plan'!L3 -> 0 | G36: =B36+C36+D36+E36+F36 -> 171050 | H36: ='Withdrawal Plan'!G3 -> 148320 | I36: ='Withdrawal Plan'!N3 -> 27737 | J36: ='Withdrawal Plan'!O3 -> 10895.885 | K36: ='Withdrawal Plan'!P3 -> -15902.885
A37: ='Withdrawal Plan'!A4 -> 66 | B37: ='Withdrawal Plan'!H4 -> 0 | C37: ='Withdrawal Plan'!I4 -> 0 | D37: ='Withdrawal Plan'!J4 -> 171050 | E37: ='Withdrawal Plan'!K4 -> 0 | F37: ='Withdrawal Plan'!L4 -> 0 | G37: =B37+C37+D37+E37+F37 -> 171050 | H37: ='Withdrawal Plan'!G4 -> 150951 | I37: ='Withdrawal Plan'!N4 -> 27737 | J37: ='Withdrawal Plan'!O4 -> 10895.885 | K37: ='Withdrawal Plan'!P4 -> -18533.885
A38: ='Withdrawal Plan'!A5 -> 67 | B38: ='Withdrawal Plan'!H5 -> 47664 | C38: ='Withdrawal Plan'!I5 -> 0 | D38: ='Withdrawal Plan'!J5 -> 130535.6 | E38: ='Withdrawal Plan'!K5 -> 0 | F38: ='Withdrawal Plan'!L5 -> 0 | G38: =B38+C38+D38+E38+F38 -> 178199.6 | H38: ='Withdrawal Plan'!G5 -> 153663.15 | I38: ='Withdrawal Plan'!N5 -> 27737 | J38: ='Withdrawal Plan'!O5 -> 8315.1177 | K38: ='Withdrawal Plan'!P5 -> -11515.668
A39: ='Withdrawal Plan'!A6 -> 68 | B39: ='Withdrawal Plan'!H6 -> 48855.6 | C39: ='Withdrawal Plan'!I6 -> 0 | D39: ='Withdrawal Plan'!J6 -> 129522.74 | E39: ='Withdrawal Plan'!K6 -> 0 | F39: ='Withdrawal Plan'!L6 -> 0 | G39: =B39+C39+D39+E39+F39 -> 178378.34 | H39: ='Withdrawal Plan'!G6 -> 156459 | I39: ='Withdrawal Plan'!N6 -> 27737 | J39: ='Withdrawal Plan'!O6 -> 8250.5985 | K39: ='Withdrawal Plan'!P6 -> -14068.254
A40: ='Withdrawal Plan'!A7 -> 69 | B40: ='Withdrawal Plan'!H7 -> 50076.99 | C40: ='Withdrawal Plan'!I7 -> 0 | D40: ='Withdrawal Plan'!J7 -> 128484.56 | E40: ='Withdrawal Plan'!K7 -> 0 | F40: ='Withdrawal Plan'!L7 -> 0 | G40: =B40+C40+D40+E40+F40 -> 178561.55 | H40: ='Withdrawal Plan'!G7 -> 159341.16 | I40: ='Withdrawal Plan'!N7 -> 27737 | J40: ='Withdrawal Plan'!O7 -> 8184.4664 | K40: ='Withdrawal Plan'!P7 -> -16701.082
A41: ='Withdrawal Plan'!A8 -> 70 | B41: ='Withdrawal Plan'!H8 -> 51328.915 | C41: ='Withdrawal Plan'!I8 -> 23832 | D41: ='Withdrawal Plan'!J8 -> 127420.42 | E41: ='Withdrawal Plan'!K8 -> 0 | F41: ='Withdrawal Plan'!L8 -> 0 | G41: =B41+C41+D41+E41+F41 -> 202581.34 | H41: ='Withdrawal Plan'!G8 -> 152712.37 | I41: ='Withdrawal Plan'!N8 -> 27737 | J41: ='Withdrawal Plan'!O8 -> 8116.6809 | K41: ='Withdrawal Plan'!P8 -> 14015.289
A42: ='Withdrawal Plan'!A9 -> 71 | B42: ='Withdrawal Plan'!H9 -> 52612.138 | C42: ='Withdrawal Plan'!I9 -> 24427.8 | D42: ='Withdrawal Plan'!J9 -> 126329.68 | E42: ='Withdrawal Plan'!K9 -> 0 | F42: ='Withdrawal Plan'!L9 -> 0 | G42: =B42+C42+D42+E42+F42 -> 203369.62 | H42: ='Withdrawal Plan'!G9 -> 155775.41 | I42: ='Withdrawal Plan'!N9 -> 27737 | J42: ='Withdrawal Plan'!O9 -> 8047.2008 | K42: ='Withdrawal Plan'!P9 -> 11810.015
A43: ='Withdrawal Plan'!A10 -> 72 | B43: ='Withdrawal Plan'!H10 -> 53927.441 | C43: ='Withdrawal Plan'!I10 -> 25038.495 | D43: ='Withdrawal Plan'!J10 -> 125211.68 | E43: ='Withdrawal Plan'!K10 -> 0 | F43: ='Withdrawal Plan'!L10 -> 0 | G43: =B43+C43+D43+E43+F43 -> 204177.61 | H43: ='Withdrawal Plan'!G10 -> 158933.17 | I43: ='Withdrawal Plan'!N10 -> 27737 | J43: ='Withdrawal Plan'!O10 -> 7975.9837 | K43: ='Withdrawal Plan'!P10 -> 9531.4598
A44: ='Withdrawal Plan'!A11 -> 73 | B44: ='Withdrawal Plan'!H11 -> 55275.627 | C44: ='Withdrawal Plan'!I11 -> 25664.457 | D44: ='Withdrawal Plan'!J11 -> 124065.72 | E44: ='Withdrawal Plan'!K11 -> 0 | F44: ='Withdrawal Plan'!L11 -> 0 | G44: =B44+C44+D44+E44+F44 -> 205005.8 | H44: ='Withdrawal Plan'!G11 -> 162188.64 | I44: ='Withdrawal Plan'!N11 -> 27737 | J44: ='Withdrawal Plan'!O11 -> 7902.9862 | K44: ='Withdrawal Plan'!P11 -> 7177.1773
A45: ='Withdrawal Plan'!A12 -> 74 | B45: ='Withdrawal Plan'!H12 -> 56657.518 | C45: ='Withdrawal Plan'!I12 -> 26306.069 | D45: ='Withdrawal Plan'!J12 -> 122891.11 | E45: ='Withdrawal Plan'!K12 -> 0 | F45: ='Withdrawal Plan'!L12 -> 0 | G45: =B45+C45+D45+E45+F45 -> 205854.7 | H45: ='Withdrawal Plan'!G12 -> 165544.9 | I45: ='Withdrawal Plan'!N12 -> 27737 | J45: ='Withdrawal Plan'!O12 -> 7828.1637 | K45: ='Withdrawal Plan'!P12 -> 4744.6367
A46: ='Withdrawal Plan'!A13 -> 75 | B46: ='Withdrawal Plan'!H13 -> 58073.956 | C46: ='Withdrawal Plan'!I13 -> 26963.721 | D46: ='Withdrawal Plan'!J13 -> 121687.14 | E46: ='Withdrawal Plan'!K13 -> 0 | F46: ='Withdrawal Plan'!L13 -> 0 | G46: =B46+C46+D46+E46+F46 -> 206724.81 | H46: ='Withdrawal Plan'!G13 -> 169005.12 | I46: ='Withdrawal Plan'!N13 -> 27737 | J46: ='Withdrawal Plan'!O13 -> 7751.4707 | K46: ='Withdrawal Plan'!P13 -> 2231.2213
A47: ='Withdrawal Plan'!A14 -> 76 | B47: ='Withdrawal Plan'!H14 -> 59525.805 | C47: ='Withdrawal Plan'!I14 -> 27637.814 | D47: ='Withdrawal Plan'!J14 -> 120453.07 | E47: ='Withdrawal Plan'!K14 -> 0 | F47: ='Withdrawal Plan'!L14 -> 0 | G47: =B47+C47+D47+E47+F47 -> 207616.68 | H47: ='Withdrawal Plan'!G14 -> 172572.6 | I47: ='Withdrawal Plan'!N14 -> 27737 | J47: ='Withdrawal Plan'!O14 -> 7672.8603 | K47: ='Withdrawal Plan'!P14 -> -365.77459
... A56: ='Withdrawal Plan'!A23 -> 85 | B56: ='Withdrawal Plan'!H23 -> 74339.573 | C56: ='Withdrawal Plan'!I23 -> 34515.842 | D56: ='Withdrawal Plan'!J23 -> 107861.36 | E56: ='Withdrawal Plan'!K23 -> 0 | F56: ='Withdrawal Plan'!L23 -> 0 | G56: =B56+C56+D56+E56+F56 -> 216716.78 | H56: ='Withdrawal Plan'!G23 -> 174103.66 | I56: ='Withdrawal Plan'!N23 -> 27737 | J56: ='Withdrawal Plan'!O23 -> 6870.7688 | K56: ='Withdrawal Plan'!P23 -> 8005.3444
A58: Age | B58: Bear 4% | C58: Base 8% | D58: Bull 10% | E58: Withdrawal Rate % | F58: 4% Guide
A59: ='Stress Test'!A4 -> 65 | B59: ='Stress Test'!C4 -> 9132439.1 | C59: ='Stress Test'!E4 -> 9490351 | D59: ='Stress Test'!F4 -> 9669306.9 | E59: =IFERROR(('Withdrawal Plan'!J3+'Withdrawal Plan'!K3+'Withdrawal Plan'!L3+'Withdrawal Plan'!M3)/Portfolio!H12*100,0) -> 2.8939404 | F59: 4
A60: ='Stress Test'!A5 -> 66 | B60: ='Stress Test'!C5 -> 9324355.7 | C60: ='Stress Test'!E5 -> 10076198 | D60: ='Stress Test'!F5 -> 10462857 | E60: =IFERROR(('Withdrawal Plan'!J4+'Withdrawal Plan'!K4+'Withdrawal Plan'!L4+'Withdrawal Plan'!M4)/Portfolio!H13*100,0) -> 2.8579467 | F60: 4
A61: ='Stress Test'!A6 -> 67 | B61: ='Stress Test'!C6 -> 9564346.7 | C61: ='Stress Test'!E6 -> 10749311 | D61: ='Stress Test'!F6 -> 11376159 | E61: =IFERROR(('Withdrawal Plan'!J5+'Withdrawal Plan'!K5+'Withdrawal Plan'!L5+'Withdrawal Plan'!M5)/Portfolio!H14*100,0) -> 2.1426973 | F61: 4
A62: ='Stress Test'!A7 -> 68 | B62: ='Stress Test'!C7 -> 9814827.9 | C62: ='Stress Test'!E7 -> 11477163 | D62: ='Stress Test'!F7 -> 12381682 | E62: =IFERROR(('Withdrawal Plan'!J6+'Withdrawal Plan'!K6+'Withdrawal Plan'!L6+'Withdrawal Plan'!M6)/Portfolio!H15*100,0) -> 2.0741342 | F62: 4
A63: ='Stress Test'!A8 -> 69 | B63: ='Stress Test'!C8 -> 10076238 | C63: ='Stress Test'!E8 -> 12264153 | D63: ='Stress Test'!F8 -> 13488668 | E63: =IFERROR(('Withdrawal Plan'!J7+'Withdrawal Plan'!K7+'Withdrawal Plan'!L7+'Withdrawal Plan'!M7)/Portfolio!H16*100,0) -> 2.0012525 | F63: 4
A64: ='Stress Test'!A9 -> 70 | B64: ='Stress Test'!C9 -> 10349034 | C64: ='Stress Test'!E9 -> 13115031 | D64: ='Stress Test'!F9 -> 14707281 | E64: =IFERROR(('Withdrawal Plan'!J8+'Withdrawal Plan'!K8+'Withdrawal Plan'!L8+'Withdrawal Plan'!M8)/Portfolio!H17*100,0) -> 1.9246542 | F64: 4
A65: ='Stress Test'!A10 -> 71 | B65: ='Stress Test'!C10 -> 10633690 | C65: ='Stress Test'!E10 -> 14034929 | D65: ='Stress Test'!F10 -> 16048704 | E65: =IFERROR(('Withdrawal Plan'!J9+'Withdrawal Plan'!K9+'Withdrawal Plan'!L9+'Withdrawal Plan'!M9)/Portfolio!H18*100,0) -> 1.8449966 | F65: 4
A66: ='Stress Test'!A11 -> 72 | B66: ='Stress Test'!C11 -> 10930703 | C66: ='Stress Test'!E11 -> 15029388 | D66: ='Stress Test'!F11 -> 17525239 | E66: =IFERROR(('Withdrawal Plan'!J10+'Withdrawal Plan'!K10+'Withdrawal Plan'!L10+'Withdrawal Plan'!M10)/Portfolio!H19*100,0) -> 1.7629741 | F66: 4
A67: ='Stress Test'!A12 -> 73 | B67: ='Stress Test'!C12 -> 11240585 | C67: ='Stress Test'!E12 -> 16104394 | D67: ='Stress Test'!F12 -> 19150417 | E67: =IFERROR(('Withdrawal Plan'!J11+'Withdrawal Plan'!K11+'Withdrawal Plan'!L11+'Withdrawal Plan'!M11)/Portfolio!H20*100,0) -> 1.6792983 | F67: 4
A68: ='Stress Test'!A13 -> 74 | B68: ='Stress Test'!C13 -> 11563873 | C68: ='Stress Test'!E13 -> 17266410 | D68: ='Stress Test'!F13 -> 20939124 | E68: =IFERROR(('Withdrawal Plan'!J12+'Withdrawal Plan'!K12+'Withdrawal Plan'!L12+'Withdrawal Plan'!M12)/Portfolio!H21*100,0) -> 1.5946792 | F68: 4
A69: ='Stress Test'!A14 -> 75 | B69: ='Stress Test'!C14 -> 11901125 | C69: ='Stress Test'!E14 -> 18522420 | D69: ='Stress Test'!F14 -> 22907733 | E69: =IFERROR(('Withdrawal Plan'!J13+'Withdrawal Plan'!K13+'Withdrawal Plan'!L13+'Withdrawal Plan'!M13)/Portfolio!H22*100,0) -> 1.5098071 | F69: 4
A70: ='Stress Test'!A15 -> 76 | B70: ='Stress Test'!C15 -> 12252920 | C70: ='Stress Test'!E15 -> 19879963 | D70: ='Stress Test'!F15 -> 25074256 | E70: =IFERROR(('Withdrawal Plan'!J14+'Withdrawal Plan'!K14+'Withdrawal Plan'!L14+'Withdrawal Plan'!M14)/Portfolio!H23*100,0) -> 1.425336 | F70: 4
... A79: ='Stress Test'!A24 -> 85 | B79: ='Stress Test'!C24 -> 16181651 | C79: ='Stress Test'!E24 -> 38251989 | D79: ='Stress Test'!F24 -> 57503621 | E79: =IFERROR(('Withdrawal Plan'!J23+'Withdrawal Plan'!K23+'Withdrawal Plan'!L23+'Withdrawal Plan'!M23)/Portfolio!H32*100,0) -> 0.76122581 | F79: 4
